Workbook

Sheet 2024 Balance Sheet
A1: Month | B1: Net Income (Matt) | C1: Comm Income (Matt) | D1: Net Income (Nicole)
A2: Jan | B2: ='CB - Jan 24'!B5 -> 5326.42 | C2: ='CB - Jan 24'!B4 -> 1843.01 | D2: ='CB - Jan 24'!B6 -> 3623.7
A3: Feb | B3: ='CB - Feb 24'!B5 -> 5326.42 | C3: ='CB - Feb 24'!B4 -> 924.67 | D3: ='CB - Feb 24'!B6 -> 3623.7
A4: Mar | B4: ='CB - Mar 24'!B5 -> 5669.42 | C4: ='CB - Mar 24'!B4 -> 1580.67 | D4: ='CB - Mar 24'!B6 -> 3623.7
A5: Apr | B5: ='CB - Apr 24'!B5 -> 5669.42 | C5: ='CB - Apr 24'!B4 -> 1915.94 | D5: ='CB - Apr 24'!B6 -> 3623.7
A6: May | B6: ='CB - May 24'!B5 -> 5669.42 | C6: ='CB - May 24'!B4 -> 739.74 | D6: ='CB - Mar 24'!B6 -> 3623.7
A7: Jun | B7: ='CB - Jun 24'!B5 -> 5669.42 | C7: ='CB - Jun 24'!B4 -> 0 | D7: ='CB - Jun 24'!B6 -> 3623.7
A8: Jul | B8: ='CB - Jul 24'!B5 -> 5669.42 | C8: ='CB - Jul 24'!B4 -> 0 | D8: ='CB - Jul 24'!B6 -> 3623.7
A9: Aug | B9: ='CB - Aug 24'!B5 -> 6224.56 | C9: ='CB - Aug 24'!B4 -> 0 | D9: ='CB - Aug 24'!B6 -> 4064.74
A10: Sep | B10: ='CB - Sep 24'!B5 -> 6224.56 | C10: ='CB - Sep 24'!B4 -> 0 | D10: ='CB - Sep 24'!B6 -> 4064.74
A11: Oct | B11: ='CB - Oct 24'!B5 -> 6222.56 | C11: ='CB - Oct 24'!B4 -> 0 | D11: ='CB - Oct 24'!B6 -> 4064
A12: Nov | B12: ='CB - Nov 24'!B5 -> 6222.56 | C12: ='CB - Nov 24'!B4 -> 0 | D12: ='CB - Nov 24'!B6 -> 4064
A13: Dec | B13: ='CB - Dec 24'!B5 -> 6222.56 | C13: ='CB - Dec 24'!B4 -> 0 | D13: ='CB - Dec 24'!B6 -> 4064
A15: Total | B15: =SUM(B2:B13) -> 70116.74 | C15: =SUM(C2:C13) -> 7004.03 | D15: =SUM(D2:D13) -> 45687.38 | E15: =SUM(A15:D15) -> 122808.15
A17: Matt
A18: Gross | B18: Base | C18: Comm | D18: Total
A19: Jan 1 - Feb 29 | B19: 89000 | C19: 20000 | D19: =SUM(B19:C19) -> 109000
A20: Mar 1 - Dec 31 | B20: 95000 | C20: 25000 | D20: =SUM(B20:C20) -> 120000
A22: Nicole
A23: Gross Salary | B23: Base | D23: Total
A24: Jan 1 - Dec 31 | B24: 60500 | D24: =SUM(B24:C24) -> 60500
D26: =SUM(D20+D24) -> 180500

Sheet 2024 Savings
A1: Month | B1: Emerg | C1: RRSP | D1: FHSA | E1: Savings | F1: Other
A2: January | B2: 0 | C2: 0 | D2: 0 | E2: 0
A3: February | B3: 0 | C3: 2500 | D3: 0 | E3: 0
A4: March | B4: 0 | C4: 50.08 | D4: 2500 | E4: 0
A5: April | B5: 0 | C5: 0 | D5: =3000 -> 3000 | E5: 0
A6: May | B6: 0 | C6: 0 | D6: 2500 | E6: 0
A7: June | B7: 0 | C7: 0 | D7: 0 | E7: 0
A8: July | B8: 0 | C8: 0 | D8: 0 | E8: 0
A9: August | B9: 0 | C9: 0 | D9: 0 | E9: 0
A10: September | B10: 0 | C10: 0 | D10: 0 | E10: 0
A11: October | B11: 0 | C11: 0 | D11: 0 | E11: 0
A12: November | B12: 0 | C12: 0 | D12: 0 | E12: 0
A13: December | B13: 0 | C13: 0 | D13: 0 | E13: 0
A17: Total: | B17: =SUM(B4:B13) -> 0 | C17: =SUM(C4:C13) -> 50.08 | D17: =SUM(D4:D13) -> 8000 | E17: =SUM(E4:E13) -> 0
A19: RRSP | B19: Limits | C19: Contributions | D19: Remainder
A20: Matt | C20: =50.08 -> 50.08
A21: Nicole
A23: FHSA Limits
A24: Matt | B24: 8000 | C24: =D17 -> 8000 | D24: =B24-C24 -> 0
A25: Nicole | B25: 8000 | C25: 8000 | D25: =B25-C25 -> 0
A28: HOLDINGS
A29: RRSP
A30: TFSA
A31: FHSA
A32: Savings Acct
A34: Total:

Sheet 2024 Expenses
A1: Month | B1: Matt Rent | C1: Matt Hydro | D1: Matt Gas | E1: Matt Internet | F1: Nicole Rent | G1: Nicole Hydro | H1: Nicole Gas | I1: Nicole Internet
A2: January | B2: ='CB - Jan 24'!C10 -> 1428.2946 | C2: ='CB - Jan 24'!C16 -> 92.041684 | D2: ='CB - Jan 24'!C15 -> 106.74122 | E2: ='CB - Jan 24'!C12 -> 59.179006 | F2: ='CB - Jan 24'!D10 -> 971.70541 | G2: ='CB - Jan 24'!D16 -> 62.618316 | H2: ='CB - Jan 24'!D15 -> 72.618784 | I2: ='CB - Jan 24'!D12 -> 40.260994
A3: February | B3: ='CB - Feb 24'!C10 -> 1428.2946 | C3: ='CB - Feb 24'!C16 -> 89.125583 | D3: ='CB - Feb 24'!C15 -> 42.640545 | E3: ='CB - Feb 24'!C12 -> 61.868961 | F3: ='CB - Feb 24'!D10 -> 971.70541 | G3: ='CB - Feb 24'!D16 -> 60.634417 | H3: ='CB - Feb 24'!D15 -> 29.009455 | I3: ='CB - Feb 24'!D12 -> 42.091039
A4: March | B4: ='CB - Mar 24'!C10 -> 1464.1593 | C4: ='CB - Mar 24'!C16 -> 90.271521 | D4: ='CB - Mar 24'!C15 -> 63.465205 | E4: ='CB - Mar 24'!C12 -> 63.4225 | F4: ='CB - Mar 24'!D10 -> 935.84071 | G4: ='CB - Mar 24'!D16 -> 57.698479 | H4: ='CB - Mar 24'!D15 -> 40.564795 | I4: ='CB - Mar 24'!D12 -> 40.5375
A5: April | B5: ='CB - Apr 24'!C10 -> 1464.1593 | C5: ='CB - Apr 24'!C16 -> 84.359978 | D5: ='CB - Apr 24'!C15 -> 59.701095 | E5: ='CB - Apr 24'!C12 -> 57.047306 | F5: ='CB - Apr 24'!D10 -> 935.84071 | G5: ='CB - Apr 24'!D16 -> 53.920022 | H5: ='CB - Apr 24'!D15 -> 38.158905 | I5: ='CB - Apr 24'!D12 -> 36.462694
A6: May | B6: ='CB - May 24'!C10 -> 1464.1593 | C6: ='CB - May 24'!C16 -> 77.58214 | D6: ='CB - May 24'!C15 -> 33.382832 | E6: ='CB - May 24'!C12 -> 57.047306 | F6: ='CB - May 24'!D10 -> 935.84071 | G6: ='CB - May 24'!D16 -> 49.58786 | H6: ='CB - May 24'!D15 -> 21.337168 | I6: ='CB - May 24'!D12 -> 36.462694
A7: June | B7: ='CB - Jun 24'!C10 -> 1464.1593 | C7: ='CB - Jun 24'!D16 -> 62.943086 | D7: ='CB - Jun 24'!C15 -> 26.861222 | E7: ='CB - Jun 24'!C12 -> 57.047306 | F7: ='CB - Jun 24'!D10 -> 935.84071 | G7: ='CB - Jun 24'!D16 -> 62.943086 | H7: ='CB - Jun 24'!D15 -> 17.168778 | I7: ='CB - Jun 24'!D12 -> 36.462694
A8: July | B8: ='CB - Jul 24'!C10 -> 1464.1593 | C8: ='CB - Jul 24'!C16 -> 130.46269 | D8: ='CB - Jul 24'!C15 -> 23.859696 | E8: ='CB - Jul 24'!C12 -> 57.047306 | F8: ='CB - Jul 24'!D10 -> 935.84071 | G8: ='CB - Jul 24'!D16 -> 83.387306 | H8: ='CB - Jul 24'!D15 -> 15.250304 | I8: ='CB - Jul 24'!D12 -> 36.462694
A9: August | B9: ='CB - Aug 24'!C10 -> 1035.2529 | C9: ='CB - Aug 24'!C16 -> 146.48977 | D9: ='CB - Aug 24'!C15 -> 23.714223 | E9: ='CB - Aug 24'!C12 -> 56.56931 | F9: ='CB - Aug 24'!D10 -> 676.03714 | G9: ='CB - Aug 24'!D16 -> 95.660229 | H9: ='CB - Aug 24'!D15 -> 15.485777 | I9: ='CB - Aug 24'!D12 -> 36.94069
A10: September | B10: =0 -> 0 | C10: ='CB - Sep 24'!C17 -> 130.0834 | D10: ='CB - Sep 24'!C16 -> 23.714223 | E10: ='CB - Sep 24'!C13 -> 56.56931 | F10: =0 -> 0 | G10: ='CB - Sep 24'!D17 -> 84.946599 | H10: ='CB - Sep 24'!D16 -> 15.485777 | I10: ='CB - Sep 24'!D13 -> 36.94069
A11: October | B11: =0 -> 0 | C11: ='CB - Oct 24'!C17 -> 91.875458 | D11: ='CB - Oct 24'!C16 -> 24.360184 | E11: ='CB - Oct 24'!C13 -> 56.566198 | F11: =0 -> 0 | G11: ='CB - Oct 24'!D17 -> 60.004542 | H11: ='CB - Oct 24'!D16 -> 15.909816 | I11: ='CB - Oct 24'!D13 -> 36.943802
A12: November | B12: =0 -> 0 | C12: ='CB - Nov 24'!C17 -> 182.54712 | D12: ='CB - Nov 24'!C16 -> 27.033936 | E12: ='CB - Nov 24'!C13 -> 56.566198 | F12: =0 -> 0 | G12: ='CB - Nov 24'!D17 -> 119.22288 | H12: ='CB - Nov 24'!D16 -> 17.656064 | I12: ='CB - Nov 24'!D13 -> 36.943802
A13: December | B13: =0 -> 0 | C13: ='CB - Dec 24'!C17 -> 124.33554 | D13: ='CB - Dec 24'!C16 -> 43.0825 | E13: ='CB - Dec 24'!C13 -> 56.566198 | F13: =0 -> 0 | G13: ='CB - Dec 24'!D17 -> 81.204461 | H13: ='CB - Dec 24'!D16 -> 28.1375 | I13: ='CB - Dec 24'!D13 -> 36.943802
A15: Total: | B15: =SUM(B4:B13) -> 8356.0493 | C15: =SUM(C4:C13) -> 1120.9507 | D15: =SUM(D4:D13) -> 349.17512 | E15: =SUM(E4:E13) -> 574.44894 | F15: =SUM(F2:F13) -> 7298.6515 | G15: =SUM(G4:G13) -> 748.57546 | H15: =SUM(H4:H13) -> 225.15488 | I15: =SUM(I4:I13) -> 371.10106
A16: Average: | C16: =AVERAGE(C2:C9) -> 96.659557 | G16: =AVERAGE(G2:G9) -> 65.806214
D17: =SUM(C15:E15) -> 2044.5748 | H17: =SUM(G15:I15) -> 1344.8314
A19: Total Hydro: (Jan-Aug) | C19: =SUM(C2:C9) -> 773.27646 | D19: =SUM(G2:G9) -> 526.44972 | E19: =C19+D19 -> 1299.7262
A20: Total Gas: (Jan-Aug) | C20: =SUM(D2:D9) -> 380.36603 | D20: =SUM(H2:H9) -> 249.59397 | E20: =C20+D20 -> 629.96
A21: Total Internet: (Jan Aug) | C21: =SUM(E2:E9) -> 469.229 | D21: =SUM(I2:I9) -> 305.681 | E21: =C21+D21 -> 774.91
C22: =SUM(C19:C21) -> 1622.8715 | D22: =SUM(D19:D21) -> 1081.7247 | E22: =SUM(E19:E21) -> 2704.5962
A24: Total hydro: (Sept-Dec) | C24: =SUM(C10:C13) -> 528.84152 | D24: =SUM(G10:G13) -> 345.37848 | E24: =SUM(C24:D24) -> 874.22
A25: Total Gas | C25: =SUM(D10:D13) -> 118.19084 | D25: =SUM(H10:H13) -> 77.189157 | E25: =SUM(C25:D25) -> 195.38
A26: Total Internet | C26: =SUM(E10:E13) -> 226.2679 | D26: =SUM(I10:I13) -> 147.7721 | E26: =SUM(C26:D26) -> 374.04
C27: =SUM(C24:C26) -> 873.30027 | D27: =SUM(D24:D26) -> 570.33973 | E27: =SUM(E24:E26) -> 1443.64
A28: Total Rent: | B28: =B15+F15 -> 15654.701
A29: Total Home Insurance: | B29: 1306.7

Sheet 2024 CC - Categories
A1: CATEGORY | B1: SUM | C1: AVG | D1: JAN | E1: FEB | F1: MAR | G1: APR | H1: MAY | I1: JUN | J1: JUL | K1: AUG | L1: SEP | M1: OCT | N1: NOV | O1: DEC | P1: JAN | Q1: FEB
A2: ALCOHOL | B2: =SUM(D2:O2) -> 1430.24 | C2: =AVERAGE(D2:G2) -> 114.21 | D2: ='CC - Jan 24'!H7 -> 163.07 | E2: ='CC - Feb 24'!H7 -> 43.31 | F2: ='CC - Mar 24'!H7 -> 175.91 | G2: ='CC - Apr 24'!H7 -> 74.55 | H2: ='CC - May 24'!H7 -> 0 | I2: ='CC - Jun 24'!H7 -> 160.35 | J2: ='CC - Jul 24'!H7 -> 50 | K2: ='CC - Aug 23'!H7 -> 325.62 | L2: ='CC - Sep 23'!H7 -> 437.43 | M2: ='CC - Oct 23'!H7 -> 0 | N2: ='CC - Nov 23'!J6 -> 0 | O2: ='CC - Dec 23'!J6 -> 0
A3: CANNABIS | B3: =SUM(D3:O3) -> 844.48 | C3: =AVERAGE(D3:G3) -> 89.0075 | D3: ='CC - Jan 24'!H8 -> 106.03 | E3: 0 | F3: 0 | G3: ='CC - Apr 24'!H8 -> 250 | H3: 0 | I3: ='CC - Jun 24'!H8 -> 250 | J3: ='CC - Jul 24'!H8 -> 238.45 | K3: =0 -> 0 | L3: =0 -> 0 | M3: ='CC - Oct 23'!H8 -> 0 | N3: =0 -> 0 | O3: =0 -> 0
A4: CC FEES | B4: =SUM(D4:O4) -> 50 | C4: =AVERAGE(D4:G4) -> 0 | D4: 0 | E4: 0 | F4: 0 | G4: 0 | H4: 0 | I4: 0 | J4: 0 | K4: ='CC - Aug 23'!H9 -> 50 | L4: =0 -> 0 | M4: =0 -> 0 | N4: =0 -> 0 | O4: =0 -> 0
A5: CHARITY | B5: =SUM(D5:O5) -> 1445.94 | C5: =AVERAGE(D5:G5) -> 250 | D5: ='CC - Jan 24'!H9 -> 250 | E5: ='CC - Feb 24'!H8 -> 250 | F5: ='CC - Mar 24'!H8 -> 250 | G5: ='CC - Apr 24'!H8 -> 250 | H5: ='CC - May 24'!H8 -> 112.42 | I5: ='CC - Jun 24'!H9 -> 232.39 | J5: ='CC - Jul 24'!H10 -> 64.27 | K5: ='CC - Aug 23'!H10 -> -35 | L5: ='CC - Sep 23'!H9 -> 71.86 | M5: ='CC - Oct 23'!H10 -> 0 | N5: ='CC - Nov 23'!J9 -> 0 | O5: ='CC - Dec 23'!J7 -> 0
A6: CLOTHES | B6: =SUM(D6:O6) -> 641.27 | C6: =AVERAGE(D6:G6) -> 84.4675 | D6: ='CC - Jan 24'!H10 -> 337.87 | E6: =0 -> 0 | F6: =0 -> 0 | G6: 0 | H6: ='CC - May 24'!H10 -> 153 | I6: 0 | J6: ='CC - Jul 24'!H11 -> 150.4 | K6: =0 -> 0 | L6: =0 -> 0 | M6: =0 -> 0 | N6: =0 -> 0 | O6: =0 -> 0
A7: COFFEE | B7: =SUM(D7:O7) -> 511.24 | C7: =AVERAGE(D7:G7) -> 5.41 | D7: ='CC - Jan 24'!H11 -> 4.08 | E7: ='CC - Feb 24'!H9 -> 4.15 | F7: =0 -> 0 | G7: ='CC - Apr 24'!H9 -> 13.41 | H7: ='CC - May 24'!H10 -> 153 | I7: ='CC - Jun 24'!H10 -> 130 | J7: =0 -> 0 | K7: ='CC - Aug 23'!H11 -> 14.77 | L7: ='CC - Sep 23'!H10 -> 191.83 | M7: ='CC - Oct 23'!H11 -> 0 | N7: ='CC - Nov 23'!J10 -> 0 | O7: ='CC - Dec 23'!J8 -> 0
A8: DELIVERY | B8: =SUM(D8:O8) -> 110.9 | C8: =AVERAGE(D8:G8) -> 5.27 | D8: ='CC - Jan 24'!H12 -> 21.08 | E8: =0 -> 0 | F8: =0 -> 0 | G8: =0 -> 0 | H8: =0 -> 0 | I8: =0 -> 0 | J8: ='CC - Jul 24'!H12 -> 89.82 | K8: =0 -> 0 | L8: =0 -> 0 | M8: ='CC - Oct 23'!H12 -> 0 | N8: =0 -> 0 | O8: =0 -> 0
A9: DINE IN | B9: =SUM(D9:O9) -> 2013.51 | C9: =AVERAGE(D9:G9) -> 123.875 | D9: ='CC - Jan 24'!H13 -> 436.15 | E9: =0 -> 0 | F9: =0 -> 0 | G9: ='CC - Apr 24'!H10 -> 59.35 | H9: ='CC - May 24'!H11 -> 517.75 | I9: ='CC - Jun 24'!H11 -> 577.19 | J9: ='CC - Jul 24'!H13 -> 184.13 | K9: ='CC - Aug 23'!H12 -> 158.83 | L9: ='CC - Sep 23'!H11 -> 80.11 | M9: ='CC - Oct 23'!H13 -> 0 | N9: ='CC - Nov 23'!J11 -> 0 | O9: ='CC - Dec 23'!J9 -> 0
A10: ENTERTAINMENT | B10: =SUM(D10:O10) -> 1149.36 | C10: =AVERAGE(D10:G10) -> 153.8525 | D10: ='CC - Jan 24'!H15 -> 36.97 | E10: ='CC - Feb 24'!H11 -> 157.97 | F10: ='CC - Mar 24'!H13 -> 27.78 | G10: ='CC - Apr 24'!H13 -> 392.69 | H10: ='CC - May 24'!H13 -> 271.06 | I10: ='CC - Jun 24'!H13 -> 33.08 | J10: ='CC - Jul 24'!H14 -> 51.28 | K10: ='CC - Aug 23'!H13 -> 74.26 | L10: ='CC - Sep 23'!H12 -> 104.27 | M10: ='CC - Oct 23'!H14 -> 0 | N10: ='CC - Nov 23'!J12 -> 0 | O10: ='CC - Dec 23'!J10 -> 0
A11: FURNITURE | B11: =SUM(D11:O11) -> 127.96 | C11: =AVERAGE(D11:G11) -> 31.99 | D11: 0 | E11: ='CC - Feb 24'!H12 -> 127.96 | F11: 0 | G11: 0 | H11: =0 -> 0 | I11: =0 -> 0 | J11: =0 -> 0 | K11: =0 -> 0 | L11: =0 -> 0 | M11: =0 -> 0 | N11: =0 -> 0 | O11: =0 -> 0
A12: FLIGHTS | B12: =SUM(D12:O12) -> 393.8 | C12: =AVERAGE(D12:G12) -> 98.45 | D12: ='CC - Jan 24'!H16 -> 393.8 | E12: 0 | F12: 0 | G12: 0 | H12: =0 -> 0 | I12: =0 -> 0 | J12: =0 -> 0 | K12: =0 -> 0 | L12: =0 -> 0 | M12: =0 -> 0 | N12: =0 -> 0 | O12: =0 -> 0
A13: GAS | B13: =SUM(D13:O13) -> 5803.32 | C13: =AVERAGE(D13:G13) -> 111.0425 | D13: ='CC - Jan 24'!H17 -> 236.16 | E13: ='CC - Feb 24'!H13 -> 90.95 | F13: ='CC - Mar 24'!H14 -> 0 | G13: ='CC - Apr 24'!H14 -> 117.06 | H13: ='CC - May 24'!H14 -> 4301.46 | I13: ='CC - Jun 24'!H14 -> 64.12 | J13: ='CC - Jul 24'!H15 -> 527.75 | K13: ='CC - Aug 23'!H14 -> 164.95 | L13: ='CC - Sep 23'!H13 -> 300.87 | M13: ='CC - Oct 23'!H15 -> 0 | N13: ='CC - Nov 23'!J13 -> 0 | O13: ='CC - Dec 23'!J11 -> 0
A14: GIFTS | B14: =SUM(D14:O14) -> 2329.54 | C14: =AVERAGE(D14:G14) -> 278.4 | D14: ='CC - Jan 24'!H18 -> 907.22 | E14: ='CC - Feb 24'!H14 -> 54.19 | F14: ='CC - Mar 24'!H15 -> 103.96 | G14: ='CC - Apr 24'!H15 -> 48.23 | H14: ='CC - May 24'!H15 -> 433.55 | I14: ='CC - Jun 24'!H15 -> 370.64 | J14: ='CC - Jul 24'!H16 -> 90.39 | K14: ='CC - Aug 23'!H15 -> 305.56 | L14: ='CC - Sep 23'!H14 -> 15.8 | M14: =0 -> 0 | N14: ='CC - Nov 23'!J14 -> 0 | O14: ='CC - Dec 23'!J12 -> 0
A15: GROCERIES | B15: =SUM(D15:O15) -> 7315.81 | C15: =AVERAGE(D15:G15) -> 272.0475 | D15: ='CC - Jan 24'!H16 -> 393.8 | E15: ='CC - Feb 24'!H12 -> 127.96 | F15: ='CC - Mar 24'!H12 -> 173.74 | G15: ='CC - Apr 24'!H13 -> 392.69 | H15: ='CC - May 24'!H16 -> 90.39 | I15: ='CC - Jun 24'!H16 -> 335.24 | J15: ='CC - Jul 24'!H17 -> 195.5 | K15: ='CC - Aug 23'!H16 -> 3423.58 | L15: ='CC - Sep 23'!H15 -> 2182.91 | M15: ='CC - Oct 23'!H16 -> 0 | N15: ='CC - Nov 23'!J15 -> 0 | O15: ='CC - Dec 23'!J13 -> 0
A16: HEALTH | B16: =SUM(D16:O16) -> 580.45 | C16: =AVERAGE(D16:G16) -> 58.48 | D16: ='CC - Jan 24'!H20 -> 99.44 | E16: ='CC - Feb 24'!H16 -> 134.48 | F16: 0 | G16: 0 | H16: ='CC - May 24'!H17 -> 169.17 | I16: ='CC - Jun 24'!H17 -> 116.06 | J16: ='CC - Jul 24'!H18 -> 8.99 | K16: 0 | L16: ='CC - Sep 23'!H16 -> 52.31 | M16: =0 -> 0 | N16: ='CC - Nov 23'!J16 -> 0 | O16: ='CC - Dec 23'!J14 -> 0
A17: HOTEL | B17: =SUM(D17:O17) -> 3469.48 | C17: =AVERAGE(D17:G17) -> 54.525 | D17: 0 | E17: 0 | F17: 0 | G17: ='CC - Apr 24'!H17 -> 218.1 | H17: ='CC - May 24'!H18 -> 8.99 | I17: ='CC - Jun 24'!H18 -> 68.02 | J17: =0 -> 0 | K17: ='CC - Aug 23'!H17 -> 3174.37 | L17: =0 -> 0 | M17: =0 -> 0 | N17: =0 -> 0 | O17: ='CC - Dec 23'!J15 -> 0
A18: HOUSEHOLD | B18: =SUM(D18:O18) -> 602.48 | C18: =AVERAGE(D18:G18) -> 66.4825 | D18: ='CC - Jan 24'!H21 -> 151.43 | E18: ='CC - Feb 24'!H17 -> 8.99 | F18: ='CC - Mar 24'!H17 -> 87.53 | G18: ='CC - Apr 24'!H18 -> 17.98 | H18: 0 | I18: ='CC - Jun 24'!H19 -> 90.39 | J18: ='CC - Jul 24'!H19 -> 10 | K18: ='CC - Aug 23'!H18 -> 90.39 | L18: ='CC - Sep 23'!H17 -> 145.77 | M18: ='CC - Oct 23'!H17 -> 0 | N18: ='CC - Nov 23'!J17 -> 0 | O18: ='CC - Dec 23'!J16 -> 0
A19: INTERNET | B19: =SUM(D19:O19) -> 1038.93 | C19: =AVERAGE(D19:G19) -> 124.475 | D19: ='CC - Jan 24'!H20 -> 99.44 | E19: ='CC - Feb 24'!H15 -> 103.96 | F19: ='CC - Mar 24'!H15 -> 103.96 | G19: ='CC - Apr 24'!H16 -> 190.54 | H19: ='CC - May 24'!H19 -> 4.2 | I19: 0 | J19: =0 -> 0 | K19: ='CC - Aug 23'!H19 -> 127.7 | L19: ='CC - Sep 23'!H18 -> 409.13 | M19: ='CC - Oct 23'!H18 -> 0 | N19: ='CC - Nov 23'!J18 -> 0 | O19: ='CC - Dec 23'!J17 -> 0
A20: MOBILE | B20: =SUM(D20:O20) -> -15660.67 | C20: =AVERAGE(D20:G20) -> 160.7525 | D20: ='CC - Jan 24'!H21 -> 151.43 | E20: ='CC - Feb 24'!H16 -> 134.48 | F20: ='CC - Mar 24'!H16 -> 139 | G20: ='CC - Apr 24'!H17 -> 218.1 | H20: ='CC - May 24'!H20 -> -3290.12 | I20: 0 | J20: ='CC - Jul 24'!H20 -> -13066.61 | K20: ='CC - Aug 23'!H20 -> 36.11 | L20: ='CC - Sep 23'!H19 -> 16.94 | M20: ='CC - Oct 23'!H19 -> 0 | N20: ='CC - Nov 23'!J19 -> 0 | O20: ='CC - Dec 23'!J18 -> 0
A21: NEWSPAPER | B21: =SUM(D21:O21) -> 2733.13 | C21: =AVERAGE(D21:G21) -> 474.0775 | D21: ='CC - Jan 24'!H23 -> 136.41 | E21: 0 | F21: 0 | G21: ='CC - Apr 24'!H20 -> 1759.9 | H21: 0 | I21: 0 | J21: ='CC - Jul 24'!H21 -> 822.53 | K21: ='CC - Aug 23'!H21 -> 3 | L21: ='CC - Sep 23'!H20 -> 11.29 | M21: ='CC - Oct 23'!H20 -> 0 | N21: ='CC - Nov 23'!J20 -> 0 | O21: ='CC - Dec 23'!J19 -> 0
A22: PARKING | B22: =SUM(D22:O22) -> 353.38 | C22: =AVERAGE(D22:G22) -> 7.9 | D22: 0 | E22: ='CC - Feb 24'!H21 -> 31.6 | F22: 0 | G22: 0 | H22: ='CC - May 24'!H22 -> 51.92 | I22: 0 | J22: ='CC - Jul 24'!H23 -> 269.86 | K22: =0 -> 0 | L22: =0 -> 0 | M22: ='CC - Oct 23'!H21 -> 0 | N22: =0 -> 0 | O22: =0 -> 0
A23: PETS | B23: =SUM(D23:O23) -> 3535.94 | C23: =AVERAGE(D23:G23) -> 1474.4425 | D23: ='CC - Jan 24'!H25 -> 506.24 | E23: ='CC - Feb 24'!H20 -> 3207.25 | F23: ='CC - Mar 24'!H20 -> 424.38 | G23: ='CC - Apr 24'!H20 -> 1759.9 | H23: ='CC - May 24'!H21 -> 676.3 | I23: ='CC - Jun 24'!H20 -> 229.4 | J23: ='CC - Jul 24'!H22 -> 91.45 | K23: ='CC - Aug 23'!H22 -> -3408.98 | L23: ='CC - Sep 23'!H21 -> 50 | M23: =0 -> 0 | N23: =0 -> 0 | O23: =0 -> 0
A24: SUBSCRIPTIONS | B24: =SUM(D24:O24) -> 769.22 | C24: =AVERAGE(D24:G24) -> 48.9325 | D24: ='CC - Jan 24'!H26 -> 62.55 | E24: ='CC - Feb 24'!H21 -> 31.6 | F24: ='CC - Mar 24'!H21 -> 50.79 | G24: ='CC - Apr 24'!H21 -> 50.79 | H24: ='CC - May 24'!H24 -> 93.72 | I24: ='CC - Jun 24'!H22 -> 124 | J24: ='CC - Jul 24'!H25 -> 100.14 | K24: ='CC - Aug 23'!H24 -> 16.94 | L24: ='CC - Sep 23'!H23 -> 238.69 | M24: ='CC - Oct 23'!H23 -> 0 | N24: ='CC - Nov 23'!J22 -> 0 | O24: ='CC - Dec 23'!J21 -> 0
A25: TAKEOUT | B25: =SUM(D25:O25) -> -7847.24 | C25: =AVERAGE(D25:G25) -> 312.63 | D25: ='CC - Jan 24'!H27 -> 258.51 | E25: ='CC - Feb 24'!H22 -> 295.45 | F25: ='CC - Mar 24'!H22 -> 295.54 | G25: ='CC - Apr 24'!H22 -> 401.02 | H25: ='CC - May 24'!H25 -> 4394.9 | I25: ='CC - Jun 24'!H23 -> -9606.07 | J25: ='CC - Jul 24'!H26 -> -9420.74 | K25: ='CC - Aug 23'!H26 -> 286.38 | L25: ='CC - Sep 23'!H25 -> 5247.77 | M25: ='CC - Oct 23'!H24 -> 0 | N25: ='CC - Nov 23'!J24 -> 0 | O25: ='CC - Dec 23'!J23 -> 0
A26: TECHNOLOGY | B26: =SUM(D26:O26) -> 4254.09 | C26: =AVERAGE(D26:G26) -> 75.5325 | D26: ='CC - Jan 24'!H28 -> 33.88 | E26: ='CC - Feb 24'!H23 -> 64.82 | F26: ='CC - Mar 24'!H23 -> 157.8 | G26: ='CC - Apr 24'!H23 -> 45.63 | H26: ='CC - May 24'!H26 | I26: ='CC - Jun 24'!H24 -> 3828.7 | J26: ='CC - Jul 24'!H27 | K26: ='CC - Aug 23'!H27 -> 123.26 | L26: ='CC - Sep 23'!H26 | M26: ='CC - Oct 23'!H25 -> 0 | N26: ='CC - Nov 23'!J25 -> 0 | O26: ='CC - Dec 23'!J24 -> 0
A27: TRANSPORTATION | B27: =SUM(D27:O27) -> 7493.72 | C27: =AVERAGE(D27:G27) -> 239.58 | D27: ='CC - Jan 24'!H29 -> 135.43 | E27: ='CC - Feb 24'!H24 -> 297.06 | F27: ='CC - Mar 24'!H24 -> 118.65 | G27: ='CC - Apr 24'!H24 -> 407.18 | H27: ='CC - May 24'!H27 | I27: ='CC - Jun 24'!H25 -> 76.77 | J27: ='CC - Jul 24'!H28 | K27: ='CC - Aug 23'!H28 -> 6458.63 | L27: ='CC - Sep 23'!H27 | M27: ='CC - Oct 23'!H26 -> 0 | N27: ='CC - Nov 23'!J26 -> 0 | O27: ='CC - Dec 23'!J25 -> 0
C29: =SUM(C2:C27) -> 4715.8325
A30: Total | B30: =SUM(B2:B27) -> 25490.28

Sheet CB - Jan 24
A1: Month: | B1: Jan
A3: Income:
A4: Matt Comm | B4: 1843.01
A5: Matt | B5: =2663.21*2 -> 5326.42 | C5: =B5/B7 -> 0.59512275
A6: Nicole | B6: =1811.85*2 -> 3623.7 | C6: =B6/B7 -> 0.40487725
A7: Subtotal: | B7: =SUM(B5:B6) -> 8950.12
A9: Shared Expenses: | C9: Matt | D9: Nicole
A10: Rent | B10: =2400 -> 2400 | C10: =B10*C5 -> 1428.2946 | D10: =B10*C6 -> 971.70541 | E10: PAID
A11: Insurance | B11: =165.71 -> 165.71 | C11: =B11*C5 -> 98.61779 | D11: =B11*C6 -> 67.09221 | E11: PAID
A12: Internet | B12: 99.44 | C12: =B12*C5 -> 59.179006 | D12: =B12*C6 -> 40.260994 | E12: PAID
A13: Pet Insurance | B13: 81.46 | C13: =B13*C5 -> 48.478699 | D13: =B13*C6 -> 32.981301 | E13: PAID
A14: Cell Phones | B14: 134.48 | C14: =B14*C5 -> 80.032107 | D14: =B14*C6 -> 54.447893 | E14: PAID
A15: Enbridge | B15: =179.36 -> 179.36 | C15: =B15*C5 -> 106.74122 | D15: =B15*C6 -> 72.618784 | E15: PAID
A16: London Hydro | B16: 154.66 | C16: =B16*C5 -> 92.041684 | D16: =B16*C6 -> 62.618316 | E16: PAID
A18: Sub | B18: =Sum(B10:B16) -> 3215.11 | C18: =Sum(C10:C16) -> 1913.3851 | D18: =Sum(D10:D16) -> 1301.7249
A20: Shared Savings (25%) | E20: Total
A21: Savings (25%) | B21: =B7*0.25 -> 2237.53 | C21: =B21*C5 -> 1331.605 | D21: =B21*C6 -> 905.925 | E21: =SUM(C21:D21) -> 2237.53
A23: Sub | B23: =B18+B21 -> 5452.64 | C23: =C18+C21 -> 3244.9901 | D23: =D18+D21 -> 2207.6499
A25: Deposit to Personal Accts | C25: =B5-C23 -> 2081.4299 | D25: =B6-D23 -> 1416.0501
A26: 45306 | C26: =C25/2 -> 1040.715 | D26: =D25/2 -> 708.02505
A27: 45321 | C27: =C25/2 -> 1040.715 | D27: =D25/2 -> 708.02505
A30: Other Stuff | B30: Amount | C30: Due Date | D30: Status
A31: AMEX Bill | B31: ='CC - Jan 24'!F3 -> 4198.26 | C31: ='CC - Jan 24'!F4 -> 45336
A32: VISA Bill | B32: ='CC - Jan 24'!B3 -> 578.38 | C32: ='CC - Jan 24'!B4 -> 45336 | D32: Paid
A33: MASTER Bill | B33: =0 -> 0

Sheet CC - Jan 24
A1: VISA INFINITE STATEMENT | D1: AMEX STATEMENT
A2: DATE: | B2: 45314 | D2: DATE: | F2: 45315
A3: AMOUNT: | B3: 578.38 | D3: AMOUNT: | F3: 4198.26
A4: DUE DATE: | B4: 45336 | D4: DUE DATE: | F4: 45336
B6: ITEM | C6: DATE | D6: CHARGE | E6: CATEGORY
B7: CDN TIRE STORE 00394300 WOODSTOCK | C7: 45283 | D7: 90.98 | E7: HOUSEHOLD
B8: ESSO CIRCLE K 0302 MARKHAM | C8: 45285 | D8: 62.25 | E8: GAS
B9: FIDO MOBILE ******6643 888-481-3436 | C9: 45285 | D9: 151.43 | E9: MOBILE
B10: WW CANADA LTD 866-323-4411 | C10: 45286 | D10: 13.56 | E10: HEALTH
B11: FIDO HOME ******5135 888-481-3436 | C11: 45287 | D11: 99.44 | E11: INTERNET
B12: SKIPTHEDISHES WINNIPEG | C12: 45287 | D12: 21.08 | E12: DELIVERY
B13: FRESHCO #9863 LONDON LONDON | C13: 45288 | D13: 136.12 | E13: GROCERIES
B14: LCBO/RAO #0192 LONDON LONDON | C14: 45288 | D14: 41.9 | E14: ALCOHOL
B15: CLEARLY Clearly VANCOUVER | C15: 45289 | D15: 210.77 | E15: HEALTH
B16: PAYMENT RECEIVED - THANK YOU | C16: 45289 | D16: -3646.85 | E16: PAYMENT
B17: SHELL C02231 LONDON | C17: 45290 | D17: 54.12 | E17: GAS
B18: AMAZON CHANNELS AMAZON.CA | C18: 45291 | D18: 5.64 | E18: SUBSCRIPTIONS
... B81: SESSIONS CANNABIS | C81: 45282 | D81: 26 | E81: CANNABIS

Sheet CB - Feb 24
A1: Month: | B1: Feb
A3: Income:
A4: Matt Comm | B4: 924.67
A5: Matt | B5: =2663.21*2 -> 5326.42 | C5: =B5/B7 -> 0.59512275
A6: Nicole | B6: =1811.85*2 -> 3623.7 | C6: =B6/B7 -> 0.40487725
A7: Subtotal: | B7: =SUM(B5:B6) -> 8950.12
A9: Shared Expenses: | C9: Matt | D9: Nicole
A10: Rent | B10: =2400 -> 2400 | C10: =B10*C5 -> 1428.2946 | D10: =B10*C6 -> 971.70541 | E10: PAID
A11: Insurance | B11: =175.45 -> 175.45 | C11: =B11*C5 -> 104.41429 | D11: =B11*C6 -> 71.035714 | E11: PAID
A12: Internet | B12: 103.96 | C12: =B12*C5 -> 61.868961 | D12: =B12*C6 -> 42.091039 | E12: PAID
A13: Pet Insurance | B13: 81.46 | C13: =B13*C5 -> 48.478699 | D13: =B13*C6 -> 32.981301 | E13: PAID
A14: Cell Phones | B14: 134.48 | C14: =B14*C5 -> 80.032107 | D14: =B14*C6 -> 54.447893 | E14: PAID
A15: Enbridge | B15: 71.65 | C15: =B15*C5 -> 42.640545 | D15: =B15*C6 -> 29.009455 | E15: PAID
A16: London Hydro | B16: 149.76 | C16: =B16*C5 -> 89.125583 | D16: =B16*C6 -> 60.634417 | E16: PAID
A18: Sub | B18: =Sum(B10:B16) -> 3116.76 | C18: =Sum(C10:C16) -> 1854.8548 | D18: =Sum(D10:D16) -> 1261.9052
A20: Shared Savings (25%) | E20: Total
A21: Savings (25%) | B21: =B7*0.25 -> 2237.53 | C21: =B21*C5 -> 1331.605 | D21: =B21*C6 -> 905.925 | E21: =SUM(C21:D21) -> 2237.53
A23: Sub | B23: =B18+B21 -> 5354.29 | C23: =C18+C21 -> 3186.4598 | D23: =D18+D21 -> 2167.8302
A25: Deposit to Personal Accts | C25: =B5-C23 -> 2139.9602 | D25: =B6-D23 -> 1455.8698
A26: 45337 | C26: =C25/2 -> 1069.9801 | D26: =D25/2 -> 727.93489
A27: 45351 | C27: =C25/2 -> 1069.9801 | D27: =D25/2 -> 727.93489
A30: Other Stuff | B30: Amount | C30: Due Date
A31: AMEX Bill | B31: ='CC - Feb 24'!F3 -> 6214.51 | C31: ='CC - Feb 24'!F4 -> 45368 | D31: PAID
A32: VISA Bill | B32: ='CC - Feb 24'!B3 -> 1890.06 | C32: ='CC - Feb 24'!B4 -> 45366 | D32: PAID
A33: MASTER Bill

Sheet CC - Feb 24
A1: VISA INFINITE STATEMENT | D1: AMEX STATEMENT
A2: DATE: | B2: 45346 | D2: DATE: | F2: 45346
A3: AMOUNT: | B3: 1890.06 | D3: AMOUNT: | F3: =6214.51 -> 6214.51
A4: DUE DATE: | B4: 45366 | D4: DUE DATE: | F4: 45368
B6: ITEM | C6: DATE | D6: CHARGE | E6: CATEGORY
B7: FORKED RIVER BREWING C LONDON | C7: 45086 | D7: 24 | E7: ALCOHOL
B8: APPLE.COM/BILL TORONTO | C8: 45314 | D8: 7.9 | E8: TECHNOLOGY
B9: PET VALU #2027 LONDON | C9: 45315 | D9: 255.81 | E9: PETS
B10: FIDO MOBILE ******6643 888-481-3436 | C10: 45316 | D10: 134.48 | E10: MOBILE
B11: VIA RAIL/W3V0QS MONTREAL | C11: 45316 | D11: 97.18 | E11: TRANSPORTATION
B12: UBER TRIP HTTPS://HELP.UB | C12: 45317 | D12: 6.12 | E12: TRANSPORTATION
B13: WW CANADA LTD 866-323-4411 | C13: 45317 | D13: 13.56 | E13: HEALTH
B14: FIDO HOME ******5135 888-481-3436 | C14: 45318 | D14: 103.96 | E14: INTERNET
B15: PETRO CANADA01327 LONDON | C15: 45318 | D15: 89.04 | E15: GAS
B16: THE HOME DEPOT #7033 LONDON | C16: 45318 | D16: 500 | E16: TRANSPORTATION
B17: THE HOME DEPOT #7033 LONDON | C17: 45318 | D17: -331.13 | E17: TRANSPORTATION
B18: PETSMART BURLINGTON | C18: 45319 | D18: 193.8 | E18: PETS
... B58: SPOTIFY STOCKHOLM | C58: 45346 | D58: 16.94 | E58: TECHNOLOGY
E59: HOUSEHOLD
E60: TECHNOLOGY
E61: TECHNOLOGY
E62: MOBILE
E63: SUBSCRIPTIONS
E64: TECHNOLOGY

Sheet CC - Mar 24
A1: VISA INFINITE STATEMENT | D1: AMEX STATEMENT
A2: DATE: | B2: 45375 | D2: DATE: | F2: 45375
A3: AMOUNT: | B3: =824.54 -> 824.54 | D3: AMOUNT: | F3: =1483.65 -> 1483.65
A4: DUE DATE: | B4: 45394 | D4: DUE DATE: | F4: 45399
B6: ITEM | C6: DATE | D6: CHARGE | E6: CATEGORY
B7: FIDO MOBILE ******6643 888-481-3436 | C7: 45347 | D7: 139 | E7: MOBILE
B8: WW CANADA LTD 866-323-4411 | C8: 45348 | D8: 13.56 | E8: HEALTH
B9: AMAZON CHANNELS AMAZON.CA | C9: 45349 | D9: 7.9 | E9: SUBSCRIPTIONS
B10: FIDO HOME ******5135 888-481-3436 | C10: 45349 | D10: 103.96 | E10: INTERNET
B11: GLOBE AND MAIL DIGITAL TORONTO | C11: 45349 | D11: 8.99 | E11: NEWSPAPER
B12: PAYMENT RECEIVED - THANK YOU | C12: 45350 | D12: -6214.51 | E12: PAYMENT
B13: AMAZON CHANNELS AMAZON.CA | C13: 45352 | D13: 5.64 | E13: SUBSCRIPTIONS
B14: DOMINOS PIZZA #10527 LONDON | C14: 45353 | D14: 23.05 | E14: TAKEOUT
B15: CINEPLEX ENTERTAINME 416-323-6600 | C15: 45355 | D15: 33.26 | E15: ENTERTAINMENT
B16: SHELBY'S LONDON | C16: 45355 | D16: 45.12 | E16: TAKEOUT
B17: CINEPLEX #7112 QP LONDON | C17: 45356 | D17: 94.6 | E17: ENTERTAINMENT
B18: CINEPLEX #7112 QP LONDON | C18: 45356 | D18: 10.17 | E18: ALCOHOL
... B55: WESTERN ANIMAL CLINIC | C55: 45344 | D55: 256.76 | E55: PETS
E56: CHARITY
E57: HOUSEHOLD
E58: PARAMOUNT
E59: ALCOHOL
E60: TECHNOLOGY
E61: HOUSEHOLD
E62: PETS
E63: TAKEOUT
E64: TECHNOLOGY
E65: GIFTS
E66: GROCERIES
E67: TECHNOLOGY
... E71: TECHNOLOGY

Sheet CB - Mar 24
A1: Month: | B1: Mar
A3: Income:
A4: Matt Comm | B4: 1580.67
A5: Matt | B5: =2834.71*2 -> 5669.42 | C5: =B5/B7 -> 0.61006637
A6: Nicole | B6: =1811.85*2 -> 3623.7 | C6: =B6/B7 -> 0.38993363
A7: Subtotal: | B7: =SUM(B5:B6) -> 9293.12
A9: Shared Expenses: | C9: Matt | D9: Nicole
A10: Rent | B10: =2400 -> 2400 | C10: =B10*C5 -> 1464.1593 | D10: =B10*C6 -> 935.84071
A11: Insurance | B11: 175.43 | C11: =B11*C5 -> 107.02394 | D11: =B11*C6 -> 68.406056
A12: Internet | B12: 103.96 | C12: =B12*C5 -> 63.4225 | D12: =B12*C6 -> 40.5375
A13: Pet Insurance | B13: 173.34 | C13: =B13*C5 -> 105.7489 | D13: =B13*C6 -> 67.591095
A14: Cell Phones | B14: 134.48 | C14: =B14*C5 -> 82.041726 | D14: =B14*C6 -> 52.438274
A15: Enbridge | B15: =104.03 -> 104.03 | C15: =B15*C5 -> 63.465205 | D15: =B15*C6 -> 40.564795 | E15: PAID
A16: London Hydro | B16: =147.97 -> 147.97 | C16: =B16*C5 -> 90.271521 | D16: =B16*C6 -> 57.698479 | E16: PAID
A18: Sub | B18: =Sum(B10:B16) -> 3239.21 | C18: =Sum(C10:C16) -> 1976.1331 | D18: =Sum(D10:D16) -> 1263.0769
A20: Shared Savings (25%) | E20: Total
A21: Savings (25%) | B21: =B7*0.25 -> 2323.28 | C21: =B21*C5 -> 1417.355 | D21: =B21*C6 -> 905.925 | E21: =SUM(C21:D21) -> 2323.28
A23: Sub | B23: =B18+B21 -> 5562.49 | C23: =C18+C21 -> 3393.4881 | D23: =D18+D21 -> 2169.0019
A25: Deposit to Personal Accts | C25: =B5-C23 -> 2275.9319 | D25: =B6-D23 -> 1454.6981
A26: 45366 | C26: =C25/2 -> 1137.966 | D26: =D25/2 -> 727.34905
A27: 45381 | C27: =C25/2 -> 1137.966 | D27: =D25/2 -> 727.34905
A30: Other Stuff | B30: Amount | C30: Due Date
A31: AMEX Bill | B31: ='CC - Mar 24'!F3 -> 1483.65 | C31: ='CC - Mar 24'!F4 -> 45399 | D31: PAID
A32: VISA Bill | B32: ='CC - Mar 24'!B3 -> 824.54 | C32: ='CC - Mar 24'!B4 -> 45394 | D32: PAID
A33: MASTER Bill

Sheet CB - Apr 24
A1: Month: | B1: April
A3: Income:
A4: Matt Comm | B4: 1915.94
A5: Matt | B5: =2834.71*2 -> 5669.42 | C5: =B5/B7 -> 0.61006637
A6: Nicole | B6: =1811.85*2 -> 3623.7 | C6: =B6/B7 -> 0.38993363
A7: Subtotal: | B7: =SUM(B5:B6) -> 9293.12
A9: Shared Expenses: | C9: Matt | D9: Nicole
A10: Rent | B10: =2400 -> 2400 | C10: =B10*C5 -> 1464.1593 | D10: =B10*C6 -> 935.84071 | E10: PAID
A11: Insurance | B11: =175.43 -> 175.43 | C11: =B11*C5 -> 107.02394 | D11: =B11*C6 -> 68.406056 | E11: PAID
A12: Internet | B12: =93.51 -> 93.51 | C12: =B12*C5 -> 57.047306 | D12: =B12*C6 -> 36.462694 | E12: PAID
A13: Pet Insurance | B13: =173.34 -> 173.34 | C13: =B13*C5 -> 105.7489 | D13: =B13*C6 -> 67.591095 | E13: PAID
A14: Cell Phones | B14: 134.48 | C14: =B14*C5 -> 82.041726 | D14: =B14*C6 -> 52.438274 | E14: PAID
A15: Enbridge | B15: =97.86 -> 97.86 | C15: =B15*C5 -> 59.701095 | D15: =B15*C6 -> 38.158905 | E15: PAID
A16: London Hydro | B16: =138.28 -> 138.28 | C16: =B16*C5 -> 84.359978 | D16: =B16*C6 -> 53.920022 | E16: PAID
A18: Sub | B18: =Sum(B10:B16) -> 3212.9 | C18: =Sum(C10:C16) -> 1960.0822 | D18: =Sum(D10:D16) -> 1252.8178
A20: Shared Savings (25%) | E20: Total
A21: Savings (25%) | B21: =B7*0.25 -> 2323.28 | C21: =B21*C5 -> 1417.355 | D21: =B21*C6 -> 905.925 | E21: =SUM(C21:D21) -> 2323.28
A23: Sub | B23: =B18+B21 -> 5536.18 | C23: =C18+C21 -> 3377.4372 | D23: =D18+D21 -> 2158.7428
A25: Deposit to Personal Accts | C25: =B5-C23 -> 2291.9828 | D25: =B6-D23 -> 1464.9572
A26: 45397 | C26: =C25/2 -> 1145.9914 | D26: =D25/2 -> 732.47862
A27: 45412 | C27: =C25/2 -> 1145.9914 | D27: =D25/2 -> 732.47862
A30: Other Stuff | B30: Amount | C30: Due Date
A31: AMEX Bill | B31: ='CC - Apr 24'!F3 -> 3290.12 | C31: ='CC - Apr 24'!F4 -> 45429 | D31: PAID
A32: VISA Bill | B32: ='CC - Apr 24'!B3 -> 1294.61 | C32: ='CC - Apr 24'!B4 -> 45427 | D32: PAID
A33: MASTER Bill | B33: 3780 | C33: 45425

Sheet CC - Apr 24
A1: VISA INFINITE STATEMENT | D1: AMEX STATEMENT
A2: DATE: | B2: 45406 | D2: DATE: | F2: 45406
A3: AMOUNT: | B3: 1294.61 | D3: AMOUNT: | F3: 3290.12
A4: DUE DATE: | B4: 45427 | D4: DUE DATE: | F4: 45429
B6: ITEM | C6: DATE | D6: CHARGE | E6: CATEGORY
B7: FRESHCO #9863 LONDON LONDON | C7: 45374 | D7: 41.2 | E7: GROCERIES
B8: L A MOOD LONDON | C8: 45375 | D8: 74.86 | E8: ENTERTAINMENT
B9: FIDO MOBILE ******6643 888-481-3436 | C9: 45376 | D9: 218.1 | E9: MOBILE
B10: AMAZON.CA*RA70B9G22 AMAZON.CA | C10: 45377 | D10: 34.68 | E10: HOUSEHOLD
B11: GLOBE AND MAIL DIGITAL TORONTO | C11: 45377 | D11: 8.99 | E11: NEWSPAPER
B12: METRO 150 LONDON | C12: 45377 | D12: 44.82 | E12: GROCERIES
B13: WW CANADA LTD 866-323-4411 | C13: 45377 | D13: 13.56 | E13: HEALTH
B14: AMAZON CHANNELS AMAZON.CA | C14: 45378 | D14: 7.9 | E14: SUBSCRIPTIONS
B15: AMZN MKTP CA*RH7IT9WD1 WWW.AMAZON.CA | C15: 45378 | D15: 33.71 | E15: TAKEOUT
B16: BUDWEISER GARDENS 519-432-8894 | C16: 45378 | D16: 217 | E16: ENTERTAINMENT
B17: FIDO HOME ******5135 888-481-3436 | C17: 45378 | D17: 97.03 | E17: INTERNET
B18: PAYMENT RECEIVED - THANK YOU | C18: 45378 | D18: -1483.65 | E18: PAYMENT
... B73: OLD SOUTH DENTISTRY | C73: 45374 | D73: 53.8 | E73: HEALTH

Sheet CB - May 24
A1: Month: | B1: May
A3: Income:
A4: Matt Comm | B4: =739.74 -> 739.74
A5: Matt | B5: =2834.71*2 -> 5669.42 | C5: =B5/B7 -> 0.61006637
A6: Nicole | B6: =1811.85*2 -> 3623.7 | C6: =B6/B7 -> 0.38993363
A7: Subtotal: | B7: =SUM(B5:B6) -> 9293.12
A9: Shared Expenses: | C9: Matt | D9: Nicole
A10: Rent | B10: =2400 -> 2400 | C10: =B10*C5 -> 1464.1593 | D10: =B10*C6 -> 935.84071 | E10: 45078
A11: Insurance | B11: =175.43 -> 175.43 | C11: =B11*C5 -> 107.02394 | D11: =B11*C6 -> 68.406056
A12: Internet | B12: =93.51 -> 93.51 | C12: =B12*C5 -> 57.047306 | D12: =B12*C6 -> 36.462694 | E12: 45074
A13: Pet Insurance | B13: 81.46 | C13: =B13*C5 -> 49.696007 | D13: =B13*C6 -> 31.763993 | E13: 45066
A14: Cell Phones | B14: 134.48 | C14: =B14*C5 -> 82.041726 | D14: =B14*C6 -> 52.438274
A15: Enbridge | B15: =54.72 -> 54.72 | C15: =B15*C5 -> 33.382832 | D15: =B15*C6 -> 21.337168 | E15: 45442 | F15: PAID
A16: London Hydro | B16: =127.17 -> 127.17 | C16: =B16*C5 -> 77.58214 | D16: =B16*C6 -> 49.58786 | E16: 45081 | F16: PAID
A18: Sub | B18: =Sum(B10:B16) -> 3066.77 | C18: =Sum(C10:C16) -> 1870.9332 | D18: =Sum(D10:D16) -> 1195.8368
A20: Shared Savings (25%) | E20: Total
A21: Savings (25%) | B21: =B7*0.25 -> 2323.28 | C21: =B21*C5 -> 1417.355 | D21: =B21*C6 -> 905.925 | E21: =SUM(C21:D21) -> 2323.28
A23: Sub | B23: =B18+B21 -> 5390.05 | C23: =C18+C21 -> 3288.2882 | D23: =D18+D21 -> 2101.7618
A25: Deposit to Personal Accts | C25: =B5-C23 -> 2381.1318 | D25: =B6-D23 -> 1521.9382
A26: 45427 | C26: =C25/2 -> 1190.5659 | D26: =D25/2 -> 760.96912
A27: 45442 | C27: =C25/2 -> 1190.5659 | D27: =D25/2 -> 760.96912
A30: Other Stuff | C30: Due Date
A31: AMEX Bill | B31: ='CC - May 24'!I3 | C31: 45092
A32: VISA Bill | B32: ='CC - May 24'!B3 | C32: 45089

Sheet CC - May 24
A1: VISA INFINITE STATEMENT | D1: AMEX STATEMENT
A2: DATE: | B2: 45070 | D2: DATE: | F2: 45070
A3: AMOUNT: | D3: AMOUNT:
A4: DUE DATE: | B4: 45092 | D4: DUE DATE: | F4: 45094
B6: ITEM | C6: DATE | D6: CHARGE | E6: CATEGORY
B7: FIDO MOBILE ******6643 888-481-3436 | C7: 45407 | D7: 169.17 | E7: MOBILE
B8: PET VALU #2027 LONDON | C8: 45407 | D8: 101.69 | E8: PETS
B9: PLAZA SUSHI OMAKASE 001 LONDON | C9: 45407 | D9: 59.78 | E9: TAKEOUT
B10: LASIK MD LONDON LONDON LONDON | C10: 45408 | D10: 4270 | E10: HEALTH
B11: METRO 150 LONDON | C11: 45408 | D11: 46.4 | E11: GROCERIES
B12: WW CANADA LTD 866-323-4411 | C12: 45408 | D12: 13.56 | E12: HEALTH
B13: AMAZON CHANNELS AMAZON.CA | C13: 45409 | D13: 7.9 | E13: PRIME VIDEO
B14: PETSMART INC. 2433 LONDON | C14: 45409 | D14: 111.76 | E14: PETS
B15: METRO 150 LONDON | C15: 45410 | D15: 37.15 | E15: GROCERIES
B16: NESPRESSO CANADA 855-325-5781 | C16: 45411 | D16: 153 | E16: COFFEE
B17: PAYMENT RECEIVED - THANK YOU | C17: 45411 | D17: -3290.12 | E17: PAYMENT
B18: AMAZON CHANNELS AMAZON.CA | C18: 45412 | D18: 5.64 | E18: PRIME VIDEO
... B68: SPOTIFY STOCKHOLM | C68: 45436 | D68: 16.94 | E68: TECHNOLOGY

Sheet CB - Jun 24
A1: Month: | B1: June
A3: Income:
A4: Matt Comm | B4: 0
A5: Matt | B5: =2834.71*2 -> 5669.42 | C5: =B5/B7 -> 0.61006637
A6: Nicole | B6: =1811.85*2 -> 3623.7 | C6: =B6/B7 -> 0.38993363
A7: Subtotal: | B7: =SUM(B5:B6) -> 9293.12
A9: Shared Expenses: | C9: Matt | D9: Nicole
A10: Rent | B10: =2400 -> 2400 | C10: =B10*C5 -> 1464.1593 | D10: =B10*C6 -> 935.84071
A11: Insurance | B11: =175.43 -> 175.43 | C11: =B11*C5 -> 107.02394 | D11: =B11*C6 -> 68.406056
A12: Internet | B12: =93.51 -> 93.51 | C12: =B12*C5 -> 57.047306 | D12: =B12*C6 -> 36.462694
A13: Pet Insurance | B13: 81.46 | C13: =B13*C5 -> 49.696007 | D13: =B13*C6 -> 31.763993
A14: Cell Phones | B14: 134.48 | C14: =B14*C5 -> 82.041726 | D14: =B14*C6 -> 52.438274
A15: Enbridge | B15: 44.03 | C15: =B15*C5 -> 26.861222 | D15: =B15*C6 -> 17.168778
A16: London Hydro | B16: 161.42 | C16: =B16*C5 -> 98.476914 | D16: =B16*C6 -> 62.943086
A18: Sub | B18: =Sum(B10:B16) -> 3090.33 | C18: =Sum(C10:C16) -> 1885.3064 | D18: =Sum(D10:D16) -> 1205.0236
A20: Shared Savings (25%)
A21: Savings (25%) | B21: =B7*0.25 -> 2323.28 | C21: =B21*C5 -> 1417.355 | D21: =B21*C6 -> 905.925
A23: Sub | B23: =B18+B21 -> 5413.61 | C23: =C18+C21 -> 3302.6614 | D23: =D18+D21 -> 2110.9486
A25: Deposit to Personal Accts | C25: =B5-C23 -> 2366.7586 | D25: =B6-D23 -> 1512.7514
A26: 45458 | C26: =C25/2 -> 1183.3793 | D26: =D25/2 -> 756.37571
A27: 45473 | C27: =C25/2 -> 1183.3793 | D27: =D25/2 -> 756.37571
A30: Other Stuff | C30: Due Date
A31: AMEX Bill | B31: ='CC - May 24'!I3 | C31: 45092
A32: VISA Bill | B32: ='CC - May 24'!B3 | C32: 45089
A33: MASTER Bill

Sheet CC - Jun 24
A1: VISA INFINITE STATEMENT | D1: AMEX STATEMENT
A2: DATE: | B2: 45099 | D2: DATE: | F2: 45101
A3: AMOUNT: | D3: AMOUNT:
A4: DUE DATE: | B4: 45120 | D4: DUE DATE: | F4: 45124
B6: ITEM | C6: DATE | D6: CHARGE | E6: CATEGORY
B7: DISNEY PLUS ADY | C7: 45467 | D7: -60 | E7: PAYMENT
B8: SPOTIFY STOCKHOLM | C8: 45467 | D8: 16.94 | E8: TECHNOLOGY
B9: AMZN MKTP CA*RC2S09NK0 WWW.AMAZON.CA | C9: 45466 | D9: 17.46 | E9: HOUSEHOLD
B10: APPLE.COM/BILL TORONTO | C10: 45465 | D10: 14.68 | E10: TECHNOLOGY
B11: PET VALU #2027 LONDON | C11: 45465 | D11: 151.28 | E11: PETS
B12: DISNEY PLUS RECURRING BURBANK | C12: 45464 | D12: 169.48 | E12: Disney+
B13: SHOPPERS DRUG MART #098 TORONTO | C13: 45463 | D13: 16.49 | E13: HEALTH
B14: VIA RAIL CANADA INC MONTREAL | C14: 45463 | D14: 27.5 | E14: TRANSPORTATION
B15: CINEPLEX #7112 QP LONDON | C15: 45462 | D15: 132.91 | E15: DINE IN
B16: CINEPLEX ENTERTAINME 416-323-6600 | C16: 45462 | D16: 25.18 | E16: ENTERTAINMENT
B17: GLOBAL-E* EXPRESSO DIS VANCOUVER | C17: 45462 | D17: 913.04 | E17: TECHNOLOGY
B18: GLOBE AND MAIL DIGITAL TORONTO | C18: 45461 | D18: 8.99 | E18: NEWSPAPER
... B82: Merla Mae Ice Cream | C82: 45460 | D82: 27 | E82: TAKEOUT
E83: TECHNOLOGY
E84: TAKEOUT
E85: TAKEOUT
E86: TAKEOUT
E87: GIFTS
E88: GIFTS
E89: GIFTS
E90: ENTERTAINMENT
E91: ENTERTAINMENT
E92: TECHNOLOGY

Sheet CB - Jul 24
A1: Month: | B1: July
A3: Income:
A4: Matt Comm | B4: 0
A5: Matt | B5: =2834.71*2 -> 5669.42 | C5: =B5/B7 -> 0.61006637
A6: Nicole | B6: =1811.85*2 -> 3623.7 | C6: =B6/B7 -> 0.38993363
A7: Subtotal: | B7: =SUM(B5:B6) -> 9293.12
A9: Shared Expenses: | C9: Matt | D9: Nicole
A10: Rent | B10: =2400 -> 2400 | C10: =B10*C5 -> 1464.1593 | D10: =B10*C6 -> 935.84071 | E10: PAID
A11: Car Insurance | B11: =175.43 -> 175.43 | C11: =B11*C5 -> 107.02394 | D11: =B11*C6 -> 68.406056 | E11: PAID
A12: Internet | B12: =93.51 -> 93.51 | C12: =B12*C5 -> 57.047306 | D12: =B12*C6 -> 36.462694
A13: Pet Insurance | B13: =138 -> 138 | C13: =B13*C5 -> 84.189159 | D13: =B13*C6 -> 53.810841
A14: Cell Phones | B14: 134.48 | C14: =B14*C5 -> 82.041726 | D14: =B14*C6 -> 52.438274
A15: Enbridge | B15: =39.11 -> 39.11 | C15: =B15*C5 -> 23.859696 | D15: =B15*C6 -> 15.250304 | E15: PAID
A16: London Hydro | B16: =213.85 -> 213.85 | C16: =B16*C5 -> 130.46269 | D16: =B16*C6 -> 83.387306 | E16: PAID
A18: Shared Savings (30%) | E18: Comm | F18: Total
A19: Wedding (10%) | B19: =B7*0.1 -> 929.312 | C19: =B19*C5 -> 566.942 | D19: =B19*C6 -> 362.37 | E19: =B4*0.33 -> 0 | F19: =SUM(C19:E19) -> 929.312
A20: Retirement (10%) | B20: =B7*0.1 -> 929.312 | C20: =B20*C5 -> 566.942 | D20: =B20*C6 -> 362.37 | E20: =B4*0.33 -> 0 | F20: =SUM(C20:E20) -> 929.312
A21: House (10%) | B21: =B7*0.1 -> 929.312 | C21: =B21*C5 -> 566.942 | D21: =B21*C6 -> 362.37 | E21: =B4*0.33 -> 0 | F21: =Sum(C21:E21) -> 929.312
A23: Deposit to Personal Acct | C23: =SUM(C10:C20)-C12 -> 3025.6205 | D23: =SUM(D10:D20) -> 1970.3362
A24: 45122 | C24: =C23/2 -> 1512.8103 | D24: =D23/2 -> 985.16809
A25: 45137 | C25: =C23/2 -> 1512.8103 | D25: =D23/2 -> 985.16809
A26: Remainder: | C26: Matt | D26: Nicole
C27: =B5-C23 -> 2643.7995 | D27: =B6-D23 -> 1653.3638
A30: Other Stuff | C30: Due Date
A31: AMEX Bill | B31: =3210.13 -> 3210.13 | C31: 45152
A32: VISA Bill | B32: =2579.79 -> 2579.79 | C32: 45152
A33: MASTER Bill
A35: Shared | B35: sub | C35: 0.6 | D35: 0.4
A36: Total Paid by Matt
A37: Total Paid by Nicole

Sheet CC - Jul 24
A1: VISA INFINITE STATEMENT | D1: AMEX STATEMENT
A2: DATE: | B2: 45129 | D2: DATE: | F2: 45131
A3: AMOUNT: | B3: 359.94 | D3: AMOUNT:
A4: DUE DATE: | B4: 45151 | D4: DUE DATE: | F4: 45155
B6: ITEM | C6: DATE | D6: CHARGE | E6: CATEGORY
B7: SPOTIFY STOCKHOLM | C7: 45497 | D7: 16.94 | E7: TECHNOLOGY
B8: APPLE.COM/BILL TORONTO | C8: 45495 | D8: 14.68 | E8: TECHNOLOGY
B9: APPLE.COM/BILL TORONTO | C9: 45495 | D9: 18.07 | E9: TECHNOLOGY
B10: DOGTOPIA OF LONDON 00-0 LONDON | C10: 45495 | D10: 3.39 | E10: PETS
B11: DOGTOPIA OF LONDON 00-0 LONDON | C11: 45495 | D11: 145.77 | E11: PETS
B12: COUSIN VINNYS PIZZA LONDON | C12: 45494 | D12: 22.99 | E12: TAKEOUT
B13: AMZN MKTP CA*RJ9L04E10 WWW.AMAZON.CA | C13: 45493 | D13: 19.19 | E13: HOUSEHOLD
B14: METRO 150 LONDON | C14: 45493 | D14: 21.46 | E14: GROCERIES
B15: AMZN MKTP CA*RS01P5Y62 WWW.AMAZON.CA | C15: 45491 | D15: 15.81 | E15: HOUSEHOLD
B16: AMZN MKTP CA*RS43X3Y32 WWW.AMAZON.CA | C16: 45491 | D16: 25.59 | E16: HOUSEHOLD
B17: AMZN MKTP CA*RS5756YP2 WWW.AMAZON.CA | C17: 45491 | D17: 29.38 | E17: HOUSEHOLD
B18: METRO 150 LONDON | C18: 45491 | D18: 26.97 | E18: GROCERIES
... B72: WINKS EATERY | C72: 45494 | D72: 58.09 | E72: ALCOHOL

Sheet CB - Aug 24
A1: Month: | B1: Aug
A3: Income:
A4: Matt Comm | B4: 0
A5: Matt | B5: =3112.28*2 -> 6224.56 | C5: =B5/B7 -> 0.60495466
A6: Nicole | B6: =2032.37*2 -> 4064.74 | C6: =B6/B7 -> 0.39504534
A7: Subtotal: | B7: =SUM(B5:B6) -> 10289.3
A9: Shared Expenses: | C9: Matt | D9: Nicole
A10: Mortgage | B10: =1711.29 -> 1711.29 | C10: =B10*C5 -> 1035.2529 | D10: =B10*C6 -> 676.03714
A11: Insurance | B11: =175.43 -> 175.43 | C11: =B11*C5 -> 106.1272 | D11: =B11*C6 -> 69.302804
A12: Internet | B12: =93.51 -> 93.51 | C12: =B12*C5 -> 56.56931 | D12: =B12*C6 -> 36.94069
A13: Pet Insurance | B13: 81.46 | C13: =B13*C5 -> 49.279607 | D13: =B13*C6 -> 32.180393
A14: Cell Phones | B14: 134.48 | C14: =B14*C5 -> 81.354303 | D14: =B14*C6 -> 53.125697
A15: Enbridge | B15: =39.2 -> 39.2 | C15: =B15*C5 -> 23.714223 | D15: =B15*C6 -> 15.485777
A16: London Hydro | B16: =242.15 -> 242.15 | C16: =B16*C5 -> 146.48977 | D16: =B16*C6 -> 95.660229
A18: Sub | B18: =Sum(B10:B16) -> 2477.52 | C18: =Sum(C10:C16) -> 1498.7873 | D18: =Sum(D10:D16) -> 978.73273
A20: Shared Savings (25%)
A21: Savings (25%) | B21: =B7*0.25 -> 2572.325 | C21: =B21*C5 -> 1556.14 | D21: =B21*C6 -> 1016.185
A23: Sub | B23: =B18+B21 -> 5049.845 | C23: =C18+C21 -> 3054.9273 | D23: =D18+D21 -> 1994.9177
A25: Deposit to Personal Accts | C25: =B5-C23 -> 3169.6327 | D25: =B6-D23 -> 2069.8223
A26: 45519 | C26: =C25/2 -> 1584.8164 | D26: =D25/2 -> 1034.9111
A27: 45534 | C27: =C25/2 -> 1584.8164 | D27: =D25/2 -> 1034.9111
A30: Other Stuff | C30: Due Date
A31: AMEX Bill | B31: ='CC - May 24'!I3 | C31: 45092
A32: VISA Bill | B32: ='CC - May 24'!B3 | C32: 45089
A33: MASTER Bill

Sheet CC - Aug 23
A1: VISA INFINITE STATEMENT | E1: AMEX STATEMENT
A2: DATE: | B2: 45161 | E2: DATE: | G2: 45162
A3: AMOUNT: | E3: AMOUNT:
A4: DUE DATE: | B4: 45186 | E4: DUE DATE: | G4: 45186
B6: ITEM | C6: DATE | D6: CHARGE | E6: CATEGORY
B7: MEMBERSHIP FEE | C7: 45528 | D7: 599 | E7: CC FEES
B8: SPOTIFY STOCKHOLM | C8: 45528 | D8: 16.94 | E8: SPOTIFY
B9: LONDON BREWING London | C9: 45527 | D9: 76.47 | E9: ALCOHOL
B10: APPLE.COM/BILL TORONTO | C10: 45526 | D10: 14.68 | E10: SUBSCRIPTION SERVICES
B11: APPLE.COM/BILL TORONTO | C11: 45526 | D11: 18.07 | E11: SUBSCRIPTION SERVICES
B12: LCBO/RAO #0192 LONDON LONDON | C12: 45525 | D12: 46.95 | E12: ALCOHOL
B13: DOGTOPIA OF LONDON 00-0 LONDON | C13: 45524 | D13: 79.1 | E13: PETS
B14: METRO 150 LONDON | C14: 45524 | D14: 72.77 | E14: GROCERIES
B15: PLAYSTATION NETWORK 877-971-7669 | C15: 45524 | D15: 18.35 | E15: ENTERTAINMENT
B16: SHELBY'S LONDON | C16: 45524 | D16: 45.4 | E16: TAKEOUT
B17: AIRBNB * HMCXSYYFDD LONDON | C17: 45523 | D17: 2081.53 | E17: HOTELS
B18: DOGTOPIA OF LONDON 00-0 LONDON | C18: 45523 | D18: 145.77 | E18: PETS
... B82: WESTJET CALGARY | C82: 45495 | D82: 12.49 | E82: TAKEOUT

Sheet CB - Sep 24
B1: Sept
A3: Income:
A4: Matt Comm | B4: 0
A5: Matt | B5: =3112.28*2 -> 6224.56 | C5: =B5/B7 -> 0.60495466
A6: Nicole | B6: =2032.37*2 -> 4064.74 | C6: =B6/B7 -> 0.39504534
A7: Subtotal: | B7: =SUM(B5:B6) -> 10289.3
A9: Shared Expenses: | C9: Matt | D9: Nicole
A10: Rent | B10: 1711.29 | C10: =B10*C5 -> 1035.2529 | D10: =B10*C6 -> 676.03714
A11: Reliance (Water Heater) | B11: 116.14 | C11: =B11*C5 -> 70.259434 | D11: =B11*C6 -> 45.880566
A12: Insurance | B12: =154.29 -> 154.29 | C12: =B12*C5 -> 93.338455 | D12: =B12*C6 -> 60.951545
A13: Internet | B13: =93.51 -> 93.51 | C13: =B13*C5 -> 56.56931 | D13: =B13*C6 -> 36.94069
A14: Pet Insurance | B14: 138.83 | C14: =B14*C5 -> 83.985856 | D14: =B14*C6 -> 54.844144
A15: Cell Phones | B15: 134.48 | C15: =B15*C5 -> 81.354303 | D15: =B15*C6 -> 53.125697
A16: Enbridge | B16: =39.2 -> 39.2 | C16: =B16*C5 -> 23.714223 | D16: =B16*C6 -> 15.485777
A17: London Hydro | B17: 215.03 | C17: =B17*C5 -> 130.0834 | D17: =B17*C6 -> 84.946599
A19: Shared Savings (25%)
B20: =B7*0.25 -> 2572.325 | C20: =B20*C5 -> 1556.14 | D20: =B20*C6 -> 1016.185
A22: Sub | B22: =SUM(B10:B20) -> 5175.095 | C22: =SUM(C10:C20) -> 3130.6978 | D22: =SUM(D10:D20) -> 2044.3972
A24: Deposit to Personal Accts | C24: =B5-C22 -> 3093.8622 | D24: =B6-D22 -> 2020.3428
A25: 45184 | C25: =C24/2 -> 1546.9311 | D25: =D24/2 -> 1010.1714
A26: 45199 | C26: =C24/2 -> 1546.9311 | D26: =D24/2 -> 1010.1714
A30: Other Stuff | C30: Due Date
A31: AMEX Bill | B31: =3286.78 -> 3286.78 | C31: Paid
A32: VISA Bill | B32: =1691.15 -> 1691.15 | C32: Paid
A33: MASTER | B33: =1000 -> 1000 | C33: Paid
B34: =B31+B32+B33 -> 5977.93
A35: Shared | B35: sub | C35: 0.6 | D35: 0.4
A36: Total Paid by Matt
A37: Total Paid by Nicole

Sheet CC - Sep 23
A1: VISA INFINITE STATEMENT | E1: AMEX STATEMENT
A2: DATE: | B2: 45162 | E2: DATE: | G2: 45162
A3: AMOUNT: | E3: AMOUNT:
A4: DUE DATE: | B4: 45184 | E4: DUE DATE: | G4: 45186
B6: ITEM | C6: DATE | D6: CHARGE | E6: CATEGORY
B7: SPOTIFY STOCKHOLM | C7: 45559 | D7: 16.94 | E7: SPOTIFY
B8: DOGTOPIA OF LONDON 00-0 LONDON | C8: 45558 | D8: 11.3 | E8: PETS
B9: DOGTOPIA OF LONDON 00-0 LONDON | C9: 45558 | D9: 145.77 | E9: PETS
B10: NATIONAL CANADA C133 LONDON | C10: 45558 | D10: 186.94 | E10: TRANSPORTATION
B11: APPLE.COM/BILL TORONTO | C11: 45557 | D11: 18.07 | E11: TECHNOLOGY
B12: COUCHE-TARD # 1274 LACHINE | C12: 45557 | D12: 60 | E12: TAKEOUT
B13: DUNDAS ST ESSO 0322 LONDON | C13: 45557 | D13: 5.27 | E13: TAKEOUT
B14: ONROUTE MALLORYTOWN | C14: 45557 | D14: 17.05 | E14: GAS
B15: SHELL FLYING J 862 AYR | C15: 45557 | D15: 67.05 | E15: GAS
B16: AGENCE DE MOBILITE DURA MONTREAL | C16: 45556 | D16: 12.75 | E16: TAKEOUT
B17: SAQ23210MONT-ROYAL E-ME MONTREAL | C17: 45556 | D17: 18.6 | E17: TAKEOUT
B18: STEAK FRITES (ST-ANTOIN MONTREAL | C18: 45556 | D18: 60.71 | E18: TAKEOUT
... B78: TOO GOOD TO GO CANADA T VANCOUVER | C78: 45535 | D78: 6.77 | E78: TECHNOLOGY
B79: AMAZON CHANNELS AMAZON.CA | C79: 45534 | D79: 24.85
B80: PAYMENT RECEIVED - THANK YOU | C80: 45534 | D80: -9867.61
B81: PLAYSTATION NETWORK 877-971-7669 | C81: 45534 | D81: 101.69
B82: CHICK-FIL-A WHARNCLIFFE LONDON | C82: 45533 | D82: 29.13
B83: PET VALU #2323 LONDON | C83: 45533 | D83: 101.69
B84: GLOBAL PET FOODS LONDON | C84: 45532 | D84: 33.89
B85: METRO 150 LONDON | C85: 45532 | D85: 24.48
B86: PLAYSTATION NETWORK 877-971-7669 | C86: 45532 | D86: 45.75
B87: STARBUCKS COFFEE #51 LONDON | C87: 45532 | D87: 13.07
B88: AMAZON CHANNELS AMAZON.CA | C88: 45531 | D88: 7.9
B89: AMAZON CHANNELS AMAZON.CA | C89: 45531 | D89: 14.68
B90: TIM HORTONS #270 PARRY SOUND | C90: 45531 | D90: 9.26
... B97: PETSMART #3042 LONDON | C97: 45527 | D97: 94.65

Sheet CB - Oct 24
A1: Month: | B1: Oct
A3: Income:
A4: Matt Comm | B4: 0
A5: Matt | B5: =3111.28*2 -> 6222.56 | C5: =B5/B7 -> 0.60492137
A6: Nicole | B6: =2032*2 -> 4064 | C6: =B6/B7 -> 0.39507863
A7: Subtotal: | B7: =SUM(B5:B6) -> 10286.56
A9: Shared Expenses: | C9: Matt | D9: Nicole
A10: Rent | B10: 1711.29 | C10: =B10*C5 -> 1035.1959 | D10: =B10*C6 -> 676.0941
A11: Reliance (Water Heater) | B11: 35 | C11: =B11*C5 -> 21.172248 | D11: =B11*C6 -> 13.827752
A12: Insurance (Home+Auto) | B12: =366.24 -> 366.24 | C12: =B12*C5 -> 221.5464 | D12: =B12*C6 -> 144.6936
A13: Internet | B13: =93.51 -> 93.51 | C13: =B13*C5 -> 56.566198 | D13: =B13*C6 -> 36.943802
A14: Pet Insurance | B14: 138.83 | C14: =B14*C5 -> 83.981234 | D14: =B14*C6 -> 54.848766
A15: Cell Phones | B15: 134.48 | C15: =B15*C5 -> 81.349826 | D15: =B15*C6 -> 53.130174
A16: Enbridge | B16: 40.27 | C16: =B16*C5 -> 24.360184 | D16: =B16*C6 -> 15.909816
A17: London Hydro | B17: =151.88 -> 151.88 | C17: =B17*C5 -> 91.875458 | D17: =B17*C6 -> 60.004542
A19: Shared Savings (25%)
B20: =B7*0.25 -> 2571.64 | C20: =B20*C5 -> 1555.64 | D20: =B20*C6 -> 1016
A22: Sub | B22: =SUM(B10:B20) -> 5243.14 | C22: =SUM(C10:C20) -> 3171.6874 | D22: =SUM(D10:D20) -> 2071.4526
A24: Deposit to Personal Accts | C24: =B5-C22 -> 3050.8726 | D24: =B6-D22 -> 1992.5474
A25: 45214 | C25: =C24/2 -> 1525.4363 | D25: =D24/2 -> 996.27372
A26: 45229 | C26: =C24/2 -> 1525.4363 | D26: =D24/2 -> 996.27372
A30: Other Stuff | C30: Due Date
A31: AMEX Bill
A32: VISA Bill
A33: MASTER

Sheet CC - Oct 23
A1: VISA INFINITE STATEMENT | G1: AMEX STATEMENT
A2: DATE: | B2: 45193 | G2: DATE: | I2: 45193
A3: AMOUNT: | G3: AMOUNT:
A4: DUE DATE: | B4: 45222 | G4: DUE DATE: | I4: 45222
B6: ITEM | C6: DATE | D6: CHARGE | E6: CATEGORY
E7: GROCERIES
E8: GROCERIES
E9: TAKEOUT
E10: CANNABIS
E11: PAYMENT
E12: PETS
E13: TAKEOUT
E14: DINE IN
E15: GROCERIES
E16: PETS
E17: MOBILE
E18: TAKEOUT
... E74: TECHNOLOGY

Sheet CB - Nov 24
A1: Month: | B1: Nov
A3: Income:
A4: Matt Comm | B4: 0
A5: Matt | B5: =3111.28*2 -> 6222.56 | C5: =B5/B7 -> 0.60492137
A6: Nicole | B6: =2032*2 -> 4064 | C6: =B6/B7 -> 0.39507863
A7: Subtotal: | B7: =SUM(B5:B6) -> 10286.56
A9: Shared Expenses: | C9: Matt | D9: Nicole
A10: Rent | B10: 1711.29 | C10: =B10*C5 -> 1035.1959 | D10: =B10*C6 -> 676.0941
A11: Reliance (Water Heater) | B11: 38.3 | C11: =B11*C5 -> 23.168489 | D11: =B11*C6 -> 15.131511
A12: Insurance | B12: =154.29 -> 154.29 | C12: =B12*C5 -> 93.333319 | D12: =B12*C6 -> 60.956681
A13: Internet | B13: =93.51 -> 93.51 | C13: =B13*C5 -> 56.566198 | D13: =B13*C6 -> 36.943802
A14: Pet Insurance | B14: 138.83 | C14: =B14*C5 -> 83.981234 | D14: =B14*C6 -> 54.848766
A15: Cell Phones | B15: 200 | C15: =B15*C5 -> 120.98427 | D15: =B15*C6 -> 79.015725
A16: Enbridge | B16: 44.69 | C16: =B16*C5 -> 27.033936 | D16: =B16*C6 -> 17.656064
A17: London Hydro | B17: 301.77 | C17: =B17*C5 -> 182.54712 | D17: =B17*C6 -> 119.22288
A19: Shared Savings (25%)
B20: =B7*0.25 -> 2571.64 | C20: =B20*C5 -> 1555.64 | D20: =B20*C6 -> 1016
A22: Sub | B22: =SUM(B10:B20) -> 5254.32 | C22: =SUM(C10:C20) -> 3178.4505 | D22: =SUM(D10:D20) -> 2075.8695
A24: Personal Accts | C24: =B5-C22 -> 3044.1095 | D24: =B6-D22 -> 1988.1305
A25: 45245 | C25: =C24/2 -> 1522.0548 | D25: =D24/2 -> 994.06523
A26: 45260 | C26: =C24/2 -> 1522.0548 | D26: =D24/2 -> 994.06523
A30: Other Stuff | C30: Due Date
A31: AMEX Bill | C31: Paid
A32: VISA Bill | C32: Paid
A33: MASTER | C33: Paid

Sheet CC - Nov 23
A1: VISA INFINITE STATEMENT
A2: DATE: | B2: 45223
A3: AMOUNT:
A4: DUE DATE: | B4: 45253
I5: CATEGORY | J5: SUM of CHARGE
B6: ITEM | C6: DATE | D6: CHARGE | E6: CATEGORY | I6: ALCOHOL | J6: 0
E7: HOUSEHOLD | I7: CANNABIS | J7: 0
E8: MOBILE | I8: CHARITY | J8: 0
E9: HEALTH | I9: COFFEE | J9: 0
E10: INTERNET | I10: DINE IN | J10: 0
E11: ALCOHOL | I11: ENTERTAINMENT | J11: 0
E12: HOUSEHOLD | I12: GAS | J12: 0
E13: PETS | I13: GIFTS | J13: 0
E14: HOUSEHOLD | I14: GROCERIES | J14: 0
E15: TECHNOLOGY | I15: HEALTH | J15: 0
E16: PAYMENT | I16: HOUSEHOLD | J16: 0
E17: SUBSCRIPTIONS | I17: INTERNET | J17: 0
E18: HOUSEHOLD | I18: MOBILE | J18: 0
... E27: NEWSPAPER | I27: Grand Total | J27: 0
E28: CHARITY
E29: TRANSPORTATION
E30: TECHNOLOGY
E31: TECHNOLOGY
E32: TRANSPORTATION
E33: SUBSCRIPTIONS
E34: HEALTH
E35: GROCERIES
E36: CHARITY
E37: GROCERIES
E38: GROCERIES
E39: SUBSCRIPTIONS SERVICES
... E74: TAKEOUT

Sheet CB - Dec 24
A1: Month: | B1: Dec
A3: Income:
A4: Matt Comm | B4: 0
A5: Matt | B5: =3111.28*2 -> 6222.56 | C5: =B5/B7 -> 0.60492137
A6: Nicole | B6: =2032*2 -> 4064 | C6: =B6/B7 -> 0.39507863
A7: Subtotal: | B7: =SUM(B5:B6) -> 10286.56
A9: Shared Expenses: | C9: Matt | D9: Nicole
A10: Rent | B10: 1711.29 | C10: =B10*C5 -> 1035.1959 | D10: =B10*C6 -> 676.0941
A11: Reliance (Water Heater) | B11: 116.14 | C11: =B11*C5 -> 70.255568 | D11: =B11*C6 -> 45.884432
A12: Insurance | B12: =154.29 -> 154.29 | C12: =B12*C5 -> 93.333319 | D12: =B12*C6 -> 60.956681
A13: Internet | B13: =93.51 -> 93.51 | C13: =B13*C5 -> 56.566198 | D13: =B13*C6 -> 36.943802
A14: Pet Insurance | B14: 138.83 | C14: =B14*C5 -> 83.981234 | D14: =B14*C6 -> 54.848766
A15: Cell Phones | B15: 134.48 | C15: =B15*C5 -> 81.349826 | D15: =B15*C6 -> 53.130174
A16: Enbridge | B16: 71.22 | C16: =B16*C5 -> 43.0825 | D16: =B16*C6 -> 28.1375
A17: London Hydro | B17: 205.54 | C17: =B17*C5 -> 124.33554 | D17: =B17*C6 -> 81.204461
A19: Shared Savings (25%)
B20: =B7*0.25 -> 2571.64 | C20: =B20*C5 -> 1555.64 | D20: =B20*C6 -> 1016
A22: Sub | B22: =SUM(B10:B20) -> 5196.94 | C22: =SUM(C10:C20) -> 3143.7401 | D22: =SUM(D10:D20) -> 2053.1999
A24: Deposit to Personal Accts | C24: =B5-C22 -> 3078.8199 | D24: =B6-D22 -> 2010.8001
A25: 45184 | C25: =C24/2 -> 1539.41 | D25: =D24/2 -> 1005.4
A26: 45199 | C26: =C24/2 -> 1539.41 | D26: =D24/2 -> 1005.4
A30: Other Stuff | C30: Due Date
A31: AMEX Bill
A32: VISA Bill
A33: MASTER

Sheet CC - Dec 23
A1: VISA INFINITE STATEMENT
A2: DATE: | B2: 45254
A3: AMOUNT:
A4: DUE DATE: | B4: 45283
I5: CATEGORY | J5: SUM of CHARGE
B6: ITEM | C6: DATE | D6: CHARGE | E6: CATEGORY | I6: ALCOHOL | J6: 0
E7: MOBILE | I7: CHARITY | J7: 0
E8: ENTERTAINMENT | I8: COFFEE | J8: 0
E9: TAKEOUT | I9: DINE IN | J9: 0
E10: SUBSCRIPTIONS SERVICES | I10: ENTERTAINMENT | J10: 0
E11: GIFTS | I11: GAS | J11: 0
E12: INTERNET | I12: GIFTS | J12: 0
E13: HOUSEHOLD | I13: GROCERIES | J13: 0
E14: GROCERIES | I14: HEALTH | J14: 0
E15: SUBSCRIPTIONS | I15: HOTELS | J15: 0
E16: GROCERIES | I16: HOUSEHOLD | J16: 0
E17: PAYMENT | I17: INTERNET | J17: 0
E18: TRANSPORTATION | I18: MOBILE | J18: 0
... E26: SUBSCRIPTIONS | I26: Grand Total | J26: 0
E27: TAKEOUT
E28: CHARITY
E29: TAKEOUT
E30: ALCOHOL
E31: GIFTS
E32: TECHNOLOGY
E33: TECHNOLOGY
E34: DINE IN
E35: GROCERIES
E36: HEALTH
E37: SUBSCRIPTIONS
E38: GROCERIES
... E69: ALCOHOL
