Workbook

Sheet Summary
A1: Month | B1: Net Income (Matt) | C1: Comm Income (Matt) | D1: Net Income (Nicole) | E1: Total
A2: Jan | B2: ='Jan-2025'!B5 -> 5674.45 | C2: ='Jan-2025'!B4 -> 1497.82 | D2: ='Jan-2025'!B6 -> 3854.91 | E2: =SUM(B2:D2) -> 11027.18
A3: Feb | B3: ='Feb-2025'!B5 -> 4948.2 | C3: ='Feb-2025'!B4 -> 1955.54 | D3: ='Feb-2025'!B6 -> 3958.02 | E3: =SUM(B3:D3) -> 10861.76
A4: Mar | B4: ='Mar-2025'!B5 -> 5742.84 | C4: ='Mar-2025'!B4 -> 1161.07 | D4: ='Mar-2025'!B6 -> 3958.02 | E4: =SUM(B4:D4) -> 10861.93
A5: Apr | B5: ='Apr-2025'!B5 -> 9797.83 | C5: ='Apr-2025'!B4 -> 1623.16 | D5: ='Apr-2025'!B6 -> 4078.49 | E5: =SUM(B5:D5) -> 15499.48
A6: May | B6: ='May-2025'!B5 -> 7410.76 | C6: ='May-2025'!B4 -> 0 | D6: ='May-2025'!B6 -> 3958.02 | E6: =SUM(B6:D6) -> 11368.78
A7: Jun | B7: ='Jun-2025'!B5 -> 7410.76 | C7: ='Jun-2025'!B4 -> 0 | D7: ='Jun-2025'!B6 -> 3958.02 | E7: =SUM(B7:D7) -> 11368.78
A8: Jul | B8: ='Jul-2025'!B5 -> 6812.62 | C8: ='Jul-2025'!B4 -> 0 | D8: ='Jul-2025'!B6 -> 3958.02 | E8: =SUM(B8:D8) -> 10770.64
A9: Aug | B9: ='Aug-2025'!B5 -> 6813.58 | C9: ='Jul-2025'!B4 -> 0 | D9: ='Jul-2025'!B6 -> 3958.02 | E9: =SUM(B9:D9) -> 10771.6
A10: Sep | B10: ='Sep-2025'!B5 -> 7429.45 | C10: ='Sep-2025'!B4 -> 0 | D10: ='Sep-2025'!B6 -> 4286.52 | E10: =SUM(B10:D10) -> 11715.97
A11: Oct | B11: ='Oct-2025'!B5 -> 12414.97 | C11: ='Oct-2025'!B4 -> 0 | D11: ='Oct-2025'!B6 -> 4180.61 | E11: =SUM(B11:D11) -> 16595.58
A12: Nov | B12: ='Nov-2025'!B5 -> 6054.57 | C12: ='Nov-2025'!B4 -> 0 | D12: ='Nov-2025'!B6 -> 4060.36 | E12: =SUM(B12:D12) -> 10114.93
A13: Dec | B13: ='Dec-2025'!B5 -> 5898.22 | C13: ='Dec-2025'!B4 -> 0 | D13: ='Dec-2025'!B6 -> 4060.36 | E13: =SUM(B13:D13) -> 9958.58
A15: Total | B15: =SUM(B2:B13) -> 86408.25 | C15: =SUM(C2:C13) -> 6237.59 | D15: =SUM(D2:D13) -> 48269.37 | E15: =SUM(E2:E13) -> 140915.21
A17: Matt
A18: Gross Salary | B18: Base | C18: Comm | D18: Total
A19: Jan 1 - Feb 28 | B19: 95000 | C19: 25000 | D19: =SUM(B19:C19) -> 120000
A20: Mar 1 - Mar 30 | B20: 99000 | C20: 29000 | D20: =SUM(B20:C20) -> 128000
A21: Apr 7 - Jun 30 | B21: 145000 | C21: 0 | D21: 145000
A22: Jul 1 - Dec 31 | B22: 130500 | C22: 32625 | D22: =SUM(B22:C22) -> 163125
A24: Nicole
A25: Gross Salary | B25: Base | D25: Total
A26: Jan 1 - Jun 30 | B26: 61900 | D26: =SUM(B26:C26) -> 61900
A27: Jul 1 - Dec 31 | B27: 63300 | D27: =SUM(B27:C27) -> 63300
A32: 🚦 Savings Vehicle Priority (to stay on track)
A33: 1 | B33: Kill LOC ($5K) immediately.
A34: 2 | B34: Emergency fund $30K–$45K in HISA (after renos).
A35: 3 | B35: Employer-matched RRSP ($1,050/mo, keep forever).
A36: 4 | B36: ESPP max out → sell + reinvest gains (guaranteed 15%).
A37: 5 | B37: TFSA contributions ($1,500/mo Matt, $500/mo Nicole + reinvest ESPP & RSUs).
A38: 6 | B38: Interest-free loan → save ~$530/mo until Dec 2026.
A39: 7 | B39: Mortgage → pay as scheduled/accelerated, no extra beyond plan.
A40: 8 | B40: Extra RRSP only if TFSA is maxed and you need tax deductions.

Sheet Debts
A1: Loan Name | B1: Creditor | C1: Initial Balance | D1: Monthly Payment | E1: Monthly Extra | F1: Current Balance | G1: Savings | H1: Remaining | I1: Balance at Due | J1: Due Date | K1: Notes
A2: Brookstone (Doors) | B2: FinanceIt | C2: 9647.52 | D2: 54.4 | E2: 525 | F2: 9303.72 | G2: 2103.5 | H2: =F2-G2 -> 7200.22 | I2: 8487.72 | J2: 46419 | K2: 0% interest for 24 months
A3: Home Depot (Range) | B3: Home Depot CC | C3: 3524.47 | D3: 35 | F3: 1728.04 | I3: 1728.04 | J3: 46478 | K3: 0% interest for 24 months
A4: Tangerine Line of Credit | B4: Tangerine | C4: 5907.78 | F4: 5907.78
A5: Total: | C5: =SUM(C2:C4) -> 19079.77 | F5: =SUM(F2:F4) -> 16939.54
A8: Potential Loans
A9: HandyBros (WaterHeater/Furnace/Heatpump) | B9: FinanceIt | C9: 20376.16 | K9: 0% interest for 90 days
A10: HandyBros (WaterHeater/Furnace/Heatpump) | B10: Canada Greener Homes Loan | C10: 20376.16 | K10: 0% interest for 20 years

Sheet 2025 - Expenses
A1: Sep | B1: Municipal Taxes | C1: Hydro | D1: Gas | E1: Internet | F1: Mortgage | G1: Reliance | H1: Security | I1: Mobile | J1: Car Insurance | K1: Home Insurance | L1: Pet Insurance | M1: Car Payment | N1: Alcohol | O1: Apple Sub | P1: Cannabis | Q1: Canva Sub | R1: Car Expenses | S1: Charity | T1: Clothes | U1: Coffee | V1: Daycare | W1: Dine-In | X1: Entertainment | Y1: Gas | Z1: Gifts | AA1: Groceries | AB1: Health & Beauty | AC1: Home | AD1: Ipsy Sub | AE1: Misc | AF1: Newspaper | AG1: Pet Food/Toys | AH1: Prime Video Sub | AI1: Spotify | AJ1: Takeout | AK1: Travel | AL1: Uber | AM1: Vet Bill | AN1: YouTube
A2: Jan | B2: 0 | C2: ='Jan-2025'!B19 -> 229.3 | D2: ='Jan-2025'!B18 -> 184.62 | E2: ='Jan-2025'!B13 -> 0 | F2: ='Jan-2025'!B10 -> 1711.29 | G2: ='Jan-2025'!B11 -> 39.64 | H2: ='Jan-2025'!B15 -> 39.55 | I2: ='Jan-2025'!B17 -> 526.15 | J2: ='Jan-2025'!B14 -> 161.78 | K2: ='Jan-2025'!B12 -> 211.95 | L2: ='Jan-2025'!B16 -> 220.92 | M2: ='Jan-2025'!B20 -> 317.16 | N2: =0 -> 0 | O2: ='Jan-2025 (CC)'!G8 -> 97.41 | P2: ='Jan-2025 (CC)'!G9 -> 359.31 | Q2: ='Jan-2025 (CC)'!G10 -> 19 | R2: 0 | S2: ='Jan-2025 (CC)'!G11 -> 250 | T2: =0 -> 0 | U2: ='Jan-2025 (CC)'!G12 -> 278.2 | V2: ='Jan-2025 (CC)'!G13 -> 714.49 | W2: ='Jan-2025 (CC)'!G14 -> 461.95 | X2: ='Jan-2025 (CC)'!G15 -> 237.35 | Y2: ='Jan-2025 (CC)'!G16 -> 172.5 | Z2: ='Jan-2025 (CC)'!G17 -> 159.89 | AA2: ='Jan-2025 (CC)'!G18 -> 1332.16 | AB2: ='Jan-2025 (CC)'!G19 -> 299.64 | AC2: ='Jan-2025 (CC)'!G20 -> 478.95 | AD2: ='Jan-2025 (CC)'!G21 -> 70.11 | AE2: ='Jan-2025 (CC)'!G22 -> 1773.15 | AF2: ='Jan-2025 (CC)'!G25 -> 72.22 | AG2: ='Jan-2025 (CC)'!G27 -> 714.53 | AH2: ='Jan-2025 (CC)'!G28 -> 119.68 | AI2: ='Jan-2025 (CC)'!G30 -> 20.22 | AJ2: ='Jan-2025 (CC)'!G31 -> 178.7 | AK2: ='Jan-2025 (CC)'!G33 -> 2529.24 | AL2: ='Jan-2025 (CC)'!G34 -> 13.32 | AM2: =0 -> 0 | AN2: ='Jan-2025 (CC)'!G35 -> 14.68
A3: Feb | B3: 1047 | C3: ='Feb-2025'!B19 -> 258.4 | D3: ='Feb-2025'!B18 -> 125.71 | E3: ='Feb-2025'!B13 -> 0 | F3: ='Feb-2025'!B10 -> 1711.29 | G3: ='Feb-2025'!B11 -> 39.64 | H3: ='Feb-2025'!B15 -> 39.55 | I3: ='Feb-2025'!B17 -> 110.13 | J3: ='Feb-2025'!B14 -> 161.78 | K3: ='Feb-2025'!B12 -> 211.95 | L3: ='Feb-2025'!B16 -> 236.5 | M3: ='Feb-2025'!B20 -> 317.16 | N3: =0 -> 0 | O3: ='Feb-2025 (CC)'!G8 -> 156.99 | P3: ='Feb-2025 (CC)'!G9 -> 165.5 | Q3: ='Feb-2025 (CC)'!G10 -> 19 | R3: =0 -> 0 | S3: ='Feb-2025 (CC)'!G11 -> 50 | T3: ='Feb-2025 (CC)'!G12 -> 421.75 | U3: ='Feb-2025 (CC)'!G13 -> 35.3 | V3: ='Feb-2025 (CC)'!G14 -> 527.15 | W3: ='Feb-2025 (CC)'!G15 -> 135.32 | X3: ='Feb-2025 (CC)'!G16 -> 198.05 | Y3: ='Feb-2025 (CC)'!G17 -> 122.44 | Z3: ='Feb-2025 (CC)'!G18 -> 103.95 | AA3: ='Feb-2025 (CC)'!G19 -> 684.78 | AB3: ='Feb-2025 (CC)'!G20 -> 323.22 | AC3: ='Feb-2025 (CC)'!G21 -> 101.68 | AD3: ='Feb-2025 (CC)'!G23 -> 80.1 | AE3: ='Feb-2025 (CC)'!G24 -> 170.12 | AF3: ='Feb-2025 (CC)'!G27 -> 129.9 | AG3: ='Feb-2025 (CC)'!G29 -> 539.18 | AH3: ='Feb-2025 (CC)'!G30 -> 154.71 | AI3: ='Feb-2025 (CC)'!G32 -> 20.22 | AJ3: ='Feb-2025 (CC)'!G33 -> 533.34 | AK3: ='Feb-2025 (CC)'!G35 -> 1488.89 | AL3: ='Feb-2025 (CC)'!G36 -> 44.09 | AM3: ='Feb-2025 (CC)'!G37 -> 380.31 | AN3: ='Feb-2025 (CC)'!G38 -> 14.68
A4: Mar | B4: 1046.13 | C4: ='Mar-2025'!B19 -> 257.58 | D4: ='Mar-2025'!B18 -> 173.47 | E4: ='Apr-2025'!B13 -> 0 | F4: ='Mar-2025'!B10 -> 1711.29 | G4: ='Mar-2025'!B11 -> 39.64 | H4: ='Mar-2025'!B15 -> 39.55 | I4: ='Mar-2025'!B17 -> 293.64 | J4: ='Mar-2025'!B14 -> 161.78 | K4: ='Mar-2025'!B12 -> 211.95 | L4: ='Mar-2025'!B16 -> 220.92 | M4: ='Mar-2025'!B20 -> 317.16 | N4: ='Mar-2025 (CC)'!G17 -> 210.17 | O4: ='Mar-2025 (CC)'!G18 -> 227.07 | P4: ='Mar-2025 (CC)'!G19 -> 284.47 | Q4: 0 | R4: 0 | S4: ='Mar-2025 (CC)'!G20 -> 50 | T4: ='Mar-2025 (CC)'!G21 -> 350.3 | U4: ='Mar-2025 (CC)'!G22 -> 277.56 | V4: ='Mar-2025 (CC)'!G23 -> 540.52 | W4: ='Mar-2025 (CC)'!G24 -> 516.07 | X4: ='Mar-2025 (CC)'!G25 -> 131.68 | Y4: ='Mar-2025 (CC)'!G26 -> 56.6 | Z4: ='Mar-2025 (CC)'!G27 -> 150 | AA4: ='Mar-2025 (CC)'!G28 -> 1396.3 | AB4: ='Mar-2025 (CC)'!G29 -> 44.36 | AC4: ='Mar-2025 (CC)'!G30 -> 135.64 | AD4: =0 -> 0 | AE4: ='Mar-2025 (CC)'!G31 -> 1917.84 | AF4: =0 -> 0 | AG4: ='Mar-2025 (CC)'!G35 -> 645.63 | AH4: ='Mar-2025 (CC)'!G36 -> 77.9 | AI4: ='Mar-2025 (CC)'!G38 -> 20.22 | AJ4: ='Mar-2025 (CC)'!G39 -> 435.68 | AK4: ='Mar-2025 (CC)'!G41 -> 3679.9 | AL4: ='Mar-2025 (CC)'!G42 -> 34.8 | AM4: =0 -> 0 | AN4: =0 -> 0
A5: Apr | B5: 0 | C5: ='Apr-2025'!B19 -> 193.49 | D5: ='Apr-2025'!B18 -> 75.41 | E5: ='Apr-2025'!B13 -> 0 | F5: ='Apr-2025'!B10 -> 1711.29 | G5: ='Apr-2025'!B11 -> 39.64 | H5: ='Apr-2025'!B15 -> 45.2 | I5: ='Apr-2025'!B17 -> 141.32 | J5: ='Apr-2025'!B14 -> 153.15 | K5: ='Apr-2025'!B12 -> 211.95 | L5: ='Apr-2025'!B16 -> 236.5 | M5: ='Apr-2025'!B21 -> 317.16 | N5: ='Apr-2025 (CC)'!G5 -> 52.35 | O5: ='Apr-2025 (CC)'!G6 -> 133.26 | P5: ='Apr-2025 (CC)'!G7 -> 276.17 | Q5: ='Apr-2025 (CC)'!G8 -> 38 | R5: ='Apr-2025 (CC)'!G9 -> 1900.12 | S5: =0 -> 0 | T5: ='Apr-2025 (CC)'!G10 -> 394.98 | U5: ='Apr-2025 (CC)'!G11 -> 290.77 | V5: ='Apr-2025 (CC)'!G12 -> 524.95 | W5: ='Apr-2025 (CC)'!G13 -> 216.58 | X5: ='Apr-2025 (CC)'!G14 -> 980.01 | Y5: ='Apr-2025 (CC)'!G15 -> 130.62 | Z5: ='Apr-2025 (CC)'!G16 -> 730.3 | AA5: ='Apr-2025 (CC)'!G17 -> 1202.29 | AB5: ='Apr-2025 (CC)'!G18 -> 236.52 | AC5: ='Apr-2025 (CC)'!G19 -> 3043.77 | AD5: ='Apr-2025 (CC)'!G22 -> 127.45 | AE5: ='Apr-2025 (CC)'!G23 -> 473.42 | AF5: ='Apr-2025 (CC)'!G25 -> 99.33 | AG5: ='Apr-2025 (CC)'!G27 -> 718.75 | AH5: ='Apr-2025 (CC)'!G28 -> 144.54 | AI5: ='Apr-2025 (CC)'!G30 -> 20.22 | AJ5: ='Apr-2025 (CC)'!G31 -> 734.2 | AK5: ='Apr-2025 (CC)'!G33 -> 1976.59 | AL5: ='Apr-2025 (CC)'!G34 -> 11.29 | AM5: ='Apr-2025 (CC)'!G35 -> 1069.05 | AN5: ='Apr-2025 (CC)'!G36 -> 29.36
A6: May | B6: 0 | C6: ='May-2025'!B19 -> 223.45 | D6: ='May-2025'!B18 -> 68.28 | E6: ='May-2025'!B13 -> 0 | F6: ='May-2025'!B10 -> 1711.29 | G6: ='May-2025'!B11 -> 39.64 | H6: ='May-2025'!B15 -> 45.2 | I6: ='May-2025'!B17 -> 93.86 | J6: ='May-2025'!B14 -> 161.78 | K6: ='May-2025'!B12 -> 211.95 | L6: ='May-2025'!B16 -> 242.75 | M6: ='May-2025'!B22 -> 317.16 | N6: ='May-2025 (CC)'!G5 -> 429.07 | O6: ='May-2025 (CC)'!G6 -> 107.29 | P6: ='May-2025 (CC)'!G7 -> 265.16 | Q6: ='May-2025 (CC)'!G8 -> 19 | R6: 0 | S6: ='May-2025 (CC)'!G9 -> 50 | T6: ='May-2025 (CC)'!G10 -> 355.67 | U6: ='May-2025 (CC)'!G11 -> 355.83 | V6: ='May-2025 (CC)'!G12 -> 637.49 | W6: ='May-2025 (CC)'!G13 -> 393.17 | X6: ='May-2025 (CC)'!G14 -> 48.12 | Y6: ='May-2025 (CC)'!G15 -> 99 | Z6: ='May-2025 (CC)'!G16 -> 134.23 | AA6: ='May-2025 (CC)'!G17 -> 1326.4 | AB6: ='May-2025 (CC)'!G18 -> 146.82 | AC6: ='May-2025 (CC)'!G19 -> 1081.6 | AD6: ='May-2025 (CC)'!G22 -> 58.04 | AE6: ='May-2025 (CC)'!G23 -> 1211.11 | AF6: ='May-2025 (CC)'!G26 -> 143.46 | AG6: ='May-2025 (CC)'!G28 -> 546.85 | AH6: ='May-2025 (CC)'!G29 -> 105 | AI6: ='May-2025 (CC)'!G31 -> 20.22 | AJ6: ='May-2025 (CC)'!G32 -> 439 | AK6: ='May-2025 (CC)'!G34 -> 5191.25 | AL6: ='May-2025 (CC)'!G35 -> 18.92 | AM6: ='May-2025 (CC)'!G36 -> 282.9 | AN6: ='May-2025 (CC)'!G37 -> 14.68
A7: Jun | B7: 1029 | C7: ='Jun-2025'!B19 -> 207.16 | D7: ='Jun-2025'!B18 -> 0 | E7: ='Jun-2025'!B13 -> 56.5 | F7: ='Jun-2025'!B10 -> 1711.29 | G7: ='Jun-2025'!B11 -> 115.65 | H7: ='Jun-2025'!B15 -> 45.2 | I7: ='Jun-2025'!B17 -> 93.86 | J7: ='Jun-2025'!B14 -> 161.78 | K7: ='Jun-2025'!B12 -> 211.95 | L7: ='Jun-2025'!B16 -> 242.75 | M7: ='Jun-2025'!B20 -> 317.16 | N7: ='Jun-2025 (CC)'!G5 -> 210.1 | O7: ='Jun-2025 (CC)'!G6 -> 235.42 | P7: ='Jun-2025 (CC)'!G6 -> 235.42 | R7: 0 | S7: ='Jun-2025 (CC)'!G7 -> 50 | T7: 0 | U7: ='Jun-2025 (CC)'!G10 -> 180.78 | V7: ='Jun-2025 (CC)'!G9 -> 316.25 | W7: =0 -> 0 | X7: ='Jun-2025 (CC)'!G11 -> 591.16 | Y7: ='Jun-2025 (CC)'!G12 -> 284.1 | Z7: ='Jun-2025 (CC)'!G13 -> 22.59 | AA7: ='Jun-2025 (CC)'!G16 -> 696.53 | AB7: ='Jun-2025 (CC)'!G15 -> 245.11 | AC7: ='Jun-2025 (CC)'!G16 -> 696.53 | AD7: ='Jun-2025 (CC)'!G19 -> 8.5 | AE7: ='Jun-2025 (CC)'!G22 -> 166.36 | AF7: ='Jun-2025 (CC)'!G22 -> 166.36 | AG7: ='Jun-2025 (CC)'!G24 -> 254.55 | AH7: ='Jun-2025 (CC)'!G25 -> 194.24 | AI7: ='Jun-2025 (CC)'!G27 -> 20.22 | AJ7: ='Jun-2025 (CC)'!G28 -> 632.42 | AK7: ='Jun-2025 (CC)'!G30 -> 1071.32 | AL7: ='Jun-2025 (CC)'!G31 -> 14.29 | AM7: =0 -> 0 | AN7: =0 -> 0
A8: Jul | B8: 0 | C8: ='Jul-2025'!B18 -> 248.04 | D8: ='Jul-2025'!B17 -> 25.57 | E8: ='Jul-2025'!B12 -> 56.5 | F8: ='Jul-2025'!B10 -> 1711.29 | G8: =0 -> 0 | H8: ='Jul-2025'!B14 -> 45.2 | I8: ='Jul-2025 (CC)'!G21 -> 172.96 | J8: ='Jul-2025'!B13 -> 151.61 | K8: ='Jul-2025'!B11 -> 146.21 | L8: ='Jul-2025'!B15 -> 242.75 | M8: ='Jul-2025'!B19 -> 158.58 | N8: ='Jul-2025 (CC)'!G5 -> 123.12 | O8: ='Jul-2025 (CC)'!G6 -> 245.67 | P8: ='Jul-2025 (CC)'!G7 -> 98.46 | Q8: 0 | R8: 0 | S8: ='Jul-2025 (CC)'!G9 -> 50 | T8: =0 -> 0 | U8: ='Jul-2025 (CC)'!G10 -> 93.5 | V8: ='Jul-2025 (CC)'!G11 -> 785.77 | W8: =0 -> 0 | X8: ='Jul-2025 (CC)'!G12 -> 306.24 | Y8: ='Jul-2025 (CC)'!G13 -> 263.57 | Z8: ='Jul-2025 (CC)'!G14 -> 36.35 | AA8: ='Jul-2025 (CC)'!G15 -> 797.44 | AB8: ='Jul-2025 (CC)'!G16 -> 8.99 | AC8: ='Jul-2025 (CC)'!G17 -> 125.69 | AD8: =0 -> 0 | AE8: ='Jul-2025 (CC)'!G20 -> 155.07 | AF8: =0 -> 0 | AG8: ='Jul-2025 (CC)'!G23 -> 591.71 | AH8: ='Jul-2025 (CC)'!G24 -> 41.76 | AI8: ='Jul-2025 (CC)'!G25 -> 20.22 | AJ8: ='Jul-2025 (CC)'!G26 -> 600.01 | AK8: ='Jul-2025 (CC)'!G28 -> 2030.29 | AL8: ='Jul-2025 (CC)'!G29 -> 32.09 | AM8: =0 -> 0 | AN8: =0 -> 0
A9: Aug | B9: 1029 | C9: ='Aug-2025'!B18 -> 378.68 | D9: ='Aug-2025'!B17 -> 44.34 | E9: ='Aug-2025'!B12 -> 56.5 | F9: ='Aug-2025'!B10 -> 1711.29 | G9: =0 -> 0 | H9: 0 | I9: ='Aug-2025 (CC)'!G20 -> 118.72 | J9: ='Aug-2025'!B13 -> 151.61 | K9: ='Aug-2025'!B11 -> 146.21 | L9: ='Aug-2025'!B15 -> 242.75 | M9: =0 -> 0 | N9: ='Aug-2025 (CC)'!G5 -> 291.34 | O9: ='Aug-2025 (CC)'!G6 -> 86.36 | P9: =0 -> 0 | Q9: =0 -> 0 | R9: ='Aug-2025 (CC)'!G7 -> 15.81 | S9: ='Aug-2025 (CC)'!G8 -> 50 | T9: =0 -> 0 | U9: ='Aug-2025 (CC)'!G9 -> 131.94 | V9: ='Aug-2025 (CC)'!G10 -> 316.21 | W9: ='Aug-2025 (CC)'!G11 -> 45.2 | X9: ='Aug-2025 (CC)'!G12 -> 1075.5 | Y9: ='Aug-2025 (CC)'!G13 -> 186.01 | Z9: =0 -> 0 | AA9: ='Aug-2025 (CC)'!G14 -> 1165.84 | AB9: ='Aug-2025 (CC)'!G15 -> 135.9 | AC9: ='Aug-2025 (CC)'!G16 -> 233.77 | AD9: =0 -> 0 | AE9: ='Aug-2025 (CC)'!G19 -> 208.99 | AF9: ='Aug-2025 (CC)'!G21 -> 107.35 | AG9: ='Aug-2025 (CC)'!G23 -> 425.4 | AH9: ='Aug-2025 (CC)'!G24 -> 66.61 | AI9: ='Aug-2025 (CC)'!G25 -> 36.02 | AJ9: ='Aug-2025 (CC)'!G26 -> 312.9 | AK9: =0 -> 0 | AL9: ='Aug-2025 (CC)'!G27 -> 40.09 | AM9: ='Aug-2025 (CC)'!G28 -> 608.89 | AN9: =0 -> 0
A10: Sep | B10: 0 | C10: ='Sep-2025'!B18 -> 346.22 | D10: ='Sep-2025'!B17 -> 40.76 | E10: ='Sep-2025'!B12 -> 56.5 | F10: ='Sep-2025'!B10 -> 1967.98 | G10: =0 -> 0 | H10: ='Sep-2025 (CC)'!G22 -> 91.72 | I10: ='Sep-2025 (CC)'!G16 -> 110.13 | K10: 146.21 | L10: ='Sep-2025'!B15 -> 242.75 | M10: =0 -> 0 | N10: ='Sep-2025 (CC)'!G5 -> 15.98 | O10: ='Sep-2025 (CC)'!G6 -> 133.81 | P10: =0 -> 0 | R10: 0 | S10: ='Sep-2025 (CC)'!G7 -> 50 | T10: =0 -> 0 | U10: =0 -> 0 | V10: ='Sep-2025 (CC)'!G8 -> 348.3 | W10: =0 -> 0 | X10: ='Sep-2025 (CC)'!G9 -> 147.11 | Y10: ='Sep-2025 (CC)'!G10 -> 107.5 | Z10: =0 -> 0 | AA10: ='Sep-2025 (CC)'!G11 -> 683.4 | AB10: ='Sep-2025 (CC)'!G12 -> 87.5 | AC10: ='Sep-2025 (CC)'!G13 -> 678 | AE10: ='Sep-2025 (CC)'!G15 -> 677.07 | AF10: =0 -> 0 | AG10: ='Sep-2025 (CC)'!G18 -> 422.55 | AH10: ='Sep-2025 (CC)'!G19 -> 53.05 | AI10: ='Sep-2025 (CC)'!G20 -> 36.02 | AJ10: ='Sep-2025 (CC)'!G21 -> 209.24 | AK10: =0 -> 0 | AL10: ='Sep-2025 (CC)'!G23 -> 58.26 | AM10: =0 -> 0
A11: Oct | B11: 1028.93 | C11: ='Oct-2025'!B18 -> 291.71 | D11: ='Oct-2025'!B17 -> 38.45 | E11: ='Oct-2025'!B12 -> 56.5 | F11: ='Oct-2025'!B10 -> 1967.98 | G11: =0 -> 0 | H11: ='Oct-2025 (CC)'!G28 -> 45.2 | I11: ='Oct-2025 (CC)'!G21 -> 93.86 | K11: 146.21 | L11: ='Oct-2025'!B15 -> 257.21 | M11: =0 -> 0 | N11: ='Oct-2025 (CC)'!G5 -> 172.94 | O11: ='Oct-2025 (CC)'!G6 -> 43.44 | P11: =0 -> 0 | R11: 0 | S11: ='Oct-2025 (CC)'!G7 -> 50 | T11: ='Oct-2025 (CC)'!G8 -> 163.82 | U11: ='Oct-2025 (CC)'!G9 -> 122.76 | V11: ='Oct-2025 (CC)'!G10 -> 576.96 | W11: ='Oct-2025 (CC)'!G11 -> 177.98 | X11: ='Oct-2025 (CC)'!G12 -> 283.39 | Y11: ='Oct-2025 (CC)'!G13 -> 192.94 | Z11: ='Oct-2025 (CC)'!G14 -> 175.7 | AA11: ='Oct-2025 (CC)'!G15 -> 584.54 | AB11: ='Oct-2025 (CC)'!G16 -> 374.74 | AC11: ='Oct-2025 (CC)'!G17 -> 144.64 | AE11: ='Oct-2025 (CC)'!G20 -> 297.78 | AF11: ='Oct-2025 (CC)'!G22 -> 107.35 | AG11: ='Oct-2025 (CC)'!G24 -> 599.94 | AH11: ='Oct-2025 (CC)'!G25 -> 181.1 | AI11: ='Oct-2025 (CC)'!G26 -> 36.02 | AJ11: ='Oct-2025 (CC)'!G27 -> 439.01 | AK11: ='Oct-2025 (CC)'!G29 -> 821.61 | AL11: ='Oct-2025 (CC)'!G30 -> 21.92 | AM11: =0 -> 0
A12: Nov | B12: 0 | C12: ='Nov-2025'!B18 -> 243.09 | D12: ='Nov-2025'!B17 -> 62.26 | E12: 79.1 | F12: ='Nov-2025'!B10 -> 1967.98 | G12: =0 -> 0 | H12: ='Nov-2025 (CC)'!G27 -> 45.2 | I12: ='Nov-2025 (CC)'!G22 -> 105.16 | K12: 146.21 | L12: ='Nov-2025'!B15 -> 257.21 | M12: =0 -> 0 | N12: ='Nov-2025 (CC)'!G5 -> 40.2 | O12: ='Nov-2025 (CC)'!G6 -> 77.33 | P12: ='Nov-2025 (CC)'!G7 -> 142.97 | R12: ='Nov-2025 (CC)'!G8 -> 1092.62 | S12: ='Nov-2025 (CC)'!G9 -> 50 | T12: =0 -> 0 | U12: ='Nov-2025 (CC)'!G10 -> 122.76 | V12: ='Nov-2025 (CC)'!G11 -> 800.17 | W12: ='Nov-2025 (CC)'!G13 -> 668.11 | X12: ='Nov-2025 (CC)'!G14 -> 64.79 | Y12: ='Nov-2025 (CC)'!G15 -> 77.14 | Z12: ='Nov-2025 (CC)'!G16 -> 158.95 | AA12: ='Nov-2025 (CC)'!G17 -> 1053.96 | AB12: =0 -> 0 | AC12: ='Nov-2025 (CC)'!G18 -> 6645.71 | AE12: ='Nov-2025 (CC)'!G21 -> 385.89 | AF12: =0 -> 0 | AG12: =0 -> 0 | AH12: ='Nov-2025 (CC)'!G24 -> 44.57 | AI12: ='Nov-2025 (CC)'!G25 -> 36.02 | AJ12: ='Nov-2025 (CC)'!G26 -> 417.48 | AK12: ='Nov-2025 (CC)'!G28 -> 416.76 | AL12: ='Nov-2025 (CC)'!G29 -> 28.58 | AM12: =0 -> 0
A13: Dec | B13: 0 | C13: ='Dec-2025'!B18 -> 214.44 | D13: ='Dec-2025'!B17 -> 107.14 | E13: 79.1 | F13: ='Dec-2025'!B10 -> 1967.98 | G13: =0 -> 0 | H13: ='Dec-2025 (CC)'!G19 -> 45.2 | K13: 146.21 | L13: ='Dec-2025'!B15 -> 257.21 | M13: =0 -> 0 | N13: ='Dec-2025 (CC)'!G5 -> 99.35 | O13: ='Dec-2025 (CC)'!G6 -> 681.31 | P13: =0 -> 0 | R13: 0 | S13: ='Dec-2025 (CC)'!G7 -> 50 | T13: =0 -> 0 | U13: ='Dec-2025 (CC)'!G8 -> 122.76 | V13: ='Dec-2025 (CC)'!G9 -> 272.12 | W13: =0 -> 0 | X13: ='Dec-2025 (CC)'!G11 -> 228.6 | Y13: ='Dec-2025 (CC)'!G12 -> 154.77 | Z13: ='Dec-2025 (CC)'!G13 -> 734.28 | AA13: ='Dec-2025 (CC)'!G14 -> 479.72 | AB13: =0 -> 0 | AC13: =0 -> 0 | AE13: ='Dec-2025 (CC)'!G16 -> 269.24 | AF13: =0 -> 0 | AG13: =0 -> 0 | AH13: ='Dec-2025 (CC)'!G17 -> 42.89 | AI13: =0 -> 0 | AJ13: ='Dec-2025 (CC)'!G18 -> 141.66 | AK13: ='Dec-2025 (CC)'!G20 -> 1298.91 | AL13: ='Dec-2025 (CC)'!G21 -> 41.19 | AM13: =0 -> 0
A15: AVG | B15: =average('2025 - Expenses'!$B$2:$B$13) -> 431.67167 | C15: =average('2025 - Expenses'!$C$2:$C$13) -> 257.63 | D15: =AVERAGE('2025 - Expenses'!$Y$2:$Y$13) -> 153.9325 | E15: =AVERAGE('2025 - Expenses'!$E$2:$E$13) -> 36.725 | F15: =AVERAGE('2025 - Expenses'!$F$2:$F$13) -> 1796.8533 | G15: =AVERAGE('2025 - Expenses'!$G$2:$G$13) -> 26.154167 | H15: =average('2025 - Expenses'!$H$2:$H$13) -> 43.8975 | I15: =AVERAGE('2025 - Expenses'!$I$2:$I$13) -> 169.07182 | J15: =AVERAGE('2025 - Expenses'!$J$2:$J$13) -> 158.15875 | K15: =AVERAGE('2025 - Expenses'!$K$2:$K$13) -> 179.08 | L15: =AVERAGE('2025 - Expenses'!$L$2:$L$13) -> 241.685 | M15: =AVERAGE('2025 - Expenses'!$M$2:$M$13) -> 171.795 | N15: =AVERAGE('2025 - Expenses'!$N$2:$N$13) -> 137.05167 | O15: =AVERAGE('2025 - Expenses'!$O$2:$O$13) -> 185.44667 | P15: =AVERAGE('2025 - Expenses'!$P$2:$P$13) -> 152.28833 | Q15: =average('2025 - Expenses'!$Q$2:$Q$13) -> 13.571429 | R15: =average('2025 - Expenses'!$R$2:$R$13) -> 250.7125 | S15: =average('2025 - Expenses'!$S$2:$S$13) -> 62.5 | T15: =AVERAGE('2025 - Expenses'!$T$2:$T$13) -> 140.54333 | U15: =average('2025 - Expenses'!$U$2:$U$13) -> 167.68 | V15: =average('2025 - Expenses'!$V$2:$V$13) -> 530.03167 | W15: =average('2025 - Expenses'!$W$2:$W$13) -> 217.865 | X15: =average('2025 - Expenses'!$X$2:$X$13) -> 357.66667 | Y15: =average('2025 - Expenses'!$Y$2:$Y$13) -> 153.9325 | Z15: =average('2025 - Expenses'!$Z$2:$Z$13) -> 200.52 | AA15: =average('2025 - Expenses'!$AA$2:$AA$13) -> 950.28 | AB15: =average('2025 - Expenses'!$AB$2:$AB$13) -> 158.56667 | AC15: =average('2025 - Expenses'!$AC$2:$AC$13) -> 1113.8317 | AD15: =average('2025 - Expenses'!$AD$2:$AD$13) -> 43.025 | AE15: =average('2025 - Expenses'!$AE$2:$AE$13) -> 642.17 | AF15: =average('2025 - Expenses'!$AF$2:$AF$13) -> 68.830833 | AG15: =average('2025 - Expenses'!$AG$2:$AG$13) -> 454.92417 | AH15: =average('2025 - Expenses'!$AH$2:$AH$13) -> 102.17083 | AI15: =average('2025 - Expenses'!$AI$2:$AI$13) -> 23.801667 | AJ15: =average('2025 - Expenses'!$AJ$2:$AJ$13) -> 422.80333 | AK15: =average('2025 - Expenses'!$AK$2:$AK$13) -> 1708.73 | AL15: =average('2025 - Expenses'!$AL$2:$AL$13) -> 29.903333 | AM15: =average('2025 - Expenses'!$AM$2:$AM$13) -> 195.09583 | AN15: =average('2025 - Expenses'!$AN$2:$AN$13) -> 9.175
A16: TOTAL | B16: =SUM('2025 - Expenses'!$B$2:$B$13) -> 5180.06 | C16: =SUM('2025 - Expenses'!$C$2:$C$13) -> 3091.56 | D16: =sum(D2:D13) -> 946.01 | E16: =sum('2025 - Expenses'!$E$2:$E$13) -> 440.7 | F16: =sum('2025 - Expenses'!$F$2:$F$13) -> 21562.24 | G16: =sum('2025 - Expenses'!$G$2:$G$13) -> 313.85 | H16: =SUM('2025 - Expenses'!$H$2:$H$13) -> 526.77 | I16: =SUM('2025 - Expenses'!$I$2:$I$13) -> 1859.79 | J16: =sum('2025 - Expenses'!$J$2:$J$13) -> 1265.27 | K16: =SUM('2025 - Expenses'!$K$2:$K$13) -> 2148.96 | L16: =SUM('2025 - Expenses'!$L$2:$L$13) -> 2900.22 | M16: =SUM('2025 - Expenses'!$M$2:$M$13) -> 2061.54 | N16: =SUM('2025 - Expenses'!$N$2:$N$13) -> 1644.62 | O16: =SUM('2025 - Expenses'!$O$2:$O$13) -> 2225.36 | P16: =SUM('2025 - Expenses'!$P$2:$P$13) -> 1827.46 | Q16: =SUM('2025 - Expenses'!$Q$2:$Q$13) -> 95 | R16: =SUM('2025 - Expenses'!$R$2:$R$13) -> 3008.55 | S16: =SUM('2025 - Expenses'!$S$2:$S$13) -> 750 | T16: =SUM('2025 - Expenses'!$T$2:$T$13) -> 1686.52 | U16: =SUM('2025 - Expenses'!$U$2:$U$13) -> 2012.16 | V16: =SUM('2025 - Expenses'!$V$2:$V$13) -> 6360.38 | W16: =SUM('2025 - Expenses'!$W$2:$W$13) -> 2614.38 | X16: =SUM('2025 - Expenses'!$X$2:$X$13) -> 4292 | Y16: =SUM('2025 - Expenses'!$Y$2:$Y$13) -> 1847.19 | Z16: =SUM('2025 - Expenses'!$Z$2:$Z$13) -> 2406.24 | AA16: =SUM('2025 - Expenses'!$AA$2:$AA$13) -> 11403.36 | AB16: =SUM('2025 - Expenses'!$AB$2:$AB$13) -> 1902.8 | AC16: =SUM('2025 - Expenses'!$AC$2:$AC$13) -> 13365.98 | AD16: =SUM('2025 - Expenses'!$AD$2:$AD$13) -> 344.2 | AE16: =SUM('2025 - Expenses'!$AE$2:$AE$13) -> 7706.04 | AF16: =SUM('2025 - Expenses'!$AF$2:$AF$13) -> 825.97 | AG16: =SUM('2025 - Expenses'!$AG$2:$AG$13) -> 5459.09 | AH16: =SUM('2025 - Expenses'!$AH$2:$AH$13) -> 1226.05 | AI16: =SUM('2025 - Expenses'!$AI$2:$AI$13) -> 285.62 | AJ16: =SUM('2025 - Expenses'!$AJ$2:$AJ$13) -> 5073.64 | AK16: =SUM('2025 - Expenses'!$AK$2:$AK$13) -> 20504.76 | AL16: =SUM('2025 - Expenses'!$AL$2:$AL$13) -> 358.84 | AM16: =SUM('2025 - Expenses'!$AM$2:$AM$13) -> 2341.15 | AN16: =SUM('2025 - Expenses'!$AN$2:$AN$13) -> 73.4
B19: Jan-Apr | C19: May-Dec | D19: Total | E19: Divide by 2 | G19: =C20+C21+C22 -> 3249.19
A20: Hydro | B20: 745.28 | C20: =D20-B20 -> 2346.28 | D20: 3091.56 | E20: =D20/2 -> 1545.78
A21: Gas | B21: 483.8 | C21: =D21-B21 -> 462.21 | D21: 946.01 | E21: =D21/2 -> 473.005
A22: Internet | B22: 0 | C22: =D22-B22 -> 440.7 | D22: 440.7 | E22: =D22/2 -> 220.35
A23: Insurance | B23: =211.95*3 -> 635.85 | C23: =D23-B23 -> 1513.11 | D23: =2148.96 -> 2148.96 | E23: =D23/2 -> 1074.48
A24: Property Taxes | B24: =1047+1046.13 -> 2093.13 | C24: =D24-B24 -> 3086.93 | D24: =5180.06 -> 5180.06 | E24: =D24/2 -> 2590.03

Sheet Jan-2025 (CC)
A1: DATE | B1: ITEM | C1: AMOUNT | D1: CATEGORY
A2: 45681 | B2: GOODFOOD* GOODFOOD MAR | C2: 96.89 | D2: GROCERIES
A3: 45681 | B3: MANDARIN LONDON | C3: 64.94 | D3: DINE IN
A4: 45681 | B4: SPOTIFY STOCKHOLM | C4: 20.22 | D4: SPOTIFY SUB
A5: 45680 | B5: SESSIONS CANNABIS | C5: 72.5 | D5: CANNABIS
A6: 45679 | B6: METRO 150 LONDON | C6: 59.9 | D6: GROCERIES
A7: 45679 | B7: PETSMART INC. 2433 LONDON | C7: 118.64 | D7: PET FOOD/TOYS
A8: 45679 | B8: SCENTBIRD | C8: 32.64 | D8: HEALTH & BEAUTY
A9: 45678 | B9: AMAZON CHANNELS AMAZON.CA | C9: 11.29 | D9: PRIME VIDEO SUB
A10: 45678 | B10: ONE OF A KIND SHOW | C10: -7.24 | D10: PAYMENT
A11: 45677 | B11: DOGTOPIA OF LONDON 00-0 LONDON | C11: 125.43 | D11: DAY CARE
A12: 45677 | B12: DOMINOS PIZZA #10250 | C12: 50.9 | D12: TAKE OUT
A13: 45677 | B13: PETSMART INC. 2433 LONDON | C13: 55.81 | D13: PET FOOD/TOYS
... A121: 45680 | B121: PAYMENT - THANK YOU | C121: -1197.36 | D121: PAYMENT

Sheet Feb-2025 (CC)
A1: DATE | B1: ITEM | C1: AMOUNT | D1: CATEGORY
A2: 45712 | B2: UBER TRIP HTTPS://HELP.UB | C2: 3 | D2: UBER
A3: 45712 | B3: UBER TRIP HTTPS://HELP.UB | C3: 19.61 | D3: UBER
A4: 45712 | B4: ARAMARK/LONDON APT #53 LONDON | C4: 38.14 | D4: TAKE OUT
A5: 45712 | B5: HUEY MAGOOS LAKE NONA 0 ORLANDO | C5: 41.23 | D5: TAKE OUT
A6: 45712 | B6: SPOTIFY STOCKHOLM | C6: 20.22 | D6: SPOTIFY SUB
A7: 45712 | B7: DOGTOPIA OF LONDON 00-0 LONDON | C7: 125.43 | D7: DAY CARE
A8: 45712 | B8: LUSH Fresh Handmade Co | C8: 100 | D8: HEALTH & BEAUTY
A9: 45711 | B9: MCDONALD'S #1501 LONDON | C9: 31.39 | D9: TAKE OUT
A10: 45711 | B10: METRO 150 LONDON | C10: 2.92 | D10: GROCERIES
A11: 45711 | B11: FACTORY SHOE LONDON LONDON | C11: 242.93 | D11: CLOTHES
A12: 45711 | B12: SQ *LOCOMOTIVE ESPRESS | C12: 15.3 | D12: COFFEE
A13: 45710 | B13: UBER TRIP HTTPS://HELP.UB | C13: 18.48 | D13: UBER
... A121: 45713 | B121: SQ *CAFE #65115 DELRAY | C121: 15.81 | D121: TAKE OUT

Sheet Mar-2025 (CC)
A1: DATE | B1: ITEM | C1: AMOUNT | D1: CATEGORY
A2: 45740 | B2: SPOTIFY STOCKHOLM | C2: 20.22 | D2: SPOTIFY SUB
A3: 45740 | B3: THE HOME DEPOT #7274 NORTH YORK | C3: 41.81 | D3: HOME
A4: 45740 | B4: METRO 150 | C4: 65.1 | D4: GROCERIES
A5: 45740 | B5: SESSIONS CANNABIS | C5: 64 | D5: CANNABIS
A6: 45740 | B6: GLOBAL PET FOODS | C6: 156.14 | D6: PET FOOD/TOYS
A7: 45740 | B7: DOLLARAMA # 443 | C7: 10.45 | D7: MISC
A8: 45739 | B8: METRO 150 LONDON | C8: 190.3 | D8: GROCERIES
A9: 45739 | B9: THE HOME DEPOT #7274 NORTH YORK | C9: 65.47 | D9: HOME
A10: 45739 | B10: SHOPPERS DRUG MART #07 | C10: 26.34 | D10: HEALTH & BEAUTY
A11: 45739 | B11: LYNN'S BAKERY & DELI | C11: 18.42 | D11: GROCERIES
A12: 45739 | B12: STARBUCKS 800-782-7282 | C12: 10 | D12: COFFEE
A13: 45738 | B13: SQ *LOCOMOTIVE ESPRESS | C13: 22.76 | D13: COFFEE
... A114: 45720 | B114: APPLE.COM/BILL | C114: 3.38 | D114: APPLE SUB

Sheet Apr-2025 (CC)
A1: DATE | B1: ITEM | C1: AMOUNT | D1: CATEGORY
A2: 45741 | B2: THE HOME DEPOT #7274 NORTH YORK | C2: 503.99 | D2: HOME
A3: 45742 | B3: KOMOKA KILWORTH HOME HA KOMOKA | C3: 228.23 | D3: HOME
A4: 45742 | B4: THE GLOBE AND MAIL INC TORONTO | C4: 36.11 | D4: NEWSPAPERS
A5: 45743 | B5: COUNTRY PAWS BOARDING 2 LONDON | C5: 28.97 | D5: DAY CARE
A6: 45743 | B6: AMAZON CHANNELS AMAZON.CA | C6: 16.94 | D6: PRIME VIDEO SUB
A7: 45743 | B7: UBER CANADA/UBEREATS | C7: 46.46 | D7: TAKE OUT
A8: 45743 | B8: GOOGLE *YouTubePremium | C8: 14.68 | D8: YOUTUBE SUB
A9: 45744 | B9: LCBO/RAO #0575 LONDON LONDON | C9: 36.9 | D9: ALCOHOL
A10: 45744 | B10: CANADIAN TIRE #058 LONDON | C10: 391.88 | D10: HOME
A11: 45744 | B11: NIKU FARMS 647-5787639 | C11: -20 | D11: PAYMENT
A12: 45744 | B12: TIM HORTONS #0047 | C12: 7.13 | D12: COFFEE
A13: 45744 | B13: WORKWEEKLUNCH.COM | C13: 17.63 | D13: MISC
... A176: 45777 | B176: METRO 150 | C176: 64.59 | D176: GROCERIES

Sheet May-2025 (CC)
A1: DATE | B1: ITEM | C1: AMOUNT | D1: CATEGORY
A2: 45778 | B2: COUNTRY PAWS BOARDING 2 LONDON | C2: 34.62 | D2: DAY CARE
A3: 45778 | B3: HONK - CAN 866-675-7337 | C3: 3.1 | D3: TRAVEL
A4: 45778 | B4: START CA | C4: 56.5 | D4: INTERNET
A5: 45779 | B5: COMPANY BAR LONDON | C5: 199.33 | D5: DINE IN
A6: 45779 | B6: APPLE.COM/BILL | C6: 3.38 | D6: TRAVEL
A7: 45779 | B7: J.S. RYAN & CO | C7: 50 | D7: HEALTH & BEAUTY
A8: 45779 | B8: LONDON BIN RENTALS INC | C8: 423.75 | D8: HOME
A9: 45779 | B9: SP TONIC BLOOMS | C9: 134.23 | D9: GIFTS
A10: 45780 | B10: LONDON BREWING London | C10: 52.18 | D10: ALCOHOL
A11: 45780 | B11: NIKU FARMS 647-5787639 | C11: -17 | D11: PAYMENT
A12: 45780 | B12: WESTERN ANIMAL CLINIC | C12: 282.9 | D12: VET BILL
A13: 45780 | B13: WENDYS 114 | C13: 21.09 | D13: TAKE OUT
... A132: 45802 | B132: UBER TRIP HTTPS://HELP.UB | C132: 7.63 | D132: UBER

Sheet Jun-2025 (CC)
A1: DATE | B1: ITEM | C1: AMOUNT | D1: CATEGORY
A2: 45832 | B2: COUNTRY PAWS BOARDING 2 LONDON | C2: 32.35 | D2: DAY CARE
A3: 45832 | B3: SPOTIFY STOCKHOLM | C3: 20.22 | D3: SPOTIFY SUB
A4: 45832 | B4: ANC*ANCESTRY.CA | C4: 16.94 | D4: MISC
A5: 45832 | B5: SESSIONS CANNABIS | C5: 70 | D5: CANNABIS
A6: 45832 | B6: BLD* FLEXJOBS.COM | C6: 4.17 | D6: MISC
A7: 45831 | B7: ENTERPRISE CANADA C102 LONDON | C7: 241.61 | D7: TRAVEL
A8: 45831 | B8: PEARSON PARKING RESERVE TORONTO | C8: 141.25 | D8: TRAVEL
A9: 45831 | B9: UBER CANADA/UBEREATS | C9: 46.1 | D9: TAKE OUT
A10: 45830 | B10: CINEPLEX #7112 QP LONDON | C10: 53.68 | D10: ENTERTAINMENT
A11: 45830 | B11: CINEPLEX #7112 QP LONDON | C11: 54.76 | D11: ENTERTAINMENT
A12: 45830 | B12: ULTRAMAR #42441 ULTRAMA WHITBY | C12: 2.3 | D12: GAS
A13: 45830 | B13: ULTRAMAR #42441 ULTRAMA WHITBY | C13: 100.03 | D13: GAS
... A138: 45833 | B138: PAYMENT - THANK YOU | C138: -654.09 | D138: PAYMENT

Sheet Jul-2025 (CC)
A1: DATE | B1: ITEM | C1: AMOUNT | D1: CATEGORY
A2: 45867 | B2: PAYMENT RECEIVED - THANK YOU | C2: -5803.08 | D2: PAYMENT
A3: 45860 | B3: COUNTRY PAWS BOARDING 2 LONDON | C3: 28.97 | D3: DAY CARE
A4: 45860 | B4: METRO 150 LONDON | C4: 49.08 | D4: GROCERIES
A5: 45860 | B5: NESTLÉ CANADA INC TORONTO | C5: 90.4 | D5: COFFEE
A6: 45858 | B6: BANK BAO | C6: -5 | D6: PAYMENT
A7: 45858 | B7: COUNTRY PAWS BOARDING 2 LONDON | C7: 62.14 | D7: DAY CARE
A8: 45857 | B8: BANK BAO 001 TORONTO | C8: 27.12 | D8: TAKE OUT
A9: 45857 | B9: BLOOD BROTHERS BREWING TORONTO | C9: 19.66 | D9: ALCOHOL
A10: 45857 | B10: GENUWINE IMPORTS | C10: -5 | D10: PAYMENT
A11: 45857 | B11: GENUWINE IMPORTS Toronto | C11: 34.67 | D11: ALCOHOL
A12: 45857 | B12: PIONEER 43368 PIONEER 4 LONDON | C12: 49.31 | D12: GAS
A13: 45857 | B13: RURU BAKED INC 001 TORONTO | C13: 16 | D13: TAKE OUT
... A108: 45863 | B108: SPIRITLEAF KEMPTVILLE | C108: 44.06 | D108: CANNABIS

Sheet Aug-2025 (CC)
A1: DATE | B1: ITEM | C1: AMOUNT | D1: CATEGORY
A2: 45879 | B2: APPLE.COM/BILL TORONTO | C2: 4.51 | D2: APPLE SUB
A3: 45879 | B3: MEMBERSHIP FEE INSTALLMENT | C3: 12.99 | D3: MISC
A4: 45878 | B4: LONDON OK MART 001 LONDON | C4: 24.57 | D4: ALCOHOL
A5: 45877 | B5: METRO 150 LONDON | C5: 49.95 | D5: GROCERIES
A6: 45877 | B6: THE ECONOMIST The Econo NEW YORK | C6: 107.35 | D6: NEWSPAPERS
A7: 45876 | B7: COUNTRY PAWS BOARDING 2 LONDON | C7: 11.01 | D7: DAY CARE
A8: 45876 | B8: COUNTRY PAWS BOARDING 2 LONDON | C8: 28.97 | D8: DAY CARE
A9: 45876 | B9: METRO 150 LONDON | C9: 56.85 | D9: GROCERIES
A10: 45875 | B10: CINEPLEX #8030 WEB QP TORONTO | C10: 22.58 | D10: ENTERTAINMENT
A11: 45875 | B11: SP ODDBUNCH LONDON | C11: 35.99 | D11: GROCERIES
A12: 45874 | B12: COUNTRY PAWS BOARDING 2 LONDON | C12: 28.97 | D12: DAY CARE
A13: 45873 | B13: CINEPLEX #7112 QP LONDON | C13: 48.82 | D13: ENTERTAINMENT
... A102: 45892 | B102: SHOPPERS DRUG MART #76 | C102: 15.9 | D102: HEALTH & BEAUTY

Sheet Sep-2025 (CC)
A1: DATE | B1: ITEM | C1: AMOUNT | D1: CATEGORY
A2: 45910 | B2: APPLE.COM/BILL TORONTO | C2: 4.51 | D2: APPLE SUB
A3: 45910 | B3: MEMBERSHIP FEE INSTALLMENT | C3: 12.99 | D3: MISC
A4: 45909 | B4: COUNTRY PAWS BOARDING 2 LONDON | C4: 28.97 | D4: DAY CARE
A5: 45909 | B5: NIKU FARMS 647-5787639 | C5: 9.6 | D5: GROCERIES
A6: 45909 | B6: NIKU FARMS 647-5787639 | C6: 239 | D6: GROCERIES
A7: 45907 | B7: Pay Balance with Points | C7: -133.2 | D7: PAYMENT
A8: 45904 | B8: COUNTRY PAWS BOARDING 2 LONDON | C8: 28.97 | D8: DAY CARE
A9: 45903 | B9: PLAYSTATION NETWORK 877-971-7669 | C9: 68.13 | D9: ENTERTAINMENT
A10: 45903 | B10: SP ODDBUNCH LONDON | C10: 35.99 | D10: GROCERIES
A11: 45902 | B11: COUNTRY PAWS BOARDING 2 LONDON | C11: 28.97 | D11: DAY CARE
A12: 45930 | B12: COUNTRY PAWS BOARDING 2 LONDON | C12: 28.97 | D12: DAY CARE
A13: 45930 | B13: Pay Balance with Points | C13: -65.99 | D13: PAYMENT
... A82: 45901 | B82: START CA | C82: 56.5 | D82: INTERNET

Sheet Oct-2025 (CC)
A1: DATE | B1: ITEM | C1: AMOUNT | D1: CATEGORY
A2: 10 Oct 2025 | B2: APPLE.COM/BILL TORONTO | C2: 4.51 | D2: APPLE SUB
A3: 10 Oct 2025 | B3: MEMBERSHIP FEE INSTALLMENT | C3: 12.99 | D3: MISC
A4: 10 Oct 2025 | B4: SP GUESSWHERETRIPS LONDON | C4: 66.11 | D4: GIFTS
A5: 10 Oct 2025 | B5: COUNTRY PAWS BOARDING 2 LONDON | C5: 28.97 | D5: DAY CARE
A6: 08 Oct 2025 | B6: COUNTRY PAWS BOARDING 2 LONDON | C6: 28.97 | D6: DAY CARE
A7: 08 Oct 2025 | B7: LONDON CURLING CLUB 00- LONDON | C7: 9.25 | D7: ALCOHOL
A8: 05 Oct 2025 | B8: UBER TRIP HTTPS://HELP.UB | C8: 9.25 | D8: UBER
A9: 06 Oct 2025 | B9: MCDONALD'S #1501 LONDON | C9: 7.33 | D9: TAKE OUT
A10: 06 Oct 2025 | B10: MCDONALD'S #1501 LONDON | C10: 21.9 | D10: TAKE OUT
A11: 04 Oct 2025 | B11: ESSO CIRCLE K 0325 LONDON | C11: 49.1 | D11: GAS
A12: 03 Oct 2025 | B12: NIKU FARMS 647-5787639 | C12: 246.32 | D12: GROCERIES
A13: 03 Oct 2025 | B13: CINEPLEX #8030 WEB QP TORONTO | C13: 35.56 | D13: ENTERTAINMENT
... A57: 12 Oct 2025 | B57: WENDYS 114 LONDON | C57: 7.44 | D57: TAKE OUT
A58: 45952 | B58: Amazon.ca*NU7VG9Q51 | C58: 37.26 | D58: MISC
A59: 45951 | B59: LONDON CURLING CLUB | C59: 9.25 | D59: ALCOHOL
A60: 45951 | B60: Amazon Channels | C60: 20.33 | D60: PRIME VIDEO SUB
A61: 45950 | B61: Amazon Channels | C61: -5.8 | D61: PRIME VIDEO SUB
A62: 45950 | B62: Amazon Channels | C62: 37.28 | D62: PRIME VIDEO SUB
A63: 45950 | B63: METRO 150 | C63: 94.19 | D63: GROCERIES
A64: 45950 | B64: Amazon Channels | C64: 5.64 | D64: PRIME VIDEO SUB
A65: 45949 | B65: TELUS PRE-AUTH PAYMENT | C65: 45.2 | D65: TELUS SECURITY
A66: 45948 | B66: Amazon.ca*NU6KE1ZE0 | C66: 33.46 | D66: MISC
A67: 45948 | B67: APPLE.COM/BILL | C67: 14.68 | D67: APPLE SUB
A68: 45945 | B68: Amazon Channels | C68: 4.51 | D68: PRIME VIDEO SUB
A69: 45945 | B69: AMZN Mktp CA*NM8B125T1 | C69: 42.92 | D69: MISC
... A117: 45944 | B117: SQ *CASH BY CASH APP | C117: -0.96 | D117: MISC

Sheet Nov-2025 (CC)
A1: DATE | B1: ITEM | C1: AMOUNT | D1: CATEGORY
A2: 10 Nov 2025 | B2: APPLE.COM/BILL TORONTO | C2: 4.51 | D2: APPLE SUB
A3: 10 Nov 2025 | B3: MEMBERSHIP FEE INSTALLMENT | C3: 12.99 | D3: MISC
A4: 10 Nov 2025 | B4: JERSEY MIKES' SUBS KITCHENER | C4: 66.73 | D4: TAKE OUT
A5: 10 Nov 2025 | B5: CANADIAN TIRE GAS BAR # LONDON | C5: 21 | D5: GAS
A6: 08 Nov 2025 | B6: COUNTRY PAWS BOARDING 2 LONDON | C6: 54.22 | D6: DAY CARE
A7: 09 Nov 2025 | B7: RONA+ S.W. LONDON 8306 LONDON | C7: 69.35 | D7: HOME
A8: 09 Nov 2025 | B8: SP MTERVODESIGN SHERIDAN | C8: 51 | D8: GIFTS
A9: 09 Nov 2025 | B9: U-HAUL MOVING & STORA LONDON | C9: 25.21 | D9: HOME
A10: 09 Nov 2025 | B10: CANADIAN TIRE #058 LONDON | C10: 51.95 | D10: HOME
A11: 08 Nov 2025 | B11: METRO 150 LONDON | C11: 43.51 | D11: GROCERIES
A12: 07 Nov 2025 | B12: Pay Balance with Points | C12: -137.51 | D12: PAYMENT
A13: 08 Nov 2025 | B13: THE HOME DEPOT #7033 LONDON | C13: 2574.38 | D13: HOME
... A75: 11 Nov 2025 | B75: THE HOME DEPOT #7033 LONDON | C75: 87.65 | D75: HOME
A76: 45984 | B76: Amazon Channels | C76: 6.22 | D76: PRIME VIDEO SUB
A77: 45984 | B77: DOMINOS PIZZA #10250 | C77: 39.85 | D77: TAKE OUT
A78: 45984 | B78: APPLE.COM/BILL | C78: 10.71 | D78: APPLE SUB
A79: 45984 | B79: FAMOUS FLOWER CANNABIS CO | C79: 75.98 | D79: CANNABIS
A80: 45983 | B80: ROVER.COM* PET SVCS. | C80: 435.12 | D80: DAY CARE
A81: 45983 | B81: CRATE AND BARREL CANADA I | C81: 169.44 | D81: HOME
A82: 45981 | B82: Amazon Channels | C82: 5.64 | D82: PRIME VIDEO SUB
A83: 45980 | B83: TELUS PRE-AUTH PAYMENT | C83: 45.2 | D83: TELUS SECURITY
A84: 45979 | B84: APPLE.COM/BILL | C84: 14.68 | D84: APPLE SUB
A85: 45979 | B85: SWISS CHALET #1135E | C85: 71.78 | D85: TAKE OUT
A86: 45976 | B86: Amazon Channels | C86: 4.51 | D86: PRIME VIDEO SUB
A87: 45974 | B87: Amazon.ca Prime Member | C87: 11.29 | D87: PRIME VIDEO SUB
... A111: 45984 | B111: McDonalds 1501 | C111: 11.57 | D111: TAKE OUT

Sheet Dec-2025 (CC)
A1: DATE | B1: ITEM | C1: AMOUNT | D1: CATEGORY
A2: 10 Dec 2025 | B2: MEMBERSHIP FEE INSTALLMENT | C2: 12.99 | D2: MISC
A3: 09 Dec 2025 | B3: COUNTRY PAWS BOARDING 2 LONDON | C3: 28.97 | D3: DAY CARE
A4: 09 Dec 2025 | B4: NICKEL BROOK BREWING CO Burlington | C4: 74.9 | D4: ALCOHOL
A5: 09 Dec 2025 | B5: SP CALENDARCLUB.CA PARIS | C5: 36.04 | D5: MISC
A6: 10 Dec 2025 | B6: SP ODDBUNCH LONDON | C6: 35.99 | D6: GROCERIES
A7: 07 Dec 2025 | B7: UBER TRIP HTTPS://HELP.UB | C7: 17.38 | D7: UBER
A8: 07 Dec 2025 | B8: LCBO/RAO #0192 LONDON LONDON | C8: 16.2 | D8: ALCOHOL
A9: 07 Dec 2025 | B9: METRO 150 LONDON | C9: 111.78 | D9: GROCERIES
A10: 07 Dec 2025 | B10: SP E-UP GAMES LONDON | C10: 44.99 | D10: GIFTS
A11: 06 Dec 2025 | B11: UBER EATS HTTPS://HELP.UB | C11: 85.48 | D11: DELIVERY
A12: 06 Dec 2025 | B12: COUNTRY PAWS BOARDING 2 LONDON | C12: 193.15 | D12: DAY CARE
A13: 06 Dec 2025 | B13: DOUBLETREE BY HILTON TO TORONTO | C13: 1295.61 | D13: TRAVEL
... A25: 01 Dec 2025 | B25: NESTLÉ CANADA INC TORONTO | C25: 122.76 | D25: COFFEE
A26: 46013 | B26: DOMINOS PIZZA #10250 | C26: 34.52 | D26: TAKE OUT
A27: 46011 | B27: Amazon Channels | C27: 11.29 | D27: PRIME VIDEO SUB
A28: 46011 | B28: Amazon.ca*116U44153 | C28: 23.08 | D28: MISC
A29: 46011 | B29: PIONEER 43368 | C29: 51.22 | D29: GAS
A30: 46011 | B30: TELUS PRE-AUTH PAYMENT | C30: 45.2 | D30: TELUS SECURITY
A31: 46009 | B31: APPLE.COM/BILL | C31: 14.68 | D31: APPLE SUB
A32: 46009 | B32: Amazon.ca*344FU4WG3 | C32: 34.01 | D32: MISC
A33: 46008 | B33: AMZN Mktp CA*7Y2933353 | C33: 21.33 | D33: MISC
A34: 46008 | B34: LOBLAWS 1016 | C34: 244.34 | D34: GROCERIES
A35: 46008 | B35: Amazon.ca*UX1CV9GZ3 | C35: 34.1 | D35: MISC
A36: 46006 | B36: Amazon Channels | C36: 6.77 | D36: PRIME VIDEO SUB
A37: 46005 | B37: McDonalds 1501 | C37: 11.61 | D37: TAKE OUT
... A56: 45992 | B56: START CA | C56: 79.1 | D56: INTERNET

Sheet Jan-2025
A1: Month: | B1: Jan
A3: Income:
A4: Matt Comm | B4: 1497.82
A5: Matt | B5: =SUM(2842.82+2831.63) -> 5674.45 | C5: =B5/B7 -> 0.59547021
A6: Nicole | B6: =1979.03+1875.88 -> 3854.91 | C6: =B6/B7 -> 0.40452979
A7: Subtotal: | B7: =SUM(B5:B6) -> 9529.36
A9: Shared Expenses: | C9: Matt | D9: Nicole
A10: Mortgage | B10: 1711.29 | C10: =B10*C5 -> 1019.0222 | D10: =B10*C6 -> 692.26778
A11: Reliance (Water Heater) | B11: 39.64 | C11: =B11*C5 -> 23.604439 | D11: =B11*C6 -> 16.035561
A12: Home Insurance | B12: 211.95 | C12: =B12*C5 -> 126.20991 | D12: =B12*C6 -> 85.740089
A13: Internet | B13: 0 | C13: =B13*C5 -> 0 | D13: =B13*C6 -> 0
A14: Car Insurance | B14: 161.78 | C14: =B14*C5 -> 96.335171 | D14: =B14*C6 -> 65.444829
A15: Home Security | B15: 39.55 | C15: =B15*C5 -> 23.550847 | D15: =B15*C6 -> 15.999153
A16: Pet Insurance | B16: 220.92 | C16: =B16*C5 -> 131.55128 | D16: =B16*C6 -> 89.368721
A17: Cell Phones | B17: 526.15 | C17: =B17*C5 -> 313.30665 | D17: =B17*C6 -> 212.84335
A18: Enbridge | B18: 184.62 | C18: =B18*C5 -> 109.93571 | D18: =B18*C6 -> 74.68429
A19: London Hydro | B19: 229.3 | C19: =B19*C5 -> 136.54132 | D19: =B19*C6 -> 92.758681
A20: Car Payment | B20: =158.58*2 -> 317.16 | D20: =B20 -> 317.16
A22: Shared Savings (25%)
B23: =B7*0.25 -> 2382.34 | C23: =B23*C5 -> 1418.6125 | D23: =B23*C6 -> 963.7275
A25: Sub | B25: =SUM(B10:B23) -> 6024.7 | C25: =SUM(C10:C23) -> 3398.67 | D25: =SUM(D10:D23) -> 2626.03
A27: Deposit to Personal Accts | C27: =B5-C25 -> 2275.78 | D27: =B6-D25 -> 1228.88
A28: 45672 | C28: =C27/2 -> 1137.89 | D28: =D27/2 -> 614.44002
A29: 45687 | C29: =C27/2 -> 1137.89 | D29: =D27/2 -> 614.44002
A33: Other Stuff | C33: Due Date
A34: AMEX Bill | B34: 7120.29
A35: VISA Bill | B35: 1197.36
A36: MASTER | B36: 1500
B37: =SUM(B34:B36) -> 9817.65

Sheet Feb-2025
A1: Month: | B1: Feb
A3: Income:
A4: Matt Comm | B4: 1955.54
A5: Matt | B5: =2116.57+2831.63 -> 4948.2 | C5: =B5/B7 -> 0.55558924
A6: Nicole | B6: =1979.01*2 -> 3958.02 | C6: =B6/B7 -> 0.44441076
A7: Subtotal: | B7: =SUM(B5:B6) -> 8906.22
A9: Shared Expenses: | C9: Matt | D9: Nicole | E9: Due
A10: Mortgage | B10: 1711.29 | C10: =B10*C5 -> 950.77431 | D10: =B10*C6 -> 760.51569 | E10: 45691 | F10: PAID
A11: Reliance (Water Heater) | B11: 39.64 | C11: =B11*C5 -> 22.023557 | D11: =B11*C6 -> 17.616443 | E11: 45702 | F11: PAID
A12: Home + Life | B12: 211.95 | C12: =B12*C5 -> 117.75714 | D12: =B12*C6 -> 94.192861 | E12: 45716
A13: Internet | B13: 0 | C13: =B13*C5 -> 0 | D13: =B13*C6 -> 0
A14: Car Insurance | B14: 161.78 | C14: =B14*C5 -> 89.883227 | D14: =B14*C6 -> 71.896773 | E14: 45716
A15: Home Security | B15: 39.55 | C15: =B15*C5 -> 21.973554 | D15: =B15*C6 -> 17.576446 | E15: 45707
A16: Pet Insurance | B16: 236.5 | C16: =B16*C5 -> 131.39686 | D16: =B16*C6 -> 105.10314 | E16: 45708
A17: Cell Phones | B17: 110.13 | C17: =B17*C5 -> 61.187043 | D17: =B17*C6 -> 48.942957 | E17: 45712
A18: Enbridge | B18: 125.71 | C18: =B18*C5 -> 69.843123 | D18: =B18*C6 -> 55.866877 | E18: 45704 | F18: PAID
A19: London Hydro | B19: 258.4 | C19: =B19*C5 -> 143.56426 | D19: =B19*C6 -> 114.83574 | E19: 45704 | F19: PAID
A20: Car Payment | B20: =158.58*2 -> 317.16
A22: Shared Savings (25%)
B23: =B7*0.25 -> 2226.555 | C23: =B23*C5 -> 1237.05 | D23: =B23*C6 -> 989.505
A25: Sub | B25: =SUM(B10:B23) -> 5438.665 | C25: =SUM(C10:C23) -> 2845.4531 | D25: =SUM(D10:D23) -> 2276.0519
A27: Deposit to Personal Accts | C27: =B5-C25 -> 2102.7469 | D27: =B6-D25 -> 1681.9681
A28: 45703 | C28: =C27/2 -> 1051.3735 | D28: =D27/2 -> 840.98403
A29: 45716 | C29: =C27/2 -> 1051.3735 | D29: =D27/2 -> 840.98403
A33: Other Stuff | C33: Due Date
A34: AMEX Bill | B34: 5287.46
A35: VISA Bill | B35: 859.07
A36: MASTER

Sheet Mar-2025
A1: Month: | B1: Mar
A3: Income:
A4: Matt Comm | B4: 1161.07
A5: Matt | B5: =2934.84+2754+54 -> 5742.84 | C5: =B5/B7 -> 0.59199287
A6: Nicole | B6: =1979.01*2 -> 3958.02 | C6: =B6/B7 -> 0.40800713
A7: Subtotal: | B7: =SUM(B5:B6) -> 9700.86
A9: Shared Expenses: | C9: Matt | D9: Nicole | E9: Due
A10: Mortgage | B10: 1711.29 | C10: =B10*C5 -> 1013.0715 | D10: =B10*C6 -> 698.21851 | E10: 45717 | F10: PAID
A11: Reliance (Water Heater) | B11: 39.64 | C11: =B11*C5 -> 23.466598 | D11: =B11*C6 -> 16.173402 | E11: 45730
A12: Home + Life | B12: 211.95 | C12: =B12*C5 -> 125.47289 | D12: =B12*C6 -> 86.47711 | E12: 45744
A13: Internet | B13: 0 | C13: =B13*C5 -> 0 | D13: =B13*C6 -> 0
A14: Car Insurance | B14: 161.78 | C14: =B14*C5 -> 95.772607 | D14: =B14*C6 -> 66.007393 | E14: 45744
A15: Home Security | B15: 39.55 | C15: =B15*C5 -> 23.413318 | D15: =B15*C6 -> 16.136682 | E15: 45735
A16: Pet Insurance | B16: 220.92 | C16: =B16*C5 -> 130.78307 | D16: =B16*C6 -> 90.136934 | E16: 45736
A17: Cell Phones | B17: 293.64 | C17: =B17*C5 -> 173.83279 | D17: =B17*C6 -> 119.80721 | E17: 45740
A18: Enbridge | B18: 173.47 | C18: =B18*C5 -> 102.693 | D18: =B18*C6 -> 70.776996 | E18: 45732
A19: London Hydro | B19: 257.58 | C19: =B19*C5 -> 152.48552 | D19: =B19*C6 -> 105.09448 | E19: 45732 | F19: PAID
A20: Car Payment | B20: =158.58*2 -> 317.16
A22: Shared Savings (25%)
B23: =B7*0.25 -> 2425.215 | C23: =B23*C5 -> 1435.71 | D23: =B23*C6 -> 989.505
A25: Sub | B25: =SUM(B10:B23) -> 5852.195 | C25: =SUM(C10:C23) -> 3276.7013 | D25: =SUM(D10:D23) -> 2258.3337
A27: Deposit to Personal Accts | C27: =B5-C25 -> 2466.1387 | D27: =B6-D25 -> 1699.6863
A28: 45731 | C28: =C27/2 -> 1233.0694 | D28: =D27/2 -> 849.84314
A29: 45746 | C29: =C27/2 -> 1233.0694 | D29: =D27/2 -> 849.84314
A33: Other Stuff | C33: Due Date
A34: AMEX Bill
A35: VISA Bill
A36: MASTER

Sheet Apr-2025
A1: Month: | B1: Apr
A3: Income:
A4: Matt Comm | B4: 1623.16
A5: Matt | B5: =4159.86+5637.97 -> 9797.83 | C5: =B5/B7 -> 0.70608274
A6: Nicole | B6: =1875.88+2202.61 -> 4078.49 | C6: =B6/B7 -> 0.29391726
A7: Subtotal: | B7: =SUM(B5:B6) -> 13876.32
A9: Shared Expenses: | C9: Matt | D9: Nicole | E9: Due
A10: Mortgage | B10: 1711.29 | C10: =B10*C5 -> 1208.3123 | D10: =B10*C6 -> 502.97767 | E10: 45748
A11: Reliance (Water Heater) | B11: 39.64 | C11: =B11*C5 -> 27.98912 | D11: =B11*C6 -> 11.65088 | E11: 45761
A12: Home Insurance | B12: 211.95 | C12: =B12*C5 -> 149.65424 | D12: =B12*C6 -> 62.295764 | E12: 45775
A13: Internet | B13: 0 | C13: =B13*C5 -> 0 | D13: =B13*C6 -> 0
A14: Car Insurance | B14: 153.15 | C14: =B14*C5 -> 108.13657 | D14: =B14*C6 -> 45.013429 | E14: 45775
A15: Home Security | B15: 45.2 | C15: =B15*C5 -> 31.91494 | D15: =B15*C6 -> 13.28506 | E15: 45766
A16: Pet Insurance | B16: 236.5 | C16: =B16*C5 -> 166.98857 | D16: =B16*C6 -> 69.511433 | E16: 45767
A17: Cell Phones | B17: 141.32 | C17: =B17*C5 -> 99.783612 | D17: =B17*C6 -> 41.536388 | E17: 45771
A18: Enbridge | B18: 75.41 | C18: =B18*C5 -> 53.245699 | D18: =B18*C6 -> 22.164301 | E18: 45763
A19: London Hydro | B19: 193.49 | C19: =B19*C5 -> 136.61995 | D19: =B19*C6 -> 56.870051 | E19: 45763
A20: Doors | B20: =54.4 -> 54.4 | C20: =B20*C5 -> 38.410901 | D20: =B20*C6 -> 15.989099
A21: Car Payment | B21: =158.58*2 -> 317.16
A22: Shared Savings (25%)
B23: =B7*0.25 -> 3469.08 | C23: =B23*C5 -> 2449.4575 | D23: =B23*C6 -> 1019.6225
A25: Sub | B25: =SUM(B10:B23) -> 6648.59 | C25: =SUM(C10:C23) -> 4470.5134 | D25: =SUM(D10:D23) -> 1860.9166
A27: Deposit to Personal Accts | C27: =B5-C25 -> 5327.3166 | D27: =B6-D25 -> 2217.5734
A28: 45762 | C28: =C27/2 -> 2663.6583 | D28: =D27/2 -> 1108.7867
A29: 45777 | C29: =C27/2 -> 2663.6583 | D29: =D27/2 -> 1108.7867
A33: Other Stuff | C33: Due Date
A34: AMEX Bill
A35: VISA Bill
A36: MASTER

Sheet May-2025
A1: Month: | B1: May
A3: Income:
A4: Matt Comm | B4: 0
A5: Matt | B5: =3705.38*2 -> 7410.76 | C5: =B5/B7 -> 0.65185183
A6: Nicole | B6: =1979.01*2 -> 3958.02 | C6: =B6/B7 -> 0.34814817
A7: Subtotal: | B7: =SUM(B5:B6) -> 11368.78
A9: Shared Expenses: | C9: Matt | D9: Nicole | E9: Due
A10: Mortgage | B10: 1711.29 | C10: =B10*C5 -> 1115.5075 | D10: =B10*C6 -> 595.78249 | E10: 45778
A11: Reliance (Water Heater) | B11: 39.64 | C11: =B11*C5 -> 25.839406 | D11: =B11*C6 -> 13.800594 | E11: 45791
A12: Home + Life | B12: 211.95 | C12: =B12*C5 -> 138.15999 | D12: =B12*C6 -> 73.790006 | E12: 45805
A13: Internet | B13: 0 | C13: =B13*C5 -> 0 | D13: =B13*C6 -> 0
A14: Car Insurance | B14: 161.78 | C14: =B14*C5 -> 105.45659 | D14: =B14*C6 -> 56.323412 | E14: 45805
A15: Home Security | B15: 45.2 | C15: =B15*C5 -> 29.463703 | D15: =B15*C6 -> 15.736297 | E15: 45796
A16: Pet Insurance | B16: 242.75 | C16: =B16*C5 -> 158.23703 | D16: =B16*C6 -> 84.512969 | E16: 45797
A17: Cell Phones | B17: 93.86 | C17: =B17*C5 -> 61.182812 | D17: =B17*C6 -> 32.677188 | E17: 45801
A18: Enbridge | B18: 68.28 | C18: =B18*C5 -> 44.508443 | D18: =B18*C6 -> 23.771557 | E18: 45793
A19: London Hydro | B19: 223.45 | C19: =B19*C5 -> 145.65629 | D19: =B19*C6 -> 77.79371 | E19: 45793
A20: Car Payment | B20: =158.58*2 -> 317.16 | C20: =B20*C5 -> 206.74133 | D20: =B20*C5 -> 206.74133
A21: Doors | B21: 54.4 | C21: =B21*C5 -> 35.460739 | D21: =B21*C6 -> 18.939261
A22: Car Payments | B22: =158.58*2 -> 317.16
A24: TOTAL Expenses: | B24: =SUM(B10:B21) -> 3169.76
A26: Shared Savings (25%)
B27: =B7*0.25 -> 2842.195 | C27: =B27*C5 -> 1852.69 | D27: =B27*C6 -> 989.505
A29: Sub | B29: =SUM(B10:B27) -> 9498.875 | C29: =SUM(C10:C27) -> 3918.9038 | D29: =SUM(D10:D27) -> 2189.3738
A31: Deposit to Personal Accts | C31: =B5-C29 -> 3491.8562 | D31: =B6-D29 -> 1768.6462
A32: 45792 | C32: =C31/2 -> 1745.9281 | D32: =D31/2 -> 884.3231
A33: 45807 | C33: =C31/2 -> 1745.9281 | D33: =D31/2 -> 884.3231
A37: Other Stuff | C37: Due Date
A38: AMEX Bill
A39: VISA Bill
A40: MASTER

Sheet Jun-2025
A1: Month: | B1: June
A3: Income:
A4: Matt Comm | B4: 0
A5: Matt | B5: =3705.38*2 -> 7410.76 | C5: =B5/B7 -> 0.65185183
A6: Nicole | B6: =1979.01*2 -> 3958.02 | C6: =B6/B7 -> 0.34814817
A7: Subtotal: | B7: =SUM(B5:B6) -> 11368.78
A9: Shared Expenses: | C9: Matt | D9: Nicole | E9: Due
A10: Mortgage | B10: 1711.29 | C10: =B10*C5 -> 1115.5075 | D10: =B10*C6 -> 595.78249 | E10: 45809
A11: Reliance (Water Heater) | B11: 115.65 | C11: =B11*C5 -> 75.386664 | D11: =B11*C6 -> 40.263336 | E11: 45822
A12: Home | B12: 211.95 | C12: =B12*C5 -> 138.15999 | D12: =B12*C6 -> 73.790006 | E12: 45836
A13: Internet | B13: 56.5 | C13: =B13*C5 -> 36.829628 | D13: =B13*C6 -> 19.670372
A14: Car Insurance | B14: 161.78 | C14: =B14*C5 -> 105.45659 | D14: =B14*C6 -> 56.323412 | E14: 45836
A15: Home Security | B15: 45.2 | C15: =B15*C5 -> 29.463703 | D15: =B15*C6 -> 15.736297 | E15: 45827
A16: Pet Insurance | B16: 242.75 | C16: =B16*C5 -> 158.23703 | D16: =B16*C6 -> 84.512969 | E16: 45828
A17: Cell Phones | B17: 93.86 | C17: =B17*C5 -> 61.182812 | D17: =B17*C6 -> 32.677188 | E17: 45832
A18: Enbridge | B18: 0 | C18: =B18*C5 -> 0 | D18: =B18*C6 -> 0 | E18: 45824
A19: London Hydro | B19: 207.16 | C19: =B19*C5 -> 135.03762 | D19: =B19*C6 -> 72.122376 | E19: 45824
A20: Car Payment | B20: =158.58*2 -> 317.16 | C20: =B20*C5 -> 206.74133 | D20: =B20*C5 -> 206.74133
A21: Doors | B21: 54.4 | C21: =B21*C5 -> 35.460739 | D21: =B21*C6 -> 18.939261
A22: Municipal Taxes | B22: 1029 | C22: =B22*C5 -> 670.75553 | D22: =B22*C6 -> 358.24447
A24: Shared Savings (25%)
B25: =B7*0.25 -> 2842.195 | C25: =B25*C5 -> 1852.69 | D25: =B25*C6 -> 989.505
A27: Sub | B27: =SUM(B10:B25) -> 7088.895 | C27: =SUM(C10:C25) -> 4620.9091 | D27: =SUM(D10:D25) -> 2564.3085
A29: Deposit to Personal Accts | C29: =B5-C27 -> 2789.8509 | D29: =B6-D27 -> 1393.7115
A30: 45823 | C30: =C29/2 -> 1394.9254 | D30: =D29/2 -> 696.85575
A31: 45838 | C31: =C29/2 -> 1394.9254 | D31: =D29/2 -> 696.85575
A35: Other Stuff | C35: Due Date
A36: AMEX Bill
A37: VISA Bill
A38: MASTER

Sheet Jul-2025
A1: Month: | B1: July
A3: Income:
A4: Matt Comm | B4: 0
A5: Matt | B5: =3406.31*2 -> 6812.62 | C5: =B5/B7 -> 0.63251766
A6: Nicole | B6: =1979.01*2 -> 3958.02 | C6: =B6/B7 -> 0.36748234
A7: Subtotal: | B7: =SUM(B5:B6) -> 10770.64
A9: Shared Expenses: | C9: Matt | D9: Nicole | E9: Due
A10: Mortgage | B10: 1711.29 | C10: =B10*C5 -> 1082.4211 | D10: =B10*C6 -> 628.86886
A11: Home Insurance | B11: 146.21 | C11: =B11*C5 -> 92.480407 | D11: =B11*C6 -> 53.729593
A12: Internet | B12: 56.5 | C12: =B12*C5 -> 35.737248 | D12: =B12*C6 -> 20.762752
A13: Car Insurance | B13: 151.61 | C13: =B13*C5 -> 95.896002 | D13: =B13*C6 -> 55.713998
A14: Home Security | B14: 45.2 | C14: =B14*C5 -> 28.589798 | D14: =B14*C6 -> 16.610202
A15: Pet Insurance | B15: 242.75 | C15: =B15*C5 -> 153.54366 | D15: =B15*C6 -> 89.206338
A16: Cell Phones | B16: 172.96 | C16: =B16*C5 -> 109.40025 | D16: =B16*C6 -> 63.559746
A17: Enbridge | B17: 25.57 | C17: =B17*C5 -> 16.173477 | D17: =B17*C6 -> 9.3965235
A18: London Hydro | B18: 248.04 | C18: =B18*C5 -> 156.88968 | D18: =B18*C6 -> 91.15032
A19: Car Payment | B19: 158.58 | C19: =B19*C5 -> 100.30465 | D19: =B19*C5 -> 100.30465
A20: Doors | B20: 54.4 | C20: =B20*C5 -> 34.408961 | D20: =B20*C6 -> 19.991039
A22: Shared Savings (25%)
B23: =B7*0.25 -> 2692.66 | C23: =B23*C5 -> 1703.155 | D23: =B23*C6 -> 989.505
A25: Sub | B25: =SUM(B10:B23) -> 5705.77 | C25: =SUM(C10:C23) -> 3609.0003 | D25: =SUM(D10:D23) -> 2138.799
A27: Deposit to Personal Accts | C27: =B5-C25 -> 3203.6197 | D27: =B6-D25 -> 1819.221
A28: 45792 | C28: =C27/2 -> 1601.8099 | D28: =D27/2 -> 909.61049
A29: 45807 | C29: =C27/2 -> 1601.8099 | D29: =D27/2 -> 909.61049
A33: Other Stuff | C33: Due Date
A34: AMEX Bill
A35: VISA Bill
A36: MASTER

Sheet Aug-2025
A1: Month: | B1: Aug
A3: Income:
A4: Matt Comm | B4: 0
A5: Matt | B5: =3421.44+3392.14 -> 6813.58 | C5: =B5/B7 -> 0.62659601
A6: Nicole | B6: =2030.19+2030.19 -> 4060.38 | C6: =B6/B7 -> 0.37340399
A7: Subtotal: | B7: =SUM(B5:B6) -> 10873.96
A9: Shared Expenses: | C9: Matt | D9: Nicole | E9: Due
A10: Mortgage | B10: 1711.29 | C10: =B10*C5 -> 1072.2875 | D10: =B10*C6 -> 639.00251 | E10: PAID
A11: Home Insurance | B11: 146.21 | C11: =B11*C5 -> 91.614603 | D11: =B11*C6 -> 54.595397
A12: Internet | B12: 56.5 | C12: =B12*C5 -> 35.402675 | D12: =B12*C6 -> 21.097325
A13: Car Insurance | B13: 151.61 | C13: =B13*C5 -> 94.998222 | D13: =B13*C6 -> 56.611778
A14: Home Security | B14: 45.2 | C14: =B14*C5 -> 28.32214 | D14: =B14*C6 -> 16.87786
A15: Pet Insurance | B15: 242.75 | C15: =B15*C5 -> 152.10618 | D15: =B15*C6 -> 90.643817
A16: Cell Phones | B16: =0 -> 0 | C16: =B16*C5 -> 0 | D16: =B16*C6 -> 0
A17: Enbridge | B17: 44.34 | C17: =B17*C5 -> 27.783267 | D17: =B17*C6 -> 16.556733 | E17: PAID
A18: London Hydro | B18: 378.68 | C18: =B18*C5 -> 237.27938 | D18: =B18*C6 -> 141.40062 | E18: PAID
A19: Doors | B19: 54.4 | C19: =B19*C5 -> 34.086823 | D19: =B19*C6 -> 20.313177
A21: Savings
B22: =B7*0.25 -> 2718.49 | C22: =B22*C5 -> 1703.395 | D22: =B22*C6 -> 1015.095
A24: Sub | B24: =SUM(B10:B22) -> 5549.47 | C24: =SUM(C10:C22) -> 3477.2758 | D24: =SUM(D10:D22) -> 2072.1942
A32: Other Stuff | C32: Due Date
A33: AMEX Bill | B33: 2006.7
A34: VISA Bill | B34: 1815.81
A35: MASTER

Sheet Sep-2025
A1: Month: | B1: Sept
A3: Income:
A4: Matt Comm | B4: 0
A5: Matt | B5: =7429.45 -> 7429.45 | C5: =B5/B7 -> 0.63413017
A6: Nicole | B6: =4286.52 -> 4286.52 | C6: =B6/B7 -> 0.36586983
A7: Subtotal: | B7: =SUM(B5:B6) -> 11715.97
A9: Shared Expenses: | C9: Matt | D9: Nicole | E9: Due
A10: Mortgage | B10: 1967.98 | C10: =B10*C5 -> 1247.9555 | D10: =B10*C6 -> 720.02452
A11: Home Insurance | B11: 146.21 | C11: =B11*C5 -> 92.716172 | D11: =B11*C6 -> 53.493828
A12: Internet | B12: 56.5 | C12: =B12*C5 -> 35.828354 | D12: =B12*C6 -> 20.671646
A13: Car Insurance | B13: 151.61 | C13: =B13*C5 -> 96.140474 | D13: =B13*C6 -> 55.469526
A14: Home Security | B14: 45.2 | C14: =B14*C5 -> 28.662683 | D14: =B14*C6 -> 16.537316
A15: Pet Insurance | B15: 242.75 | C15: =B15*C5 -> 153.9351 | D15: =B15*C6 -> 88.814902
A16: Cell Phones | C16: =B16*C5 -> 0 | D16: =B16*C6 -> 0
A17: Enbridge | B17: 40.76 | C17: =B17*C5 -> 25.847146 | D17: =B17*C6 -> 14.912854
A18: London Hydro | B18: 346.22 | C18: =B18*C5 -> 219.54855 | D18: =B18*C6 -> 126.67145
A19: Doors | B19: 54.4 | C19: =B19*C5 -> 34.496681 | D19: =B19*C6 -> 19.903319
A21: Shared Savings (25%)
B22: =B7*0.25 -> 2928.9925 | C22: =B22*C5 -> 1857.3625 | D22: =B22*C6 -> 1071.63
A24: Sub | B24: =SUM(B10:B22) -> 5980.6225 | C24: =SUM(C10:C22) -> 3792.4931 | D24: =SUM(D10:D22) -> 2188.1294
A26: Deposit to Personal Accts | C26: =B5-C24 -> 3636.9569 | D26: =B6-D24 -> 2098.3906
A27: 45792 | C27: =C26/2 -> 1818.4784 | D27: =D26/2 -> 1049.1953
A28: 45807 | C28: =C26/2 -> 1818.4784 | D28: =D26/2 -> 1049.1953
A32: Other Stuff | C32: Due Date
A33: AMEX Bill
A34: VISA Bill
A35: MASTER

Sheet Oct-2025
A1: Month: | B1: Oct
A3: Income:
A4: Matt Comm | B4: 0
A5: Matt | B5: 12414.97 | C5: =B5/B7 -> 0.74808895
A6: Nicole | B6: =4180.61 -> 4180.61 | C6: =B6/B7 -> 0.25191105
A7: Subtotal: | B7: =SUM(B5:B6) -> 16595.58
A9: Shared Expenses: | C9: Matt | D9: Nicole | E9: Due
A10: Mortgage | B10: 1967.98 | C10: =B10*C5 -> 1472.2241 | D10: =B10*C6 -> 495.75591
A11: Home Insurance | B11: 146.21 | C11: =B11*C5 -> 109.37809 | D11: =B11*C6 -> 36.831915
A12: Internet | B12: 56.5 | C12: =B12*C5 -> 42.267026 | D12: =B12*C6 -> 14.232974
A13: Car Insurance | B13: 151.61 | C13: =B13*C5 -> 113.41777 | D13: =B13*C6 -> 38.192234
A14: Home Security | B14: 45.2 | C14: =B14*C5 -> 33.81362 | D14: =B14*C6 -> 11.38638
A15: Pet Insurance | B15: 257.21 | C15: =B15*C5 -> 192.41596 | D15: =B15*C6 -> 64.794041
A16: Cell Phones | C16: =B16*C5 -> 0 | D16: =B16*C6 -> 0
A17: Enbridge | B17: 38.45 | C17: =B17*C5 -> 28.76402 | D17: =B17*C6 -> 9.6859799
A18: London Hydro | B18: 291.71 | C18: =B18*C5 -> 218.22503 | D18: =B18*C6 -> 73.484973
A19: Doors | B19: 54.4 | C19: =B19*C5 -> 40.696039 | D19: =B19*C6 -> 13.703961
A20: Home Depot | B20: 35 | C20: =B20*C5 -> 26.183113 | D20: =B20*C6 -> 8.8168868
A22: Mandatory Savings
A23: Doors | B23: 525
A24: Range Oven | B24: 200
A33: Other Stuff | C33: Due Date
A34: AMEX Bill
A35: VISA Bill | B35: 3226.92
A36: MASTER

Sheet Nov-2025
A1: Month: | B1: Nov
A3: Income:
A4: Matt Comm | B4: 0
A5: Matt | B5: =6054.57 -> 6054.57 | C5: =B5/B7 -> 0.59857755
A6: Nicole | B6: =4060.36 -> 4060.36 | C6: =B6/B7 -> 0.40142245
A7: Subtotal: | B7: =SUM(B5:B6) -> 10114.93
A9: Shared Expenses: | C9: Matt | D9: Nicole | E9: Due
A10: Mortgage | B10: 1967.98 | C10: =B10*C5 -> 1177.9886 | D10: =B10*C6 -> 789.99136
A11: Home Insurance | B11: 146.21 | C11: =B11*C5 -> 87.518023 | D11: =B11*C6 -> 58.691977
A12: Internet | B12: 56.5 | C12: =B12*C5 -> 33.819631 | D12: =B12*C6 -> 22.680369
A13: Car Insurance | B13: 151.61 | C13: =B13*C5 -> 90.750342 | D13: =B13*C6 -> 60.859658
A14: Home Security | B14: 45.2 | C14: =B14*C5 -> 27.055705 | D14: =B14*C6 -> 18.144295
A15: Pet Insurance | B15: 257.21 | C15: =B15*C5 -> 153.96013 | D15: =B15*C6 -> 103.24987
A16: Cell Phones | C16: =B16*C5 -> 0 | D16: =B16*C6 -> 0
A17: Enbridge | B17: 62.26 | C17: =B17*C5 -> 37.267438 | D17: =B17*C6 -> 24.992562
A18: London Hydro | B18: 243.09 | C18: =B18*C5 -> 145.50822 | D18: =B18*C6 -> 97.581784
A19: Doors | B19: 54.4 | C19: =B19*C5 -> 32.562619 | D19: =B19*C6 -> 21.837381
A21: Shared Savings (25%)
B22: =B7*0.25 -> 2528.7325 | C22: =B22*C5 -> 1513.6425 | D22: =B22*C6 -> 1015.09
A24: Sub | B24: =SUM(B10:B22) -> 5513.1925 | C24: =SUM(C10:C22) -> 3300.0732 | D24: =SUM(D10:D22) -> 2213.1193
A26: Deposit to Personal Accts | C26: =B5-C24 -> 2754.4967 | D26: =B6-D24 -> 1847.2407
A27: 45792 | C27: =C26/2 -> 1377.2484 | D27: =D26/2 -> 923.62037
A28: 45807 | C28: =C26/2 -> 1377.2484 | D28: =D26/2 -> 923.62037
A32: Other Stuff | C32: Due Date
A33: AMEX Bill
A34: VISA Bill
A35: MASTER

Sheet Dec-2025
A1: Month: | B1: Nov
A3: Income:
A4: Matt Comm | B4: 0
A5: Matt | B5: =5898.22 -> 5898.22 | C5: =B5/B7 -> 0.5922752
A6: Nicole | B6: =4060.36 -> 4060.36 | C6: =B6/B7 -> 0.4077248
A7: Subtotal: | B7: =SUM(B5:B6) -> 9958.58
A9: Shared Expenses: | C9: Matt | D9: Nicole | E9: Due
A10: Mortgage | B10: 1967.98 | C10: =B10*C5 -> 1165.5858 | D10: =B10*C6 -> 802.39424
A11: Home Insurance | B11: 146.21 | C11: =B11*C5 -> 86.596558 | D11: =B11*C6 -> 59.613442
A12: Internet | B12: 56.5 | C12: =B12*C5 -> 33.463549 | D12: =B12*C6 -> 23.036451
A13: Car Insurance | B13: 151.61 | C13: =B13*C5 -> 89.794844 | D13: =B13*C6 -> 61.815156
A14: Home Security | B14: 45.2 | C14: =B14*C5 -> 26.770839 | D14: =B14*C6 -> 18.429161
A15: Pet Insurance | B15: 257.21 | C15: =B15*C5 -> 152.33911 | D15: =B15*C6 -> 104.87089
A16: Cell Phones | C16: =B16*C5 -> 0 | D16: =B16*C6 -> 0
A17: Enbridge | B17: 107.14 | C17: =B17*C5 -> 63.456365 | D17: =B17*C6 -> 43.683635
A18: London Hydro | B18: 214.44 | C18: =B18*C5 -> 127.00749 | D18: =B18*C6 -> 87.432505
A19: Doors | B19: 54.4 | C19: =B19*C5 -> 32.219771 | D19: =B19*C6 -> 22.180229
A21: Shared Savings (25%)
B22: =B7*0.25 -> 2489.645 | C22: =B22*C5 -> 1474.555 | D22: =B22*C6 -> 1015.09
A24: Sub | B24: =SUM(B10:B22) -> 5490.335 | C24: =SUM(C10:C22) -> 3251.7893 | D24: =SUM(D10:D22) -> 2238.5457
A26: Deposit to Personal Accts | C26: =B5-C24 -> 2646.4307 | D26: =B6-D24 -> 1821.8143
A27: 45792 | C27: =C26/2 -> 1323.2154 | D27: =D26/2 -> 910.90714
A28: 45807 | C28: =C26/2 -> 1323.2154 | D28: =D26/2 -> 910.90714
A32: Other Stuff | C32: Due Date
A33: AMEX Bill
A34: VISA Bill
A35: MASTER
