Workbook

Sheet Summary
B2: 2026 | C2: JAN | D2: FEB | E2: MAR | F2: APR | G2: MAY | H2: JUN | I2: JUL | J2: AUG | K2: SEPT | L2: OCT | M2: NOV | N2: DEC | P2: CURRENT YEAR BUDGET
B3: Total Income | C3: =C12 -> 13306.08 | D3: =D12 -> 10153.24 | E3: =E12 -> 0 | F3: =F12 -> 0 | G3: =G12 -> 0 | H3: =H12 -> 0 | I3: =I12 -> 0 | J3: =J12 -> 0 | ... N3: =N12 -> 0 | P3: =P12 -> 23459.32
B4: Total Expenses | C4: =C40 -> 13533.54 | D4: =D40 -> 7370.03 | E4: =E40 -> 3026.33 | F4: =F40 -> 2968.33 | G4: =G40 -> 2968.33 | H4: =H40 -> 2968.33 | I4: =I40 -> 2968.33 | J4: =J40 -> 3263.53 | ... N4: =N40 -> 3263.53 | P4: =P40 -> 52120.87
B5: Balance | C5: =C3-C4 -> -227.46 | D5: =D3-D4 -> 2783.21 | E5: =E3-E4 -> -3026.33 | F5: =F3-F4 -> -2968.33 | G5: =G3-G4 -> -2968.33 | H5: =H3-H4 -> -2968.33 | I5: =I3-I4 -> -2968.33 | J5: =J3-J4 -> -3263.53 | ... N5: =N3-N4 -> -3263.53 | P5: =P3-P4 -> -28661.55
B6: Data below will populate the above chart and calendar summary.
B7: Income | C7: JAN | D7: FEB | E7: MAR | F7: APR | G7: MAY | H7: JUN | I7: JUL | J7: AUG | K7: SEPT | L7: OCT | M7: NOV | N7: DEC | O7: Year-End Total
B9: Matt Pay | C9: =2884.57+6210.85 -> 9095.42 | D9: =2884.57+2793.24 -> 5677.81 | E9: 0 | F9: 0 | G9: 0 | H9: 0 | I9: 0 | J9: 0 | K9: 0 | L9: 0 | M9: 0 | N9: 0 | P9: =SUM(C9:N9) -> 14773.23
B10: Nicole Pay | C10: =2089.05+2121.61 -> 4210.66 | D10: =2121.61+2353.82 -> 4475.43 | E10: 0 | F10: 0 | G10: 0 | H10: 0 | I10: 0 | J10: 0 | K10: 0 | L10: 0 | M10: 0 | N10: 0 | P10: =SUM(C10:N10) -> 8686.09
B12: Total Income | C12: =SUM(C9:C10) -> 13306.08 | D12: =SUM(D9:D10) -> 10153.24 | E12: =SUM(E9:E10) -> 0 | F12: =SUM(F9:F10) -> 0 | G12: =SUM(G9:G10) -> 0 | H12: =SUM(H9:H10) -> 0 | I12: =SUM(I9:I10) -> 0 | J12: =SUM(J9:J10) -> 0 | ... N12: =SUM(N9:N10) -> 0 | P12: =SUM(C12:N12) -> 23459.32
B14: Expenses | C14: JAN | D14: FEB | E14: MAR | F14: APR | G14: MAY | H14: JUN | I14: JUL | J14: AUG | K14: SEPT | L14: OCT | M14: NOV | N14: DEC | O14: Year-End Total
B15: NEEDS
B16: Housing | C16: 1967.98 | D16: 1967.98 | E16: 1967.98 | F16: 1967.98 | G16: 1967.98 | H16: 1967.98 | I16: 1967.98 | J16: 2263.18 | K16: 2263.18 | L16: 2263.18 | M16: 2263.18 | N16: 2263.18 | P16: =SUM(C16:N16) -> 25091.76
B17: Enbridge | C17: 129.66 | D17: 166.36 | E17: 0 | F17: 0 | G17: 0 | H17: 0 | I17: 0 | J17: 0 | K17: 0 | L17: 0 | M17: 0 | N17: 0 | P17: =SUM(C17:N17) -> 296.02
B18: London Hydro | C18: 219.24 | D18: 214.77 | E18: 0 | F18: 0 | G18: 0 | H18: 0 | I18: 0 | J18: 0 | K18: 0 | L18: 0 | M18: 0 | N18: 0 | P18: =SUM(C18:N18) -> 434.01
B19: Groceries | C19: ='Jan - 2026 (CC)'!G18 -> 785.26 | D19: ='Feb - 2026 (CC)'!G15 -> 590.29 | E19: 0 | F19: 0 | G19: 0 | H19: 0 | I19: 0 | J19: 0 | K19: 0 | L19: 0 | M19: 0 | N19: 0 | P19: =SUM(C19:N19) -> 1375.55
B20: Pets (Daycare, Food, Toys) | C20: ='Jan - 2026 (CC)'!G14+'Jan - 2026 (CC)'!G26 -> 853.8 | D20: ='Feb - 2026 (CC)'!G10+'Feb - 2026 (CC)'!G22 -> 464.73 | E20: 0 | F20: 0 | G20: 0 | H20: 0 | I20: 0 | J20: 0 | K20: 0 | L20: 0 | M20: 0 | N20: 0 | P20: =SUM(C20:N20) -> 1318.53
B21: Transportation (Gas, Car Repairs) | C21: ='Jan - 2026 (CC)'!G16 -> 79.38 | D21: ='Feb - 2026 (CC)'!G13 -> 103.36 | E21: 0 | F21: 0 | G21: 0 | H21: 0 | I21: 0 | J21: 0 | K21: 0 | L21: 0 | M21: 0 | N21: 0 | P21: =SUM(C21:N21) -> 182.74
B22: Internet (Start.ca) | C22: ='Jan - 2026 (CC)'!G21 -> 79.1 | D22: ='Feb - 2026 (CC)'!G18 -> 79.1 | E22: 79.1 | F22: 79.1 | G22: 79.1 | H22: 79.1 | I22: 79.1 | J22: 79.1 | K22: 79.1 | L22: 79.1 | M22: 79.1 | N22: 79.1 | P22: =SUM(C22:N22) -> 949.2
B23: Home Security (Telus) | C23: ='Jan - 2026 (CC)'!G30 -> 45.2 | D23: ='Feb - 2026 (CC)'!G26 -> 45.2 | E23: 45.2 | F23: 45.2 | G23: 45.2 | H23: 45.2 | I23: 45.2 | J23: 45.2 | K23: 45.2 | L23: 45.2 | M23: 45.2 | N23: 45.2 | P23: =SUM(C23:N23) -> 542.4
B24: Mobile (Telus) | C24: ='Jan - 2026 (CC)'!G23 -> 135.15 | D24: ='Feb - 2026 (CC)'!G20 -> 171.31 | E24: 93.86 | F24: 93.86 | G24: 93.86 | H24: 93.86 | I24: 93.86 | J24: 93.86 | K24: 93.86 | L24: 93.86 | M24: 93.86 | N24: 93.86 | P24: =SUM(C24:N24) -> 1245.06
B25: Insurance (Life/Home/Auto/Pet) | C25: =257.21+146.21+151.61 -> 555.03 | D25: ='Feb - 2026 (CC)'!G17+265.51 -> 586.13 | E25: =265.21+146.21+151.61 -> 563.03 | F25: =257.21+146.21+151.61 -> 555.03 | G25: =257.21+146.21+151.61 -> 555.03 | H25: =257.21+146.21+151.61 -> 555.03 | I25: =257.21+146.21+151.61 -> 555.03 | J25: =257.21+146.21+151.61 -> 555.03 | K25: =257.21+146.21+151.61 -> 555.03 | L25: =257.21+146.21+151.61 -> 555.03 | M25: =257.21+146.21+151.61 -> 555.03 | N25: =257.21+146.21+151.61 -> 555.03 | P25: =SUM(C25:N25) -> 6699.46
B26: Property Taxes | C26: 0 | D26: 1104
B27: Debit Payments (LOC, Loans) | C27: =54.4+50+1500+750 -> 2354.4 | E27: =54.4+50 -> 104.4 | F27: 54.4 | G27: 54.4 | H27: 54.4 | I27: 54.4 | J27: 54.4 | K27: 54.4 | L27: 54.4 | M27: 54.4 | N27: 54.4 | P27: =SUM(C27:N27) -> 2948.4
B29: WANTS
B30: Subscriptions (Streaming, Software, etc.) | C30: ='Jan - 2026 (CC)'!G8+'Jan - 2026 (CC)'!G28+'Jan - 2026 (CC)'!G27 -> 131.39 | D30: ='Feb - 2026 (CC)'!G6+'Feb - 2026 (CC)'!G23+'Feb - 2026 (CC)'!G24 -> 133.44 | E30: 0 | F30: 0 | G30: 0 | H30: 0 | I30: 0 | J30: 0 | K30: 0 | L30: 0 | M30: 0 | N30: 0 | P30: =SUM(C30:N30) -> 264.83
B31: Entertainment / Dining Out / Takeout / Newspapers | C31: ='Jan - 2026 (CC)'!G15+'Jan - 2026 (CC)'!G29+'Jan - 2026 (CC)'!G24 -> 911.17 | D31: ='Feb - 2026 (CC)'!G11+'Feb - 2026 (CC)'!G25+'Feb - 2026 (CC)'!G12 -> 775.24 | E31: 0 | F31: 0 | G31: 0 | H31: 0 | I31: 0 | J31: 0 | K31: 0 | L31: 0 | M31: 0 | N31: 0 | P31: =SUM(C31:N31) -> 1686.41
B32: Clothing / Personal Care | C32: ='Jan - 2026 (CC)'!G18+'Jan - 2026 (CC)'!G12 -> 1019.74 | D32: ='Feb - 2026 (CC)'!G8+'Feb - 2026 (CC)'!G16 -> 435.97 | E32: 0 | F32: 0 | G32: 0 | H32: 0 | I32: 0 | J32: 0 | K32: 0 | L32: 0 | M32: 0 | N32: 0 | P32: =SUM(C32:N32) -> 1455.71
B33: Gifts / Donations | C33: ='Jan - 2026 (CC)'!G17 -> 235 | D33: ='Feb - 2026 (CC)'!G14 -> 190.38 | E33: 0 | F33: 0 | G33: 0 | H33: 0 | I33: 0 | J33: 0 | K33: 0 | L33: 0 | M33: 0 | N33: 0 | P33: =SUM(C33:N33) -> 425.38
B34: Charity | C34: ='Jan - 2026 (CC)'!G11 -> 50 | D34: 50 | E34: 50 | F34: 50 | G34: 50 | H34: 50 | I34: 50 | J34: 50 | K34: 50 | L34: 50 | M34: 50 | N34: 50 | P34: =SUM(C34:N34) -> 600
B35: Travel (Hotels, Flights, Uber) | C35: ='Jan - 2026 (CC)'!G31 -> 3498.43 | D35: 0 | E35: 0 | F35: 0 | G35: 0 | H35: 0 | I35: 0 | J35: 0 | K35: 0 | L35: 0 | M35: 0 | N35: 0 | P35: =SUM(C35:N35) -> 3498.43
B36: Coffee (Nespresso) | C36: ='Jan - 2026 (CC)'!G13 -> 103.2 | D36: ='Feb - 2026 (CC)'!G9 -> 136.99 | E36: 122.76 | F36: 122.76 | G36: 122.76 | H36: 122.76 | I36: 122.76 | J36: 122.76 | K36: 122.76 | L36: 122.76 | M36: 122.76 | N36: 122.76 | P36: =SUM(C36:N36) -> 1467.79
B37: Home (Improvement, Tools, etc) | C37: ='Jan - 2026 (CC)'!G20 -> 135.51 | D37: =0 -> 0
B38: Misc (Alcohol, Cannabis, Misc) | C38: ='Jan - 2026 (CC)'!G9+'Jan - 2026 (CC)'!G22 -> 244.9 | D38: ='Feb - 2026 (CC)'!G5 -> 154.78 | E38: 0 | F38: 0 | G38: 0 | H38: 0 | I38: 0 | J38: 0 | K38: 0 | L38: 0 | M38: 0 | N38: 0 | P38: =SUM(C38:N38) -> 399.68
B40: Total Expenses | C40: =SUM(C16:C38) -> 13533.54 | D40: =SUM(D16:D38) -> 7370.03 | E40: =SUM(E16:E38) -> 3026.33 | F40: =SUM(F16:F38) -> 2968.33 | G40: =SUM(G16:G38) -> 2968.33 | H40: =SUM(H16:H38) -> 2968.33 | I40: =SUM(I16:I38) -> 2968.33 | J40: =SUM(J16:J38) -> 3263.53 | ... N40: =SUM(N16:N38) -> 3263.53 | P40: =SUM(C40:N40) -> 52120.87
B42: AMEX
B43: VISA
B44: MC

Sheet Debts
A1: Loan Name | B1: Creditor | C1: Initial Balance | D1: Monthly Payment | E1: Monthly Extra | F1: Current Balance | G1: Savings | H1: Remaining | I1: Balance at Due | J1: Due Date | K1: Notes
A2: Brookstone (Doors) | B2: FinanceIt | C2: 9647.52 | D2: 54.4 | E2: 525 | F2: 9303.72 | G2: 2103.5 | H2: =F2-G2 -> 7200.22 | I2: 8487.72 | J2: 46419 | K2: 0% interest for 24 months
A3: Home Depot (Range) | B3: Home Depot CC | C3: 3524.47 | D3: 35 | F3: 1478.04 | H3: =F3 -> 1478.04 | I3: 1728.04 | J3: 46478 | K3: 0% interest for 24 months
A4: Tangerine Line of Credit | B4: Tangerine | C4: 5907.78 | F4: 8783.92
A5: Total: | C5: =SUM(C2:C4) -> 19079.77 | F5: =SUM(F2:F4) -> 19565.68
A8: Potential Loans
A9: HandyBros (WaterHeater/Furnace/Heatpump) | B9: FinanceIt | C9: 20376.16 | K9: 0% interest for 90 days
A10: HandyBros (WaterHeater/Furnace/Heatpump) | B10: Canada Greener Homes Loan | C10: 20376.16 | K10: 0% interest for 20 years

Sheet Jan - 2026 (CC)
A1: DATE | B1: ITEM | C1: AMOUNT | D1: CATEGORY
A2: 46023 | B2: NESTLÉ CANADA INC TORONTO | C2: 82.39 | D2: COFFEE
A3: 46023 | B3: Amazon Channels | C3: 1.7 | D3: PRIME VIDEO SUB
A4: 46023 | B4: START CA | C4: 79.1 | D4: INTERNET
A5: 46024 | B5: JS RYAN CO | C5: 57.5 | D5: HEALTH & BEAUTY
A6: 46024 | B6: DOMINOS PIZZA #10250 | C6: 45.71 | D6: TAKE OUT
A7: 46024 | B7: Amazon.ca*D47KD7Y63 | C7: 66.14 | D7: ENTERTAINMENT
A8: 46025 | B8: Amazon.ca*Q742C9C83 | C8: 27.22 | D8: ENTERTAINMENT
A9: 46025 | B9: PETRO-CANADA 65231 | C9: 13.54 | D9: CAR
A10: 46025 | B10: PETRO-CANADA 65231 | C10: 26.99 | D10: GAS
A11: 46025 | B11: Ad free for PrimeVideo | C11: 3.38 | D11: PRIME VIDEO SUB
A12: 46026 | B12: APPLE.COM/BILL TORONTO | C12: 152.55 | D12: HEALTH & BEAUTY
A13: 46026 | B13: CANADIAN TIRE #058 | C13: 135.51 | D13: HOME
... A97: 46053 | B97: PET VALU #2027 | C97: 133.33 | D97: PET FOOD/TOYS

Sheet Feb - 2026 (CC)
A1: DATE | B1: ITEM | C1: AMOUNT | D1: CATEGORY
A2: 46054 | B2: NESTLÉ CANADA INC TORONTO | C2: 122.76 | D2: COFFEE
A3: 46054 | B3: PLAYSTATION NETWORK 877-971-7669 | C3: 120.33 | D3: ENTERTAINMENT
A4: 46054 | B4: Pay Balance with Points | C4: -81.06 | D4: PAYMENT
A5: 46054 | B5: Amazon Channels | C5: 6.77 | D5: PRIME VIDEO SUB
A6: 46054 | B6: FOREST OF FLOWERS | C6: 90.39 | D6: GIFTS
A7: 46054 | B7: FARM BOY ONLINE WS | C7: 99.99 | D7: GIFTS
A8: 46054 | B8: START CA | C8: 79.1 | D8: INTERNET
A9: 46055 | B9: NIKU FARMS 647-5787639 | C9: -122.46 | D9: PAYMENT
A10: 46055 | B10: MARSHALLS 716 | C10: 29.18 | D10: CLOTHES
A11: 46056 | B11: COUNTRY PAWS BOARDING 2 LONDON | C11: 32.19 | D11: DAY CARE
A12: 46056 | B12: ODD BUNCH | C12: 35.99 | D12: GROCERIES
A13: 46056 | B13: Ad free for PrimeVideo | C13: 3.38 | D13: PRIME VIDEO SUB
... A87: 46073 | B87: ABE ERB | C87: 142.1 | D87: DINE IN

Sheet Mar - 2026 (CC)
A1: DATE | B1: ITEM | C1: AMOUNT | D1: CATEGORY
A2: 46082 | B2: Amazon Channels | C2: 6.77 | D2: PRIME VIDEO SUB
A3: 46082 | B3: START CA | C3: 79.1 | D3: INTERNET
A4: 46082 | B4: NESTLÉ CANADA INC TORONTO | C4: 76.5 | D4: COFFEE
A5: 46083 | B5: METRO 150 LONDON | C5: 126.88 | D5: GROCERIES
A6: 46084 | B6: Ad free for PrimeVideo | C6: 3.38 | D6: PRIME VIDEO SUB
A7: 46084 | B7: LONDON CURLING CLUB | C7: 17.41 | D7: ALCOHOL
A8: 46084 | B8: SP ODDBUNCH LONDON | C8: 35.99 | D8: GROCERIES
A9: 46085 | B9: THE BEAT GOES ON | C9: 11.29 | D9: ENTERTAINMENT
A10: 46085 | B10: Archies Seafood Restaura | C10: 48.91 | D10: TAKE OUT
A11: 46085 | B11: MTO TSD SO LONDON LAMB | C11: 90 | D11: MISC
A12: 46085 | B12: FRESHCO #9863 LONDON LONDON | C12: 41.31 | D12: GROCERIES
A13: 46085 | B13: PET VALU #2027 LONDON | C13: 9.03 | D13: PET FOOD/TOYS
... A61: 46099 | B61: APPLE.COM/BILL | C61: 14.68 | D61: APPLE SUB

Sheet Apr - 2026 (CC)
A1: DATE | B1: ITEM | C1: AMOUNT | D1: CATEGORY
D2: GROCERIES

Sheet May - 2026 (CC)
A1: DATE | B1: ITEM | C1: AMOUNT | D1: CATEGORY
D2: GROCERIES

Sheet Jun - 2026 (CC)
A1: DATE | B1: ITEM | C1: AMOUNT | D1: CATEGORY
D2: GROCERIES

Sheet Jul - 2026 (CC)
A1: DATE | B1: ITEM | C1: AMOUNT | D1: CATEGORY
D2: GROCERIES

Sheet Aug - 2026 (CC)
A1: DATE | B1: ITEM | C1: AMOUNT | D1: CATEGORY
D2: GROCERIES

Sheet Sep - 2026 (CC)
A1: DATE | B1: ITEM | C1: AMOUNT | D1: CATEGORY
D2: GROCERIES

Sheet Oct - 2026 (CC)
A1: DATE | B1: ITEM | C1: AMOUNT | D1: CATEGORY
D2: GROCERIES

Sheet Nov - 2026 (CC)
A1: DATE | B1: ITEM | C1: AMOUNT | D1: CATEGORY
D2: GROCERIES

Sheet Dec - 2026 (CC)
A1: DATE | B1: ITEM | C1: AMOUNT | D1: CATEGORY
D2: GROCERIES
